Workbook
Name fundos_xp: OFFSET('Fundos XP Locais'!$C$5,0,0,COUNTA('Fundos XP Locais'!$C:$C)-2,1)

Sheet Menu
B2: Menu
D5: Tabela contendo características gerais de todos os fundos da plataforma XP local.
D8: Fundos Internacionais distribuidos em nossa conta global, plataforma Digital.
D11: Fundos da nossa franquia alternativos, incluindo Venture Capital, Private Equity, Private Debt, Trend DI, Real Assets e Private Debt.
D14: Fundos da nossa franquia cetipados, incluindo Imobiliário, Agronegócio, Infraestrutura, Hedge Fund, Special Situations e Private Debt.
D17: Fundos da nossa franquia PR+, incluindo Venture Capital, Private Equity, Private Debt, Trend DI, Real Assets e Private Debt.
D20: Aque é possível encontrar uma descrição de o que seria cada coluna das abas "Fundos Alternativos", "Fundos Cetipados" e "Fundos PR+".
D23: Comentários do gestor sobre atribuição de performance e cenário, além do posicionamento do fundo.
D26: Comparador de caracacterísticas gerais e performance dos diferentes fundos da plataforma
D29: Simulador da receita de taxa de administração e taxa de performance, com a distribuição de diferentes fundos da plataforma
D31: Tabela contendo características gerais dos fundos da indústria
D34: Descrição explicativa de o que seria cada classificação XP feita para os fundos.

Sheet Fundos XP Locais
B1: 1 | C1: 2 | D1: 3 | E1: 4 | F1: 5 | G1: 6 | H1: 7 | I1: 8 | J1: 9 | K1: 10 | L1: 11 | M1: 12 | N1: 13 | O1: 14 | P1: 15 | Q1: 16 | R1: 17 | S1: 18 | T1: 19 | U1: 20 | V1: 21 | W1: 22 | X1: 23 | Y1: 24 | Z1: 25 | AA1: 26 | AB1: 27 | AC1: 28 | AD1: 29 | AE1: 30 | AF1: 31 | AG1: 32 | AH1: 33 | AI1: 34 | AJ1: 35 | AK1: 36 | AL1: 37 | AM1: 38 | AN1: 39 | AO1: 40 | AP1: 41 | AQ1: 42 | AR1: 43 | AS1: 44 | AT1: 45 | AU1: 46 | AV1: 47 | AW1: 48 | AX1: 49 | AY1: 50 | AZ1: 51 | BA1: 52 | BB1: 53 | BC1: 54 | BD1: 55 | BE1: 56 | BF1: 57 | BG1: 58 | BH1: 59 | BI1: 60 | BJ1: 61 | BK1: 62 | BL1: 63 | BM1: 64 | BN1: 65 | BO1: 66 | BP1: 67 | BQ1: 68 | BR1: 69 | BS1: 70 | BT1: 71 | BU1: 72 | BV1: 73 | BW1: 74 | BX1: 75 | BY1: 76 | BZ1: 77 | CA1: 78 | CB1: 79 | CC1: 80 | CD1: 81 | CE1: 82 | CF1: 83 | CG1: 84 | CH1: 85 | CI1: 86 | CJ1: 87 | CK1: 88 | CL1: 89 | CM1: 90 | CN1: 91 | CO1: 92 | CP1: 93 | CQ1: 94 | CR1: 95 | CS1: 96 | CT1: 97 | CU1: 98 | CV1: 99 | CW1: 100 | CX1: 101
B2: XP GUIA DE FUNDOS - Data base 30/04/2026
M3: Classificação | W3: Aplicação | X3: Resgate | AD3: Taxa de Administração | AM3: Rentabilidade Absoluta | AX3: Rentabilidade % CDI | BI3: Rentabilidade CDI +/- | BT3: Indicadores Técnicos | CH3: % Comissão Escritórios** | CJ3: "Margem"
B4: CNPJ | C4: Fundo | D4: Risco XP | E4: Top Fundos | F4: Classificação Morningstar | G4: Gestor | H4: Administrador | I4: Custodiante | J4: Auditor | K4: Disponibilidade | L4: Público | M4: CVM | N4: Anbima | O4: Classificação XP | P4: Tributação | Q4: Aplicação Inicial | R4: Status | S4: Envio de Cota Horário Médio | T4: Movimentação mínima | U4: Saldo de Permanencia | V4: Tipo de Cota | W4: Cotização | X4: Cotização | Y4: Liquidação | Z4: Liquidez total (Cotização + Liquidação) em número (aproximação para filtros) | AA4: Resgate Antecipado | AB4: Taxa de Saída Antecipada | AC4: Fundo Master | AD4: Taxa de Administração | AE4: Taxa de Administração da estrutura (Master + Feeder) | AF4: Taxa de Administração Máxima | AG4: Taxa de Performance (% sobre o que exceder o indexador) | AH4: Período de Pagamento Taxa de Performance | AI4: Período de Apuração Taxa de Performance | AJ4: Benchmark | AK4: Data de Início | AL4: Página do Fundo Plataforma XP | AM4: Mês | AN4: Ano | AO4: 12 Meses | AP4: 24 Meses (Anualizado) | AQ4: 36 Meses (Anualizado) | AR4: 2024 | AS4: 2023 | AT4: 2022 | AU4: 2021 | AV4: 2020 | AW4: Desde Início (Anualizado) | AX4: Mês | AY4: Ano | AZ4: 12 Meses | BA4: 24 Meses | BB4: 36 Meses | BC4: 2024 | BD4: 2023 | BE4: 2022 | BF4: 2021 | BG4: 2020 | BH4: Desde Início | BI4: Mês | BJ4: Ano | BK4: 12 Meses | BL4: 24 Meses (Anualizado) | BM4: 36 Meses (Anualizado) | BN4: 2024 | BO4: 2023 | BP4: 2022 | BQ4: 2021 | BR4: 2020 | BS4: Desde Início (Anualizado) | BT4: Volatilidade 12 meses | BU4: Volatilidade desde início | BV4: Sharpe 12 meses | BW4: Sharpe desde início | BX4: Máx Drawdown 12 meses | BY4: Máx Drawdown desde início | BZ4: Beta (Ibovespa) | CA4: Correlação 12M Ibovespa | CB4: Correlação 12M Dólar | CC4: Correlação 12M IRF-M | CD4: Correlação 12M IMA-B | CE4: Correlação 12M S&P | CF4: Correlação 12M IHFA | CG4: Cota Fechamento | CH4: Taxa de Administração | CI4: Taxa de Performance | CJ4: Taxa de Administração x Comissão | CK4: Taxa de Performance x Comissão*** | CL4: Margem Total (Margem Taxa Adm + Margem Taxa Perf) | CM4: PL (em milhares) | CN4: PL Médio (12 Meses - em milhares) | CO4: Captação Líquida (6 meses - em milhares) | CP4: % em Debêntures | CQ4: % em Títulos de Instituições Financeiras | CR4: % em Estruturados | CS4: % Investimentos no exterior | CT4: Enquadrado 3792 | CU4: Enquadrado 3922 | CV4: ISIN | CW4: ESG | CX4: Janela de Movimentação
B5: 9599346000122 | C5: 4UM Marlim Dividendos FIF CIA RL | D5: 27 | F5: «««« | G5: 4UM Investimentos | H5: BEM DTVM | I5: Banco Bradesco | J5: PriceWaterhouseCoopers | K5: Intranet | L5: Investidores em geral | M5: Ações | N5: Ações Dividendos | O5: Renda Variável Dividendos | P5: Renda Variavel | Q5: 500 | R5: ABERTO | S5: - | T5: 100 | U5: 500 | V5: Fechamento | W5: D+1 (útil) | X5: D+1 (útil) | Y5: D+3 (útil) | Z5: 4 | AA5: - | AB5: - | AC5: - | AD5: 0.02 | AE5: - | AF5: 0.02 | AG5: 0.2 | AH5: Junho / Dezembro | AI5: Maio / Novembro | AJ5: Ibovespa | AK5: 39629 | AL5: https://www.xpi.com.br/investimentos/fundos-de-investimento/lista/#/detalhes/b11fe7a5-44a7-488f-9c10-2cff35186866 | AM5: -0.0084006757 | AN5: 0.11285761 | AO5: 0.29160273 | AP5: 0.17381359 | AQ5: 0.18707523 | AR5: -0.087758255 | AS5: 0.26069811 | AT5: 0.043907817 | AU5: - | AV5: - | AW5: 0.10335676 | AX5: - | AY5: 2.4857217 | AZ5: 1.9666357 | BA5: 1.3482149 | BB5: 1.5326185 | BC5: - | BD5: 1.9980787 | BE5: 0.35486789 | BF5: - | BG5: - | BH5: 1.0831707 | BI5: -0.019310057 | BJ5: 0.067455258 | BK5: 0.14332783 | BL5: 0.039765666 | BM5: 0.057940389 | BN5: -0.19649798 | BO5: 0.13022372 | BP5: -0.079822219 | BQ5: - | BR5: - | BS5: 0.007244887 | BT5: 0.15042098 | BU5: 0.16505198 | BV5: 0.85756606 | BW5: 0.10539394 | BX5: -0.086724289 | BY5: -0.43109156 | BZ5: 0.53800416 | CA5: 0.96599763 | CB5: -0.45689983 | CC5: 0.64035535 | CD5: 0.52624838 | CE5: 0.075749626 | CF5: 0.75027795 | CG5: 5.7486298 | CH5: 0.3 | CI5: 0.15 | CJ5: 0.006 | CK5: - | CL5: 0.006 | CM5: 3.9450161e+08 | CN5: 3.8356248e+08 | CO5: -8663162.9 | CP5: - | CQ5: - | CR5: - | CS5: - | CT5: - | CU5: - | CV5: BRMRL2CTF002 | CW5: - | CX5: 25569.605
B6: 57832914000136 | C6: A1 CP High Grade FIF CIC RF CP RL | D6: 11 | G6: Asset1 Investimentos | H6: Intrag DTVM | I6: Itaú Unibanco | J6: PriceWaterhouseCoopers | K6: Geral | L6: Investidores em geral | M6: Renda Fixa | N6: Renda Fixa Duração Livre Crédito Livre | O6: Crédito Liquidez | P6: Longo Prazo | Q6: 1000 | R6: ABERTO | S6: - | T6: 1000 | U6: 1000 | V6: Fechamento | W6: D+0 | X6: D+0 | Y6: D+1 (útil) | Z6: 1 | AA6: - | AB6: - | AC6: A1 HIGH GRADE PÓS FIXADO FEEDER 2 RESP LIMITADA FIF CIC RENDA FIXA CRÉDITO PRIVADO | AD6: 0.005 | AE6: 0.105 | AF6: 0.006 | AG6: - | AH6: - | AI6: - | AJ6: CDI | AK6: 45625 | AL6: https://www.xpi.com.br/investimentos/fundos-de-investimento/lista/#/detalhes/0adbff9b-6e7c-4515-8826-d9a6e6c43893 | AM6: 0.010723758 | AN6: 0.045660662 | AO6: 0.15599284 | AP6: - | AQ6: - | AR6: - | AS6: - | AT6: - | AU6: - | AV6: - | AW6: 0.15352629 | AX6: 0.98298494 | AY6: 1.0056894 | AZ6: 1.0520515 | BA6: - | BB6: - | BC6: - | BD6: - | BE6: - | BF6: - | BG6: - | BH6: 1.0771725 | BI6: -0.00018562377 | BJ6: 0.0002583099 | BK6: 0.0077179371 | BL6: - | BM6: - | BN6: - | BO6: - | BP6: - | BQ6: - | BR6: - | BS6: 0.0096270606 | BT6: 0.0016027736 | BU6: 0.0026532838 | BV6: 4.1826778 | BW6: 3.5213098 | BX6: - | BY6: -0.0011436232 | BZ6: 0.0011677381 | CA6: 0.041200549 | CB6: 0.0050054695 | CC6: 0.049607247 | CD6: 0.017265598 | CE6: 0.051436676 | CF6: 0.040127344 | CG6: 1.2218686 | CH6: 0.22 | CI6: - | CJ6: 0.0011 | CK6: - | CL6: 0.0011 | CM6: 1.1502631e+09 | CN6: 5.9815283e+08 | CO6: 8.8855885e+08 | CP6: - | CQ6: - | CR6: - | CS6: - | CT6: - | CU6: - | CV6: BR0MD5CTF000 | CW6: - | CX6: 25569.626
B7: 38452175000102 | C7: A1 Hedge Advisory FIC FIM | D7: 13 | G7: Asset1 Investimentos | H7: XP Investimentos | I7: Banco Bradesco | J7: KPMG | K7: Geral | L7: Investidores em geral | M7: Multimercado | N7: Multimercados Livre | O7: Macro Alta Vol | P7: Longo Prazo: Haverá cobrança de IR no último dia útil dos meses de maio e novembro de cada ano sob a alíquota de 15% (“come-cotas”), ou no resgate, se ocorrido em data anterior, seguindo tabela regressiva partindo de 22,5% para intervalo entre aplicação e resgate menor do que 6 meses à 15% se o intervalo entre aplicação e resgate for maior do que 2 anos._x000D_ | Q7: 5000 | R7: ABERTO | S7: - | T7: 1000 | U7: 5000 | V7: Fechamento | W7: D+1 (útil) | X7: D+30 (corridos) | Y7: D+1 (útil) | Z7: 31 | AA7: - | AB7: - | AC7: A1 HEDGE ADVISORY FIC MULTIMERCADO | AD7: 0.02 | AE7: 0.12 | AF7: 0.021 | AG7: 0.2 | AH7: Maio / Novembro | AI7: Abril / Outubro | AJ7: CDI | AK7: 44113 | AL7: https://www.xpi.com.br/investimentos/fundos-de-investimento/lista/#/detalhes/df6d36ef-06c6-445e-9c67-f77ad0c79157 | AM7: 0.016625283 | AN7: 0.041471468 | AO7: 0.10043334 | AP7: 0.14486541 | AQ7: 0.098774291 | AR7: 0.077484659 | AS7: 0.080454883 | AT7: -0.013347758 | AU7: - | AV7: - | AW7: 0.05446783 | AX7: 1.5239436 | AY7: 0.91342113 | AZ7: 0.67734546 | BA7: 1.1087097 | BB7: 0.74392365 | BC7: 0.71256991 | BD7: 0.61663351 | BE7: - | BF7: - | BG7: - | BH7: 0.44559858 | BI7: 0.005715901 | BJ7: -0.0039308842 | BK7: -0.047841572 | BL7: 0.012562688 | BM7: -0.030015215 | BN7: -0.03125507 | BO7: -0.050019511 | BP7: -0.13707779 | BQ7: - | BR7: - | BS7: -0.060386064 | BT7: 0.055295734 | BU7: 0.04564062 | BV7: -0.74251563 | BW7: -1.066462 | BX7: -0.023904051 | BY7: -0.07357298 | BZ7: 0.03972513 | CA7: 0.37368354 | CB7: -0.24655291 | CC7: 0.59007014 | CD7: 0.3979232 | CE7: 0.0071997882 | CF7: 0.54502679 | CG7: 1.3406739 | CH7: 0.2 | CI7: 0.1 | CJ7: 0.004 | CK7: - | CL7: 0.004 | CM7: 5071423.8 | CN7: 5051823.5 | CO7: -3592.7 | CP7: - | CQ7: - | CR7: - | CS7: - | CT7: - | CU7: - | CV7: BR05FVCTF004 | CW7: - | CX7: 25569.626
B8: 29813769000100 | C8: Absolute Alpha Global Advisory FIC de FIF Multimercado RL | D8: 13 | F8: ««« | G8: Absolute Investimentos | H8: BNY Mellon Serviços Financeiros | I8: BNY Mellon Banco | J8: Deloitte Touche Tohmatsu | K8: Geral | L8: Investidores em geral | M8: Multimercado | N8: Multimercados Estratégia Específica | O8: Multiestratégia | P8: Longo Prazo - Alíquota regressiva de IR de 22,5% a 15,0% incidida sobre o lucro obtido no momento do resgate. | Q8: 500 | R8: ABERTO | S8: - | T8: 100 | U8: 500 | V8: Fechamento | W8: D+0 | X8: D+17 (corridos) | Y8: D+1 (útil) | Z8: 18 | AA8: Sim | AB8: 0.05 | AC8: ABSOLUTE ALPHA GLOBAL ADVISORY RESP LIMITADA FIF CIC MULTIMERCADO | AD8: 0.019 | AE8: 0.119 | AF8: 0.025 | AG8: 0.2 | AH8: Janeiro / Julho | AI8: Junho | AJ8: CDI | AK8: 43643 | AL8: https://www.xpi.com.br/investimentos/fundos-de-investimento/lista/#/detalhes/588ae6d7-d7c7-4816-a791-fc175e63b863 | AM8: 0.013556663 | AN8: 0.054636339 | AO8: 0.17691959 | AP8: 0.14860262 | AQ8: 0.13033214 | AR8: 0.094370117 | AS8: 0.10553207 | AT8: 0.11031521 | AU8: - | AV8: - | AW8: 0.094675011 | AX8: 1.242661 | AY8: 1.2033812 | AZ8: 1.1931863 | BA8: 1.1392936 | BB8: 1.0118593 | BC8: 0.86785316 | BD8: 0.80883355 | BE8: 0.89157987 | BF8: - | BG8: - | BH8: 0.99591635 | BI8: 0.0026472817 | BJ8: 0.0092339868 | BK8: 0.028644686 | BL8: 0.016072251 | BM8: 0.0013532297 | BN8: -0.014369611 | BO8: -0.024942327 | BP8: -0.013414826 | BQ8: - | BR8: - | BS8: -0.00035450445 | BT8: 0.01906009 | BU8: 0.016700956 | BV8: 1.3029939 | BW8: -0.0084496382 | BX8: -0.0029350231 | BY8: -0.010985557 | BZ8: 0.020073714 | CA8: 0.1282095 | CB8: -0.085371103 | CC8: 0.11409053 | CD8: 0.1247656 | CE8: 0.1314564 | CF8: 0.16710669 | CG8: 1.8534514 | CH8: 0.24 | CI8: 0.15 | CJ8: 0.00456 | CK8: 0.0007483753 | CL8: 0.0053083753 | CM8: 78525437 | CN8: 71616064 | CO8: 3922529 | CP8: - | CQ8: - | CR8: - | CS8: - | CT8: - | CU8: - | CV8: BR01VGCTF001 | CW8: - | CX8: 25569.626
B9: 35617938000130 | C9: Absolute Alpha Marb Advisory FIC de FIF Multimercado RL | D9: 13 | G9: Absolute Investimentos | H9: BNY Mellon Serviços Financeiros | I9: BNY Mellon Banco | J9: Deloitte Touche Tohmatsu | K9: Geral | L9: Investidores qualificados | M9: Multimercado | N9: Multimercados Estratégia Específica | O9: Internacional Multimercado Hedgeado | P9: Renda Variável | Q9: 500 | R9: ABERTO | S9: - | T9: 100 | U9: 100 | V9: Fechamento | W9: D+0 | X9: D+17 (corridos) | Y9: D+1 (útil) | Z9: 18 | AA9: Sim | AB9: 0.05 | AC9: ABSOLUTE ALPHA MARB ADVISORY RESP LIMITADA FIF CIC MULTIMERCADO | AD9: 0.019 | AE9: 0.119 | AF9: 0.025 | AG9: 0.2 | AH9: Janeiro / Julho | AI9: Junho | AJ9: CDI | AK9: 43826 | AL9: https://www.xpi.com.br/investimentos/fundos-de-investimento/lista/#/detalhes/1f560d4a-7821-4d7c-863c-1241e3dc34aa | AM9: 0.010260181 | AN9: 0.048890008 | AO9: 0.1917215 | AP9: 0.16598451 | AQ9: 0.13196123 | AR9: 0.089496743 | AS9: 0.083924701 | AT9: 0.11367809 | AU9: - | AV9: - | AW9: 0.10308012 | AX9: 0.94049157 | AY9: 1.0768166 | AZ9: 1.2930138 | BA9: 1.2828503 | BB9: 1.0261047 | BC9: 0.82303629 | BD9: 0.64322737 | BE9: 0.91875909 | BF9: - | BG9: - | BH9: 1.0628238 | BI9: -0.00064920019 | BJ9: 0.0034876554 | BK9: 0.043446588 | BL9: 0.032404505 | BM9: 0.0029746259 | BN9: -0.019242986 | BO9: -0.046549692 | BP9: -0.010051941 | BQ9: - | BR9: - | BS9: 0.0055543927 | BT9: 0.026932105 | BU9: 0.046769416 | BV9: 1.3931937 | BW9: 0.11688901 | BX9: -0.0063213971 | BY9: -0.04965034 | BZ9: 0.046310218 | CA9: 0.18974423 | CB9: -0.093167161 | CC9: 0.19723617 | CD9: 0.18071179 | CE9: 0.2344724 | CF9: 0.25437621 | CG9: 1.8570785 | CH9: 0.25 | CI9: 0.1 | CJ9: 0.00475 | CK9: 0.00075672799 | CL9: 0.005506728 | CM9: 76282294 | CN9: 39060432 | CO9: 47084385 | CP9: - | CQ9: - | CR9: - | CS9: - | CT9: - | CU9: - | CV9: BR03JGCTF002 | CW9: - | CX9: 25569.626
B10: 48096589000108 | C10: Absolute Atenas Advisory FIC FIF RF CP RL | D10: 2 | G10: Absolute Investimentos | H10: BTG Pactual Serviços Financeiros | I10: Banco BTG Pactual | J10: KPMG | K10: Geral | L10: Investidores em geral | M10: Renda Fixa | N10: Renda Fixa Duração Baixa Grau de Investimento | O10: Crédito Liquidez | P10: Longo Prazo | Q10: 500 | R10: ABERTO | S10: - | T10: 100 | U10: 500 | V10: Fechamento | W10: D+0 | X10: D+0 | Y10: D+1 (útil) | Z10: 1 | AA10: - | AB10: - | AC10: ABSOLUTE ATENAS ADVISORY FIF CIC RENDA FIXA | AD10: 0.0038 | AE10: 0.1038 | AF10: 0.005 | AG10: - | AH10: - | AI10: - | AJ10: CDI | AK10: 44862 | AL10: https://www.xpi.com.br/investimentos/fundos-de-investimento/lista/#/detalhes/baca96c2-efdc-4475-9709-ccafcef26bf2 | AM10: 0.0099284704 | AN10: 0.040944578 | AO10: 0.14428765 | AP10: 0.13305777 | AQ10: 0.13655073 | AR10: 0.12135209 | AS10: 0.13834874 | AT10: - | AU10: - | AV10: - | AW10: 0.13675077 | AX10: 0.91008554 | AY10: 0.90181623 | AZ10: 0.97310903 | BA10: 1.0127353 | BB10: 1.0664582 | BC10: 1.1159867 | BD10: 1.0603517 | BE10: - | BF10: - | BG10: - | BH10: 1.060327 | BI10: -0.00098091109 | BJ10: -0.0044577743 | BK10: -0.0039872566 | BL10: 0.001478912 | BM10: 0.0075435113 | BN10: 0.012612363 | BO10: 0.00787435 | BP10: - | BQ10: - | BR10: - | BS10: 0.0068915821 | BT10: 0.0024692505 | BU10: 0.0026418575 | BV10: -1.4082336 | BW10: 2.2517581 | BX10: -0.0014617527 | BY10: -0.001863807 | BZ10: -0.00053221391 | CA10: -0.0506346 | CB10: 0.019724236 | CC10: -0.027907364 | CD10: -0.016904922 | CE10: 0.079036145 | CF10: -0.024603488 | CG10: 1.5629491 | CH10: 0.3 | CI10: - | CJ10: 0.00114 | CK10: - | CL10: 0.00114 | CM10: 7.4588501e+08 | CN10: 9.397011e+08 | CO10: -5.282368e+08 | CP10: - | CQ10: - | CR10: - | CS10: - | CT10: - | CU10: - | CV10: BR0DVYCTF005 | CW10: - | CX10: 25569.626
B11: 48122126000165 | C11: Absolute Creta Advisory FIF FIRF | D11: 2 | G11: Absolute Investimentos | H11: BTG Pactual Serviços Financeiros | I11: Banco BTG Pactual | J11: KPMG | K11: Geral | L11: Investidores em geral | M11: Renda Fixa | N11: Renda Fixa Duração Baixa Grau de Investimento | O11: Crédito High Grade | P11: Longo Prazo | Q11: 500 | R11: FECHADO | S11: - | T11: 100 | U11: 500 | V11: Fechamento | W11: D+0 | X11: D+30 (corridos) | Y11: D+1 (útil) | Z11: 31 | AA11: - | AB11: - | AC11: ABSOLUTE CRETA ADVISORY FIF CIC RENDA FIXA | AD11: 0.0058 | AE11: 0.1058 | AF11: 0.007 | AG11: - | AH11: - | AI11: - | AJ11: CDI | AK11: 44862 | AL11: https://www.xpi.com.br/investimentos/fundos-de-investimento/lista/#/detalhes/9882ecb0-c421-47a2-99fb-f0b74d7f7b78 | AM11: 0.0083405799 | AN11: 0.033699826 | AO11: 0.13657197 | AP11: 0.13275738 | AQ11: 0.14080476 | AR11: 0.13047871 | AS11: 0.14185645 | AT11: - | AU11: - | AV11: - | AW11: 0.13996014 | AX11: 0.7645328 | AY11: 0.74224846 | AZ11: 0.92107268 | BA11: 1.0103066 | BB11: 1.1041541 | BC11: 1.1999176 | BD11: 1.0872359 | BE11: - | BF11: - | BG11: - | BH11: 1.0893864 | BI11: -0.0025688015 | BJ11: -0.011702526 | BK11: -0.011702942 | BL11: 0.0011970279 | BM11: 0.011779823 | BN11: 0.021738984 | BO11: 0.011382055 | BP11: - | BQ11: - | BR11: - | BS11: 0.010176573 | BT11: 0.0053903065 | BU11: 0.0048349208 | BV11: -1.8987752 | BW11: 1.8154965 | BX11: -0.0036213204 | BY11: -0.0036420568 | BZ11: -0.00022159028 | CA11: -0.039824209 | CB11: 0.0083930284 | CC11: -0.0035472962 | CD11: -0.0096471518 | CE11: 0.089192243 | CF11: -0.0096814975 | CG11: 1.5783773 | CH11: 0.3 | CI11: - | CJ11: 0.00174 | CK11: - | CL11: 0.00174 | CM11: 1.7868424e+09 | CN11: 2.0350439e+09 | CO11: -4.4727944e+08 | CP11: - | CQ11: - | CR11: - | CS11: - | CT11: - | CU11: - | CV11: BR0DWGCTF000 | CW11: - | CX11: 25569.626
B12: 18860059000115 | C12: Absolute Hedge FIC de FIF Multimercado RL | D12: 13 | F12: «««« | G12: Absolute Investimentos | H12: BTG Pactual Serviços Financeiros | I12: Banco BTG Pactual | J12: KPMG | K12: Geral | L12: Investidores em geral | M12: Multimercado | N12: Multimercados Macro | O12: Macro Média Vol | P12: Longo Prazo - Alíquota regressiva de IR de 22,5% a 15,0% incidida sobre o lucro obtido no momento do resgate. | Q12: 500 | R12: ABERTO | S12: - | T12: 500 | U12: 500 | V12: Fechamento | W12: D+0 | X12: D+4 (corridos) | Y12: D+1 (útil) | Z12: 5 | AA12: - | AB12: - | AC12: ABSOLUTE HEDGE FIF CIC MULTIMERCADO | AD12: 0.019 | AE12: 0.119 | AF12: 0.025 | AG12: 0.2 | AH12: Janeiro / Julho | AI12: Junho | AJ12: CDI | AK12: 41547 | AL12: https://www.xpi.com.br/investimentos/fundos-de-investimento/lista/#/detalhes/313c7545-362f-4755-a456-9b1166649079 | AM12: 0.014760901 | AN12: 0.042951149 | AO12: 0.10868789 | AP12: 0.11079765 | AQ12: 0.11523619 | AR12: 0.089877753 | AS12: 0.12721061 | AT12: 0.16584597 | AU12: - | AV12: - | AW12: 0.10815167 | AX12: 1.3530465 | AY12: 0.94601153 | AZ12: 0.73301605 | BA12: 0.83450752 | BB12: 0.88179679 | BC12: 0.82654017 | BD12: 0.97498528 | BE12: 1.3403857 | BF12: - | BG12: - | BH12: 1.1515488 | BI12: 0.0038515195 | BJ12: -0.0024512035 | BK12: -0.03958702 | BL12: -0.019397099 | BM12: -0.013661822 | BN12: -0.018861975 | BO12: -0.0032637801 | BP12: 0.042115936 | BQ12: - | BR12: - | BS12: 0.013011236 | BT12: 0.025115028 | BU12: 0.029547167 | BV12: -1.3850777 | BW12: 0.28523815 | BX12: -0.0090735864 | BY12: -0.046284828 | BZ12: 0.041335455 | CA12: 0.62072976 | CB12: -0.53332857 | CC12: 0.59687909 | CD12: 0.49472878 | CE12: 0.052228804 | CF12: 0.82973216 | CG12: 3.6216455 | CH12: 0.27 | CI12: 0.15 | CJ12: 0.00513 | CK12: - | CL12: 0.00513 | CM12: 3.4455302e+08 | CN12: 3.7093944e+08 | CO12: -80664151 | CP12: - | CQ12: - | CR12: - | CS12: - | CT12: - | CU12: - | CV12: BRABH1CTF002 | CW12: - | CX12: 25569.626
B13: 57027498000101 | C13: Absolute Hidra CDI Plus Advisory FIC FI Infra RF CP RL | D13: 12 | G13: ABSOLUTE DHAMA GESTÃO DE INVESTIMENTOS LTDA | H13: BTG Pactual Serviços Financeiros | I13: Banco BTG Pactual | J13: KPMG | K13: Geral | L13: Investidores em geral | M13: Renda Fixa | N13: Renda Fixa Duração Livre Crédito Livre | O13: Debêntures Incentivadas Hedgeado | P13: Debêntures incentivadas | Q13: 500 | R13: ABERTO | S13: - | T13: 100 | U13: 100 | V13: Fechamento | W13: D+0 | X13: D+30 (corridos) | Y13: D+1 (útil) | Z13: 31 | AA13: - | AB13: - | AC13: ABSOLUTE HIDRA CDI PLUS ADVISORY FIC INFRA RENDA FIXA | AD13: 0.0068 | AE13: 0.1068 | AF13: 0.008 | AG13: 0.2 | AH13: Dezembro / Junho | AI13: Novembro / Maio | AJ13: CDI | AK13: 45735 | AL13: https://www.xpi.com.br/investimentos/fundos-de-investimento/lista/#/detalhes/c203a0e2-29bd-4189-912b-cdfb7a61aaf5 | AM13: -0.00090936574 | AN13: 0.02312087 | AO13: 0.12682825 | AP13: - | AQ13: - | AR13: - | AS13: - | AT13: - | AU13: - | AV13: - | AW13: 0.12694635 | AX13: - | AY13: 0.50924388 | AZ13: 0.85535884 | BA13: - | BB13: - | BC13: - | BD13: - | BE13: - | BF13: - | BG13: - | BH13: 0.85940091 | BI13: -0.011818747 | BJ13: -0.022281482 | BK13: -0.021446655 | BL13: - | BM13: - | BN13: - | BO13: - | BP13: - | BQ13: - | BR13: - | BS13: -0.018095597 | BT13: 0.0094098631 | BU13: 0.0094071288 | BV13: -1.9999716 | BW13: -1.9231268 | BX13: -0.0053445715 | BY13: -0.0053445715 | BZ13: -0.010401588 | CA13: -0.189304 | CB13: 0.036133092 | CC13: -0.32753858 | CD13: -0.37038677 | CE13: -0.11468103 | CF13: -0.25819929 | CG13: 1.142011 | CH13: 0.24 | CI13: 0.15 | CJ13: 0.001632 | CK13: - | CL13: 0.001632 | CM13: 5.9994398e+08 | CN13: 6.1757857e+08 | CO13: 32477930 | CP13: - | CQ13: - | CR13: - | CS13: - | CT13: - | CU13: - | CV13: BR0LJGCTF000 | CW13: - | CX13: 25569.626
B14: 51112363000150 | C14: Absolute Hidra IPCA FIC de FIF RF Investimento em Infra CP | D14: 12 | G14: ABSOLUTE DHAMA GESTÃO DE INVESTIMENTOS LTDA | H14: BTG Pactual Serviços Financeiros | I14: Banco BTG Pactual | J14: KPMG | K14: Geral | L14: Investidores em geral | M14: Renda Fixa | N14: Renda Fixa Duração Livre Crédito Livre | O14: Debêntures Incentivadas Não Hedgeado | P14: Debêntures Incentivadas | Q14: 500 | R14: ABERTO | S14: - | T14: 100 | U14: 500 | V14: Fechamento | W14: D+0 | X14: D+30 (corridos) | Y14: D+1 (útil) | Z14: 31 | AA14: - | AB14: - | AC14: ABSOLUTE HIDRA IPCA FIC INFRA RENDA FIXA | AD14: 0.0068 | AE14: 0.1068 | AF14: 0.008 | AG14: 0.2 | AH14: - | AI14: - | AJ14: IMA-B 5 | AK14: 45105 | AL14: https://www.xpi.com.br/investimentos/fundos-de-investimento/lista/#/detalhes/a61efa6a-a0aa-4a16-a4e0-cccd5f92302a | AM14: -0.0037947649 | AN14: 0.024636642 | AO14: 0.095214659 | AP14: 0.095863714 | AQ14: - | AR14: 0.089215754 | AS14: - | AT14: - | AU14: - | AV14: - | AW14: 0.10860031 | AX14: - | AY14: 0.54262921 | AZ14: 0.64214951 | BA14: 0.71691948 | BB14: - | BC14: 0.82045224 | BD14: - | BE14: - | BF14: - | BG14: - | BH14: 0.83038862 | BI14: -0.014704146 | BJ14: -0.02076571 | BK14: -0.053060248 | BL14: -0.033387933 | BM14: - | BN14: -0.019523974 | BO14: - | BP14: - | BQ14: - | BR14: - | BS14: -0.019616683 | BT14: 0.016664722 | BU14: 0.019820899 | BV14: -2.8319465 | BW14: -0.88901406 | BX14: -0.0077784872 | BY14: -0.014611564 | BZ14: 0.051701136 | CA14: 0.40713154 | CB14: -0.31970613 | CC14: 0.52151531 | CD14: 0.60094846 | CE14: -0.09620398 | CF14: 0.44834028 | CG14: 1.3387048 | CH14: 0.24 | CI14: 0.15 | CJ14: 0.001632 | CK14: - | CL14: 0.001632 | CM14: 2.556526e+08 | CN14: 2.4323291e+08 | CO14: 12365234 | CP14: - | CQ14: - | CR14: - | CS14: - | CT14: - | CU14: - | CV14: BR0FWYCTF008 | CW14: - | CX14: 25569.605
B15: 32892827000143 | C15: Absolute Pace Long Biased Advisory FIC FIA | D15: 26 | F15: ««««« | G15: Absolute Investimentos | H15: BNY Mellon Serviços Financeiros | I15: BNY Mellon Banco | J15: Deloitte Touche Tohmatsu | K15: Geral | L15: Investidores qualificados | M15: Ações | N15: Ações Livre | O15: Renda Variável Long Biased | P15: Renda Variável - Alíquota de IR de 15% incidida sobre o lucro obtido no momento do resgate. | Q15: 500 | R15: FECHADO | S15: - | T15: 100 | U15: 100 | V15: Fechamento | W15: D+1 (útil) | X15: D+30 (corridos) | Y15: D+3 (útil) | Z15: 33 | AA15: Sim | AB15: 0.1 | AC15: ABSOLUTE PACE LONG BIASED ADVISORY FIF CIC AÇÕES | AD15: 0.019 | AE15: 0.119 | AF15: 0.022 | AG15: 0.2 | AH15: Janeiro / Julho | AI15: Junho | AJ15: - | AK15: 43643 | AL15: https://www.xpi.com.br/investimentos/fundos-de-investimento/lista/#/detalhes/26cc40f4-f74b-4648-91af-8069a4428d36 | AM15: 0.014986112 | AN15: 0.096777388 | AO15: 0.31900756 | AP15: 0.19569167 | AQ15: 0.23440183 | AR15: -0.046991314 | AS15: 0.27733871 | AT15: 0.1503283 | AU15: - | AV15: - | AW15: 0.18882912 | AX15: 1.3736904 | AY15: 2.1315501 | AZ15: 2.1514602 | BA15: 1.5331928 | BB15: 2.00681 | BC15: - | BD15: 2.1256179 | BE15: 1.2149702 | BF15: - | BG15: - | BH15: 2.6302932 | BI15: 0.0040767308 | BJ15: 0.051375036 | BK15: 0.17073265 | BL15: 0.060351861 | BM15: 0.10529933 | BN15: -0.15573104 | BO15: 0.14686431 | BP15: 0.026598265 | BQ15: - | BR15: - | BS15: 0.10919953 | BT15: 0.14840707 | BU15: 0.18559832 | BV15: 1.008833 | BW15: 0.53669998 | BX15: -0.067236009 | BY15: -0.4033713 | BZ15: 0.71925183 | CA15: 0.87341979 | CB15: -0.4810344 | CC15: 0.63573886 | CD15: 0.56229871 | CE15: 0.095517901 | CF15: 0.75106892 | CG15: 3.2540322 | CH15: 0.24 | CI15: 0.15 | CJ15: 0.00456 | CK15: - | CL15: 0.00456 | CM15: 7.3504333e+08 | CN15: 7.02772e+08 | CO15: 9864917.1 | CP15: - | CQ15: - | CR15: - | CS15: - | CT15: - | CU15: - | CV15: BR01VHCTF009 | CW15: - | CX15: 25569.626
B16: 28947266000165 | C16: Absolute Vertex Advisory FIC FIF Multimercado RL | D16: 13 | E16: Sim | F16: ««««« | G16: Absolute Investimentos | H16: BNY Mellon Serviços Financeiros | I16: BNY Mellon Banco | J16: Deloitte Touche Tohmatsu | K16: Geral | L16: Investidores em geral | M16: Multimercado | N16: Multimercados Macro | O16: Macro Alta Vol | P16: Longo Prazo - Alíquota regressiva de IR de 22,5% a 15,0% incidida sobre o lucro obtido no momento do resgate. | Q16: 500 | R16: ABERTO | S16: - | T16: 100 | U16: 100 | V16: Fechamento | W16: D+0 | X16: D+44 (corridos) | Y16: D+1 (útil) | Z16: 45 | AA16: Sim | AB16: 0.05 | AC16: ABSOLUTE VERTEX ADVISORY RESP LIMITADA FIF CIC MULTIMERCADO | AD16: 0.019 | AE16: 0.119 | AF16: 0.025 | AG16: 0.2 | AH16: Janeiro / Julho | AI16: Junho | AJ16: CDI | AK16: 43416 | AL16: https://www.xpi.com.br/investimentos/fundos-de-investimento/lista/#/detalhes/eaaccb10-fa3d-4e1b-8c85-1f30a3df17b2 | AM16: 0.019782088 | AN16: 0.046793581 | AO16: 0.092004177 | AP16: 0.11200284 | AQ16: 0.12244471 | AR16: 0.092206393 | AS16: 0.142031 | AT16: 0.22970151 | AU16: - | AV16: - | AW16: 0.11309996 | AX16: 1.8133098 | AY16: 1.0306422 | AZ16: 0.62049728 | BA16: 0.8440664 | BB16: 0.94346713 | BC16: 0.84795497 | BD16: 1.0885737 | BE16: 1.8564733 | BF16: - | BG16: - | BH16: 1.3113356 | BI16: 0.0088727066 | BJ16: 0.0013912291 | BK16: -0.056270731 | BL16: -0.018267511 | BM16: -0.0064941122 | BN16: -0.016533335 | BO16: 0.011556605 | BP16: 0.10597147 | BQ16: - | BR16: - | BS16: 0.02472 | BT16: 0.049834448 | BU16: 0.044780263 | BV16: -0.98389362 | BW16: 0.44204246 | BX16: -0.024261926 | BY16: -0.052435698 | BZ16: 0.086173083 | CA16: 0.62073321 | CB16: -0.52900794 | CC16: 0.60523281 | CD16: 0.50411139 | CE16: 0.059812842 | CF16: 0.83443992 | CG16: 2.2184605 | CH16: 0.25 | CI16: 0.15 | CJ16: 0.00475 | CK16: - | CL16: 0.00475 | CM16: 1.1437434e+09 | CN16: 1.2338967e+09 | CO16: -2.7242716e+08 | CP16: - | CQ16: - | CR16: - | CS16: - | CT16: - | CU16: - | CV16: BR00M8CTF005 | CW16: - | CX16: 25569.626
B17: 34258751000124 | C17: Absoluto Partners Advisory FIF em Cotas FIA RL | D17: 39 | F17: « | G17: Absoluto Partners Investimentos | H17: BTG Pactual Serviços Financeiros | I17: Banco BTG Pactual | J17: PriceWaterhouseCoopers | K17: Intranet | L17: Investidores qualificados | M17: Ações | N17: Ações Livre | O17: Renda Variável Long Only | P17: Renda Variável - Alíquota de IR de 15% incidida sobre o lucro obtido no momento do resgate. | Q17: 50000 | R17: FECHADO | S17: - | T17: 10000 | U17: 50000 | V17: Fechamento | W17: D+1 (útil) | X17: D+60 (corridos) | Y17: D+2 (útil) | Z17: 62 | AA17: - | AB17: - | AC17: ABSOLUTO PARTNERS ADVISORY FIF CIC AÇÕES | AD17: 0.0185 | AE17: 0.0585 | AF17: 0.0194 | AG17: 0.2 | AH17: - | AI17: - | AJ17: - | AK17: 43703 | AL17: https://www.xpi.com.br/investimentos/fundos-de-investimento/lista/#/detalhes/dc67fe3e-8fd3-436c-b956-5fe86e146109 | AM17: 0.015355349 | AN17: 0.088334691 | AO17: 0.38592236 | AP17: 0.21806237 | AQ17: 0.21997368 | AR17: -0.1966981 | AS17: 0.28471675 | AT17: -0.13546567 | AU17: - | AV17: - | AW17: 0.10596417 | AX17: 1.4075362 | AY17: 1.9455972 | AZ17: 2.6027489 | BA17: 1.7258679 | BB17: 1.8583087 | BC17: - | BD17: 2.1821657 | BE17: - | BF17: - | BG17: - | BH17: 1.138703 | BI17: 0.0044459673 | BJ17: 0.042932339 | BK17: 0.23764745 | BL17: 0.081424976 | BM17: 0.090846811 | BN17: -0.30543782 | BO17: 0.15424236 | BP17: -0.2591957 | BQ17: - | BR17: - | BS17: 0.011808419 | BT17: 0.19797096 | BU17: 0.25699972 | BV17: 1.0497584 | BW17: 0.16560777 | BX17: -0.099740541 | BY17: -0.47113188 | BZ17: 0.93780607 | CA17: 0.89842214 | CB17: -0.42101915 | CC17: 0.62843796 | CD17: 0.51135812 | CE17: 0.13207533 | CF17: 0.73790566 | CG17: 1.9547279 | CH17: 0.07 | CI17: - | CJ17: 0.001295 | CK17: - | CL17: 0.001295 | CM17: 1.2678276e+08 | CN17: 1.2720816e+08 | CO17: -14500730 | CP17: - | CQ17: - | CR17: - | CS17: - | CT17: - | CU17: - | CV17: BR02TYCTF006 | CW17: - | CX17: 25569.605
B18: 39992830000188 | C18: Ace Capital Absoluto FIC FIF FIA RL | D18: 26 | G18: ACE Capital | H18: BNY Mellon Serviços Financeiros | I18: BNY Mellon Banco | J18: KPMG | K18: Geral | L18: Investidores qualificados | M18: Ações | N18: Ações Livre | O18: Renda Variável Long Only | P18: Renda Variavel | Q18: 500 | R18: FECHADO | S18: - | T18: 100 | U18: 500 | V18: Fechamento | W18: D+1 (útil) | X18: D+30 (corridos) | Y18: D+2 (útil) | Z18: 32 | AA18: - | AB18: - | AC18: ACE CAPITAL ABSOLUTO RESP LIMITADA FIF CIC AÇÕES | AD18: 0.02 | AE18: 0.02 | AF18: 0.022 | AG18: 0.2 | AH18: Março / Setembro | AI18: Fevereiro / Agosto | AJ18: IMA-B | AK18: 44368 | AL18: https://www.xpi.com.br/investimentos/fundos-de-investimento/lista/#/detalhes/123ec1dc-9324-4ca4-bd21-f3d9f691dd56 | AM18: -0.017891035 | AN18: 0.051638794 | AO18: 0.27582182 | AP18: 0.15650734 | AQ18: 0.11697826 | AR18: -0.18508071 | AS18: 0.15833996 | AT18: 0.059472248 | AU18: - | AV18: - | AW18: 0.060816902 | AX18: - | AY18: 1.1373594 | AZ18: 1.8602057 | BA18: 1.2043113 | BB18: 0.89662783 | BC18: - | BD18: 1.2135711 | BE18: 0.48066137 | BF18: - | BG18: - | BH18: 0.4492834 | BI18: -0.028800417 | BJ18: 0.0062364414 | BK18: 0.12754692 | BL18: 0.023497777 | BM18: -0.011929977 | BN18: -0.29382043 | BO18: 0.027865564 | BP18: -0.064257787 | BQ18: - | BR18: - | BS18: -0.065659396 | BT18: 0.17392251 | BU18: 0.19242121 | BV18: 0.69300965 | BW18: -0.18930182 | BX18: -0.084191319 | BY18: -0.20902537 | BZ18: 0.84508966 | CA18: 0.91788566 | CB18: -0.45252067 | CC18: 0.66677169 | CD18: 0.53911882 | CE18: 0.13210993 | CF18: 0.78198555 | CG18: 133.11714 | CH18: 0.27 | CI18: 0.15 | CJ18: 0.0054 | CK18: 0.004067997 | CL18: 0.009467997 | CM18: 2976715.8 | CN18: 3244748.9 | CO18: -1870390.2 | CP18: - | CQ18: - | CR18: - | CS18: - | CT18: - | CU18: - | CV18: BR08IRCTF000 | CW18: - | CX18: 25569.626
B19: 7124064000143 | C19: Ace Capital Absoluto Institucional FIC de FIF em Ações RL | D19: 36 | G19: ACE Capital | H19: BNY Mellon Serviços Financeiros | I19: BNY Mellon Banco | J19: KPMG | K19: Geral | L19: Investidores em geral | M19: Ações | N19: Ações Livre | O19: Renda Variável Long Only | P19: Ações | Q19: 100 | R19: ABERTO | S19: - | T19: 100 | U19: 100 | V19: Fechamento | W19: D+1 (útil) | X19: D+1 (útil) | Y19: D+3 (útil) | Z19: 4 | AA19: - | AB19: - | AC19: ACE CAPITAL ABSOLUTO INSTITUCIONAL RESP LIMITADA FIF CIC AÇÕES | AD19: 0.02 | AE19: 0.02 | AF19: 0.025 | AG19: 0.2 | AH19: Julho / Janeiro | AI19: Junho | AJ19: Ibovespa | AK19: 38357 | AL19: https://www.xpi.com.br/investimentos/fundos-de-investimento/lista/#/detalhes/40b7ae9d-bd3a-4382-9268-305747654879 | AM19: -0.013499649 | AN19: 0.12251502 | AO19: 0.34137369 | AP19: 0.20543773 | AQ19: 0.21521198 | AR19: -0.058294428 | AS19: 0.1182861 | AT19: -0.089872024 | AU19: - | AV19: - | AW19: 0.13819048 | AX19: - | AY19: 2.698429 | AZ19: 2.3023025 | BA19: 1.616695 | BB19: 1.810063 | BC19: - | BD19: 0.90658477 | BE19: - | BF19: - | BG19: - | BH19: 1.9062248 | BI19: -0.024409031 | BJ19: 0.077112671 | BK19: 0.19309878 | BL19: 0.069529746 | BM19: 0.086079798 | BN19: -0.16703416 | BO19: -0.012188296 | BP19: -0.21360206 | BQ19: - | BR19: - | BS19: 0.061255479 | BT19: 0.16482922 | BU19: 0.23264445 | BV19: 1.0260828 | BW19: 0.23624467 | BX19: -0.080920805 | BY19: -0.60789348 | BZ19: 0.80954611 | CA19: 0.96765084 | CB19: -0.46902279 | CC19: 0.66206604 | CD19: 0.54138026 | CE19: 0.076024929 | CF19: 0.76470013 | CG19: 1561.9795 | CH19: 0.27 | CI19: 0.15 | CJ19: 0.0054 | CK19: - | CL19: 0.0054 | CM19: 67663262 | CN19: 61050824 | CO19: 14495360 | CP19: - | CQ19: - | CR19: - | CS19: - | CT19: - | CU19: - | CV19: BRGPFICTF005 | CW19: - | CX19: 25569.626
B20: 34774642000160 | C20: ACE Capital Advisory FIF CIC Multi RL | D20: 13 | F20: «««« | G20: ACE Capital | H20: Intrag DTVM | I20: Itaú Unibanco | J20: EY | K20: Geral | L20: Investidores em geral | M20: Multimercado | N20: Multimercados Macro | O20: Macro Média Vol | P20: Longo Prazo - Alíquota regressiva de IR de 22,5% a 15,0% incidida sobre o lucro obtido no momento do resgate. | Q20: 500 | R20: ABERTO | S20: - | T20: 100 | U20: 100 | V20: Fechamento | W20: D+0 | X20: D+30 (corridos) | Y20: D+1 (útil) | Z20: 31 | AA20: Sim | AB20: 0.1 | AC20: ACE CAPITAL ADVISORY RESP LIMITADA FIF CIC MULTIMERCADO | AD20: 0.0192 | AE20: 0.0992 | AF20: 0.022 | AG20: 0.2 | AH20: Junho / Dezembro | AI20: Maio / Novembro | AJ20: CDI | AK20: 43738 | AL20: https://www.xpi.com.br/investimentos/fundos-de-investimento/lista/#/detalhes/1a86ef5f-913f-4942-84f7-6441470f97eb | AM20: 0.015528487 | AN20: 0.022765384 | AO20: 0.12755327 | AP20: 0.13446759 | AQ20: 0.10021926 | AR20: 0.069253499 | AS20: 0.10875942 | AT20: 0.14848866 | AU20: - | AV20: - | AW20: 0.10440309 | AX20: 1.4234067 | AY20: 0.5014142 | AZ20: 0.86024851 | BA20: 1.0241423 | BB20: 0.75586186 | BC20: 0.63687394 | BD20: 0.83356909 | BE20: 1.200102 | BF20: - | BG20: - | BH20: 1.1077054 | BI20: 0.0046191055 | BJ20: -0.022636968 | BK20: -0.02072164 | BL20: 0.0028019367 | BM20: -0.028580637 | BN20: -0.039486229 | BO20: -0.021714972 | BP20: 0.024758626 | BQ20: - | BR20: - | BS20: 0.0092770359 | BT20: 0.042940252 | BU20: 0.042169674 | BV20: -0.40292243 | BW20: 0.19339105 | BX20: -0.032400966 | BY20: -0.046464961 | BZ20: 0.079572823 | CA20: 0.55369277 | CB20: -0.4121483 | CC20: 0.76899249 | CD20: 0.56099748 | CE20: 0.20370773 | CF20: 0.82340918 | CG20: 1.9174562 | CH20: 0.24 | CI20: 0.15 | CJ20: 0.004608 | CK20: - | CL20: 0.004608 | CM20: 1.7104482e+08 | CN20: 1.8141419e+08 | CO20: -20592864 | CP20: - | CQ20: - | CR20: - | CS20: - | CT20: - | CU20: - | CV20: BR02P7CTF002 | CW20: - | CX20: 25569.626
B21: 47612105000165 | C21: ACE Capital Multicenários FC FIF MULT - RL | D21: 16 | E21: Sim | G21: Ace Capital Saires Gestora de Recursos | H21: BNY Mellon Serviços Financeiros | I21: BNY Mellon Banco | J21: KPMG | K21: Geral | L21: Investidores em geral | M21: Multimercado | N21: Multimercados Trading | O21: Quantitativo | P21: Longo Prazo | Q21: 100 | R21: ABERTO | S21: - | T21: 100 | U21: 100 | V21: Fechamento | W21: D+0 | X21: D+15 (corridos) | Y21: D+2 (útil) | Z21: 17 | AA21: - | AB21: - | AC21: ACE CAPITAL MULTICENÁRIOS RESP LIMITADA FIF CIC MULTIMERCADO | AD21: 0.015 | AE21: 0.015 | AF21: 0.016 | AG21: 0.1 | AH21: Novembro / Maio | AI21: Outubro / Abril | AJ21: CDI | AK21: 44895 | AL21: https://www.xpi.com.br/investimentos/fundos-de-investimento/lista/#/detalhes/0f2d6d27-b25c-4925-ab83-32f2571b8734 | AM21: 0.032375997 | AN21: 0.070737502 | AO21: 0.33568023 | AP21: 0.28355074 | AQ21: 0.25720237 | AR21: 0.14999907 | AS21: 0.23491773 | AT21: - | AU21: - | AV21: - | AW21: 0.24409244 | AX21: 2.9677207 | AY21: 1.558014 | AZ21: 2.2639045 | BA21: 2.3104392 | BB21: 2.2486609 | BC21: 1.3794321 | BD21: 1.8004892 | BE21: - | BF21: - | BG21: - | BH21: 2.1405741 | BI21: 0.021466615 | BJ21: 0.02533515 | BK21: 0.18740533 | BL21: 0.14324496 | BM21: 0.12816284 | BN21: 0.041259338 | BO21: 0.10444334 | BP21: - | BQ21: - | BR21: - | BS21: 0.11674819 | BT21: 0.11675624 | BU21: 0.10665581 | BV21: 1.3543987 | BW21: 0.95699378 | BX21: -0.094676681 | BY21: -0.094676681 | BZ21: 0.29751904 | CA21: 0.41610856 | CB21: -0.37356871 | CC21: 0.40060716 | CD21: 0.28772724 | CE21: 0.13564782 | CF21: 0.60398275 | CG21: 2.1017173 | CH21: 0.3 | CI21: 0.15 | CJ21: 0.0045 | CK21: 0.0024480896 | CL21: 0.0069480896 | CM21: 4.1014899e+08 | CN21: 2.4175446e+08 | CO21: 2.5667764e+08 | CP21: - | CQ21: - | CR21: - | CS21: - | CT21: - | CU21: - | CV21: BR0E5ICTF007 | CW21: - | CX21: 25569.626
B22: 24078037000109 | C22: Adam Macro Advisory FIC FIF Multimercado RL | D22: 13 | F22: « | G22: Adam Capital | H22: BNY Mellon Serviços Financeiros | I22: BNY Mellon Banco | J22: Deloitte Touche Tohmatsu | K22: Geral | L22: Investidores em geral | M22: Multimercado | N22: Multimercados Macro | O22: Macro Alta Vol | P22: Longo Prazo - Alíquota regressiva de IR de 22,5% a 15,0% incidida sobre o lucro obtido no momento do resgate. | Q22: 1000 | R22: ABERTO | S22: - | T22: 1000 | U22: 1000 | V22: Fechamento | W22: D+1 (útil) | X22: D+30 (corridos) | Y22: D+1 (útil) | Z22: 31 | AA22: - | AB22: - | AC22: ADAM MACRO ADVISORY RESP LIMITADA FIF CIC MULTIMERCADO | AD22: 0.019 | AE22: 0.119 | AF22: 0.025 | AG22: 0.2 | AH22: Janeiro / Julho | AI22: Junho | AJ22: CDI | AK22: 42488 | AL22: https://www.xpi.com.br/investimentos/fundos-de-investimento/lista/#/detalhes/aa7ededd-37d2-42bd-9e92-d2810af954ea | AM22: 0.14386716 | AN22: 0.032715581 | AO22: 0.10532404 | AP22: 0.14205274 | AQ22: 0.13006515 | AR22: 0.29482157 | AS22: 0.066798775 | AT22: -0.033692782 | AU22: - | AV22: - | AW22: 0.085626816 | AX22: 13.187472 | AY22: 0.72057018 | AZ22: 0.71032948 | BA22: 1.0857575 | BB22: 1.0095285 | BC22: 2.711259 | BD22: 0.51196846 | BE22: - | BF22: - | BG22: - | BH22: 0.87569739 | BI22: 0.13295778 | BJ22: -0.012686771 | BK22: -0.04295087 | BL22: 0.0099218022 | BM22: 0.0010875193 | BN22: 0.18608184 | BO22: -0.063675619 | BP22: -0.15742282 | BQ22: - | BR22: - | BS22: -0.011071849 | BT22: 0.10631566 | BU22: 0.074179709 | BV22: -0.30592311 | BW22: -0.066213039 | BX22: -0.1257028 | BY22: -0.1257028 | BZ22: 0.089599485 | CA22: -0.25937068 | CB22: 0.18834079 | CC22: -0.19605669 | CD22: -0.19544844 | CE22: 0.38710536 | CF22: -0.091457238 | CG22: 2.2666775 | CH22: 0.2342 | CI22: 0.15 | CJ22: 0.0044498 | CK22: - | CL22: 0.0044498 | CM22: 95178917 | CN22: 99207443 | CO22: -18670455 | CP22: - | CQ22: - | CR22: - | CS22: - | CT22: - | CU22: - | CV22: BRADM8CTF008 | CW22: - | CX22: 25569.626
B23: 52297687000172 | C23: Adam Renda Fixa Ativa Advisory FIC FIF RF LP RL | D23: 11 | G23: Adam Capital | H23: BNY Mellon Serviços Financeiros | I23: BNY Mellon Banco | J23: KPMG | K23: Geral | L23: Investidores em geral | M23: Renda Fixa | N23: Renda Fixa Duração Livre Crédito Livre | O23: Renda Fixa Ativo | P23: Longo Prazo | Q23: 500 | R23: ABERTO | S23: - | T23: 100 | U23: 500 | V23: Fechamento | W23: D+0 | X23: D+5 (útil) | Y23: D+1 (útil) | Z23: 6 | AA23: - | AB23: - | AC23: ADAM RENDA FIXA ATIVA ADVISORY RESP LIMITADA FIF CIC RENDA FIXA LP | AD23: 0.009 | AE23: 0.109 | AF23: 0.01 | AG23: 0.2 | AH23: Janeiro / Julho | AI23: Junho | AJ23: CDI | AK23: 45198 | AL23: https://www.xpi.com.br/investimentos/fundos-de-investimento/lista/#/detalhes/0692f533-5c3f-48b7-9afd-d3c177f8feab | AM23: 0.010608764 | AN23: 0.046987562 | AO23: 0.14079427 | AP23: 0.13060697 | AQ23: - | AR23: 0.1114118 | AS23: - | AT23: - | AU23: - | AV23: - | AW23: 0.12786373 | AX23: 0.97244415 | AY23: 1.0349147 | AZ23: 0.94954889 | BA23: 0.99293951 | BB23: - | BC23: 1.0245731 | BD23: - | BE23: - | BF23: - | BG23: - | BH23: 0.99829721 | BI23: -0.00030061729 | BJ23: 0.0015852096 | BK23: -0.0074806341 | BL23: -0.00082074853 | BM23: - | BN23: 0.0026720749 | BO23: - | BP23: - | BQ23: - | BR23: - | BS23: -0.00019333406 | BT23: 0.0032463489 | BU23: 0.0047717435 | BV23: -2.0127983 | BW23: -0.034740524 | BX23: -0.00028012777 | BY23: -0.00091972406 | BZ23: 0.002894796 | CA23: 0.15810586 | CB23: -0.077647673 | CC23: 0.19687328 | CD23: 0.33420343 | CE23: -0.11736892 | CF23: 0.14650892 | CG23: 1.3619678 | CH23: 0.3 | CI23: 0.25 | CJ23: 0.0027 | CK23: - | CL23: 0.0027 | CM23: 13488117 | CN23: 15035638 | CO23: -4477145.2 | CP23: - | CQ23: - | CR23: - | CS23: - | CT23: - | CU23: - | CV23: BR0H18CTF004 | CW23: - | CX23: 25569.626
B24: 35828705000186 | C24: AF Global Bonds CI RF CP RL | D24: 16 | G24: AF Invest Investimentos | H24: Santander Caceis | I24: Santander Caceis | J24: PriceWaterhouseCoopers | K24: Intranet | L24: Investidores qualificados | M24: Renda Fixa | N24: Renda Fixa Investimento no Exterior | O24: Internacional Renda Fixa Hedgeado | P24: Longo Prazo: Haverá cobrança de IR no último dia útil dos meses de maio e novembro de cada ano sob a alíquota de 15% (“come-cotas”), ou no resgate, se ocorrido em data anterior, seguindo tabela regressiva partindo de 22,5% para intervalo entre aplicação e resgate menor do que 6 meses à 15% se o intervalo entre aplicação e resgate for maior do que 2 anos. | Q24: 1000 | R24: ABERTO | S24: - | T24: 1000 | U24: 500 | V24: Fechamento | W24: D+0 | X24: D+15 (corridos) | Y24: D+1 (útil) | Z24: 16 | AA24: - | AB24: - | AC24: - | AD24: 0.005 | AE24: - | AF24: 0.0075 | AG24: 0.2 | AH24: - | AI24: - | AJ24: CDI | AK24: 44048 | AL24: https://www.xpi.com.br/investimentos/fundos-de-investimento/lista/#/detalhes/f1912c9d-b780-43c2-97e7-bb62f95d86a7 | AM24: 0.01530381 | AN24: 0.042283182 | AO24: 0.14075502 | AP24: 0.13137745 | AQ24: 0.13565437 | AR24: 0.09920286 | AS24: 0.10807567 | AT24: 0.12451628 | AU24: - | AV24: - | AW24: 0.10190691 | AX24: 1.4028119 | AY24: 0.93129936 | AZ24: 0.94928413 | BA24: 0.99915828 | BB24: 1.0585512 | BC24: 0.91229638 | BD24: 0.82832861 | BE24: 1.0063545 | BF24: - | BG24: - | BH24: 0.96084448 | BI24: 0.004394429 | BJ24: -0.0031191706 | BK24: -0.0075198913 | BL24: -9.7814483e-05 | BM24: 0.0066510508 | BN24: -0.0095368679 | BO24: -0.02239872 | BP24: 0.00078623988 | BQ24: - | BR24: - | BS24: -0.0037546112 | BT24: 0.014172437 | BU24: 0.0250757 | BV24: -0.45679751 | BW24: -0.10768012 | BX24: -0.0037300944 | BY24: -0.038111782 | BZ24: 0.018327322 | CA24: 0.20632588 | CB24: -0.056843061 | CC24: 0.25808484 | CD24: 0.19836152 | CE24: 0.16878386 | CF24: 0.24345097 | CG24: 1.7404469 | CH24: 0.27 | CI24: 0.15 | CJ24: 0.00135 | CK24: - | CL24: 0.00135 | CM24: 28760078 | CN24: 30126787 | CO24: -3904629.6 | CP24: - | CQ24: - | CR24: - | CS24: - | CT24: - | CU24: - | CV24: BR04RXCTF008 | CW24: - | CX24: 25569.626
B25: 44025131000107 | C25: AF Horizonte FIF Multimercado CP RL | D25: 13 | G25: AF Invest Investimentos | H25: BTG Pactual Serviços Financeiros | I25: Banco BTG Pactual | J25: EY | K25: Geral | L25: Investidores qualificados | M25: Multimercado | N25: Multimercados Livre | O25: Crédito High Yield | P25: Longo Prazo | Q25: 1000 | R25: ABERTO | S25: - | T25: 1000 | U25: 1000 | V25: Fechamento | W25: D+0 | X25: D+59 (corridos) | Y25: D+1 (útil) | Z25: 60 | AA25: - | AB25: - | AC25: - | AD25: 0.01 | AE25: - | AF25: 0.01 | AG25: 0.2 | AH25: Dezembro / Junho | AI25: Novembro / Maio | AJ25: CDI | AK25: 44523 | AL25: https://www.xpi.com.br/investimentos/fundos-de-investimento/lista/#/detalhes/cb30cbb8-f0b6-4d23-ab4c-c4cdd49bc53f | AM25: 0.01076937 | AN25: 0.022877542 | AO25: 0.1238972 | AP25: 0.12571127 | AQ25: 0.13484002 | AR25: 0.1299722 | AS25: 0.11274598 | AT25: 0.14933649 | AU25: - | AV25: - | AW25: 0.13031539 | AX25: 0.98716598 | AY25: 0.50388451 | AZ25: 0.83559118 | BA25: 0.95352387 | BB25: 1.0513784 | BC25: 1.1952595 | BD25: 0.86412342 | BE25: 1.2069542 | BF25: - | BG25: - | BH25: 1.0287516 | BI25: -0.00014001117 | BJ25: -0.02252481 | BK25: -0.024377703 | BL25: -0.0054136244 | BM25: 0.005840295 | BN25: 0.021232469 | BO25: -0.017728415 | BP25: 0.025606456 | BQ25: - | BR25: - | BS25: 0.0032325752 | BT25: 0.011460381 | BU25: 0.0091456705 | BV25: -1.8676256 | BW25: 0.29540747 | BX25: -0.012972187 | BY25: -0.012972187 | BZ25: 0.0035993587 | CA25: 0.035268382 | CB25: -0.01230496 | CC25: 0.065103862 | CD25: 0.04731936 | CE25: -0.0021827264 | CF25: 0.11107787 | CG25: 1.7186055 | CH25: 0.24 | CI25: 0.09 | CJ25: 0.0024 | CK25: - | CL25: 0.0024 | CM25: 2.2967051e+08 | CN25: 2.263173e+08 | CO25: -2959420.5 | CP25: - | CQ25: - | CR25: - | CS25: - | CT25: - | CU25: - | CV25: BR0ACVCTF007 | CW25: - | CX25: 25569.626
B26: 29044189000104 | C26: AF Invest Geraes 30 FIRF CP | D26: 10 | G26: AF Invest Investimentos | H26: BTG Pactual Serviços Financeiros | I26: Banco BTG Pactual | J26: KPMG | K26: Geral | L26: Investidores em geral | M26: Renda Fixa | N26: Renda Fixa Duração Livre Grau de Investimento | O26: Crédito High Grade | P26: Longo Prazo: Haverá cobrança de IR no último dia útil dos meses de maio e novembro de cada ano sob a alíquota de 15% (“come-cotas”), ou no resgate, se ocorrido em data anterior, seguindo tabela regressiva partindo de 22,5% para intervalo entre aplicação e resgate menor do que 6 meses à 15% se o intervalo entre aplicação e resgate for maior do que 2 anos._x000D_ | Q26: 500 | R26: ABERTO | S26: - | T26: 100 | U26: 500 | V26: Fechamento | W26: D+0 | X26: D+30 (corridos) | Y26: D+1 (útil) | Z26: 31 | AA26: - | AB26: - | AC26: - | AD26: 0.005 | AE26: - | AF26: 0.008 | AG26: - | AH26: - | AI26: - | AJ26: CDI | AK26: 43187 | AL26: https://www.xpi.com.br/investimentos/fundos-de-investimento/lista/#/detalhes/f95a255b-c0bc-43da-b128-73a7acdbf874 | AM26: 0.0094101092 | AN26: 0.035013289 | AO26: 0.13848081 | AP26: 0.13545335 | AQ26: 0.14113547 | AR26: 0.12729654 | AS26: 0.10357166 | AT26: 0.14697884 | AU26: - | AV26: - | AW26: 0.093679999 | AX26: 0.86257037 | AY26: 0.77117786 | AZ26: 0.93394634 | BA26: 1.0321265 | BB26: 1.1070965 | BC26: 1.1706535 | BD26: 0.79380835 | BE26: 1.1878994 | BF26: - | BG26: - | BH26: 1.0525934 | BI26: -0.0014992723 | BJ26: -0.010389063 | BK26: -0.0097941007 | BL26: 0.0037270636 | BM26: 0.012109215 | BN26: 0.018556813 | BO26: -0.02690273 | BP26: 0.023248802 | BQ26: - | BR26: - | BS26: 0.0042982291 | BT26: 0.0090937745 | BU26: 0.011010765 | BV26: -0.93793482 | BW26: 0.29855922 | BX26: -0.0030525598 | BY26: -0.055045721 | BZ26: 0.001765241 | CA26: 0.15295036 | CB26: -0.081307988 | CC26: 0.13838521 | CD26: 0.15431731 | CE26: -0.031235102 | CF26: 0.13693388 | CG26: 2.0579606 | CH26: 0.27 | CI26: - | CJ26: 0.00135 | CK26: - | CL26: 0.00135 | CM26: 3.146219e+08 | CN26: 3.5232717e+08 | CO26: -32996323 | CP26: - | CQ26: - | CR26: - | CS26: - | CT26: - | CU26: - | CV26: BR002TCTF003 | CW26: - | CX26: 25569.626
B27: 9720734000110 | C27: AF Invest Geraes FIF RF CP RL | D27: 10 | F27: ««« | G27: AF Invest Investimentos | H27: BTG Pactual Serviços Financeiros | I27: Banco BTG Pactual | J27: EY | K27: Geral | L27: Investidores em geral | M27: Renda Fixa | N27: Renda Fixa Duração Livre Grau de Investimento | O27: Crédito Liquidez | P27: Longo Prazo - Alíquota regressiva de IR de 22,5% a 15,0% incidida sobre o lucro obtido no momento do resgate. | Q27: 500 | R27: ABERTO | S27: - | T27: 100 | U27: 500 | V27: Fechamento | W27: D+0 | X27: D+0 | Y27: D+1 (útil) | Z27: 1 | AA27: - | AB27: - | AC27: - | AD27: 0.004 | AE27: - | AF27: 0.006 | AG27: - | AH27: - | AI27: - | AJ27: CDI | AK27: 39702 | AL27: https://www.xpi.com.br/investimentos/fundos-de-investimento/lista/#/detalhes/cc7bce2d-35e5-431b-8b42-a0542280a0d7 | AM27: 0.010127895 | AN27: 0.039935965 | AO27: 0.14436146 | AP27: 0.13360338 | AQ27: 0.13655073 | AR27: 0.11973905 | AS27: 0.11577234 | AT27: 0.13770026 | AU27: - | AV27: - | AW27: 0.10164526 | AX27: 0.92836565 | AY27: 0.87960123 | AZ27: 0.97360681 | BA27: 1.0171482 | BB27: 1.0664582 | BC27: 1.1011527 | BD27: 0.88731847 | BE27: 1.1129089 | BF27: - | BG27: - | BH27: 1.0536536 | BI27: -0.00078148647 | BJ27: -0.0054663872 | BK27: -0.0039134485 | BL27: 0.0019909218 | BM27: 0.007543513 | BN27: 0.010999322 | BO27: -0.014702054 | BP27: 0.013970222 | BQ27: - | BR27: - | BS27: 0.0047205362 | BT27: 0.0046669238 | BU27: 0.0063204626 | BV27: -0.72958949 | BW27: 0.38583465 | BX27: -0.0020367311 | BY27: -0.036711977 | BZ27: 0.00046507659 | CA27: 0.077875057 | CB27: -0.035615895 | CC27: 0.08903046 | CD27: 0.1135462 | CE27: -0.03217238 | CF27: 0.07603618 | CG27: 5.4794122 | CH27: 0.25 | CI27: - | CJ27: 0.001 | CK27: - | CL27: 0.001 | CM27: 5.4246401e+08 | CN27: 5.9206749e+08 | CO27: -31455777 | CP27: - | CQ27: - | CR27: - | CS27: - | CT27: - | CU27: - | CV27: BRAFI3CTF003 | CW27: - | CX27: 25569.626
B28: 12987743000186 | C28: Alaska Black FIC de FIA - BDR NÍVEL I | D28: 38 | F28: « | G28: Alaska Asset Management | H28: BTG Pactual Serviços Financeiros | I28: Banco BTG Pactual | J28: EY | K28: Geral | L28: Investidores qualificados | M28: Ações | N28: Ações Livre | O28: Renda Variável Long Only | P28: Renda Variável - Alíquota de IR de 15% incidida sobre o lucro obtido no momento do resgate. | Q28: 5000 | R28: ABERTO | S28: - | T28: 1000 | U28: 5000 | V28: Fechamento | W28: D+1 (útil) | X28: D+30 (corridos) | Y28: D+2 (útil) | Z28: 32 | AA28: - | AB28: - | AC28: ALASKA BLACK FIF CIC AÇÕES | AD28: 0.0185 | AE28: 0.1685 | AF28: 0.0185 | AG28: 0.2 | AH28: Janeiro / Julho | AI28: Junho | AJ28: - | AK28: 40567 | AL28: https://www.xpi.com.br/investimentos/fundos-de-investimento/lista/#/detalhes/04570145-f065-4cba-a5a8-2ab26447c7c9 | AM28: -0.014544967 | AN28: 0.11954405 | AO28: 0.24590465 | AP28: 0.002182937 | AQ28: 0.092144338 | AR28: -0.57148685 | AS28: 0.5874196 | AT28: 0.090991395 | AU28: - | AV28: - | AW28: 0.074804301 | AX28: - | AY28: 2.6329924 | AZ28: 1.6584374 | BA28: 0.015595455 | BB28: 0.68954897 | BC28: - | BD28: 4.502183 | BE28: 0.73540264 | BF28: - | BG28: - | BH28: 0.6316525 | BI28: -0.025454348 | BJ28: 0.074141694 | BK28: 0.097629746 | BL28: -0.12087106 | BM28: -0.036595305 | BN28: -0.68022657 | BO28: 0.45694521 | BP28: -0.032738641 | BQ28: - | BR28: - | BS28: -0.039003061 | BT28: 0.43958006 | BU28: 0.38402963 | BV28: 0.40518659 | BW28: 0.14308078 | BX28: -0.26783711 | BY28: -0.73364298 | BZ28: 1.2558545 | CA28: 0.89421482 | CB28: -0.5181263 | CC28: 0.66051116 | CD28: 0.54954833 | CE28: 0.075890243 | CF28: 0.76381254 | CG28: 2.9959189 | CH28: 0.25 | CI28: 0.15 | CJ28: 0.004625 | CK28: - | CL28: 0.004625 | CM28: 8.223804e+08 | CN28: 8.4661599e+08 | CO28: -56397021 | CP28: - | CQ28: - | CR28: - | CS28: - | CT28: - | CU28: - | CV28: BRSKP7CTF008 | CW28: - | CX28: 25569.626
B29: 26673556000132 | C29: Alaska Institucional Long Only FIF em Ações RL | D29: 28 | F29: «««« | G29: Alaska Asset Management | H29: BTG Pactual Serviços Financeiros | I29: Banco BTG Pactual | J29: KPMG | K29: Geral | L29: Investidores em geral | M29: Ações | N29: Ações Livre | O29: Renda Variável Long Only | P29: Renda Variável - Alíquota de IR de 15% incidida sobre o lucro obtido no momento do resgate. | Q29: 1000 | R29: ABERTO | S29: - | T29: 500 | U29: 1000 | V29: Fechamento | W29: D+1 (útil) | X29: D+30 (corridos) | Y29: D+2 (útil) | Z29: 32 | AA29: Sim | AB29: 0.05 | AC29: - | AD29: 0.02 | AE29: - | AF29: 0.025 | AG29: 0.2 | AH29: Janeiro / Julho | AI29: Junho | AJ29: Ibovespa | AK29: 42787 | AL29: https://www.xpi.com.br/investimentos/fundos-de-investimento/lista/#/detalhes/ddd2f6a6-42a9-4fe2-935f-0ccf566b3d29 | AM29: -0.039936879 | AN29: 0.019593066 | AO29: 0.047964323 | AP29: 0.017796527 | AQ29: 0.084586559 | AR29: -0.32888698 | AS29: 0.35564604 | AT29: 0.043139551 | AU29: - | AV29: - | AW29: 0.14276479 | AX29: - | AY29: 0.43154296 | AZ29: 0.3234824 | BA29: 0.12813439 | BB29: 0.62836497 | BC29: - | BD29: 2.7257919 | BE29: 0.34865868 | BF29: - | BG29: - | BH29: 1.9895676 | BI29: -0.050846261 | BJ29: -0.025809287 | BK29: -0.10031058 | BL29: -0.10632551 | BM29: -0.044091817 | BN29: -0.43762671 | BO29: 0.22517165 | BP29: -0.080590485 | BQ29: - | BR29: - | BS29: 0.066253935 | BT29: 0.28724769 | BU29: 0.26976876 | BV29: -0.17514008 | BW29: 0.31192876 | BX29: -0.18437815 | BY29: -0.51933507 | BZ29: 1.0418354 | CA29: 0.84595023 | CB29: -0.41605374 | CC29: 0.61424126 | CD29: 0.49925452 | CE29: 0.11942061 | CF29: 0.69649703 | CG29: 3.3857995 | CH29: 0.2 | CI29: 0.15 | CJ29: 0.004 | CK29: - | CL29: 0.004 | CM29: 8.4165369e+08 | CN29: 8.9994182e+08 | CO29: -61967975 | CP29: - | CQ29: - | CR29: - | CS29: - | CT29: - | CU29: - | CV29: BRASK4CTF002 | CW29: - | CX29: 25569.626
B30: 34839385000105 | C30: AlphaKey Ações FIF em Cotas de FIA RL | D30: 38 | F30: «« | G30: ALPHAKEY CAPITAL MANAGEMENT INVESTIMENTOS LTDA | H30: BTG Pactual Serviços Financeiros | I30: Banco BTG Pactual | J30: EY | K30: Geral | L30: Investidores qualificados | M30: Ações | N30: Ações Livre | O30: Renda Variável Long Biased | P30: Renda Variável - Alíquota de IR de 15% incidida sobre o lucro obtido no momento do resgate._x000D_ | Q30: 5000 | R30: ABERTO | S30: - | T30: 1000 | U30: 1000 | V30: Fechamento | W30: D+1 (útil) | X30: D+30 (corridos) | Y30: D+2 (útil) | Z30: 32 | AA30: - | AB30: - | AC30: ALPHAKEY FIF CIC AÇÕES | AD30: 0.0187 | AE30: 0.1487 | AF30: 0.022 | AG30: 0.2 | AH30: - | AI30: - | AJ30: - | AK30: 43889 | AL30: https://www.xpi.com.br/investimentos/fundos-de-investimento/lista/#/detalhes/df57c52c-b420-4be2-bad2-06fa72983845 | AM30: -0.0086837593 | AN30: 0.075046687 | AO30: 0.31314754 | AP30: 0.28425405 | AQ30: 0.33411072 | AR30: -0.0030219311 | AS30: 0.32708484 | AT30: -0.10433458 | AU30: - | AV30: - | AW30: 0.1230343 | AX30: - | AY30: 1.6529251 | AZ30: 2.1119389 | BA30: 2.3168833 | BB30: 3.1312799 | BC30: - | BD30: 2.5068891 | BE30: - | BF30: - | BG30: - | BH30: 1.4744245 | BI30: -0.019593141 | BJ30: 0.029644335 | BK30: 0.16487263 | BL30: 0.1439099 | BM30: 0.20548433 | BN30: -0.11176166 | BO30: 0.19661044 | BP30: -0.22806461 | BQ30: - | BR30: - | BS30: 0.036539591 | BT30: 0.15609255 | BU30: 0.27921144 | BV30: 0.93807236 | BW30: 0.24113003 | BX30: -0.068126624 | BY30: -0.52376957 | BZ30: 1.0338787 | CA30: 0.87369705 | CB30: -0.41323054 | CC30: 0.62785436 | CD30: 0.52900174 | CE30: 0.14036081 | CF30: 0.72629673 | CG30: 2.3699987 | CH30: 0.25 | CI30: 0.15 | CJ30: 0.004675 | CK30: - | CL30: 0.004675 | CM30: 2.1111967e+08 | CN30: 1.8448144e+08 | CO30: 37323421 | CP30: - | CQ30: - | CR30: - | CS30: - | CT30: - | CU30: - | CV30: BR050ECTF004 | CW30: - | CX30: 25569.626
B31: 36352721000108 | C31: AlphaKey Institucional FIF em Cotas de FIA RL | D31: 43 | G31: ALPHAKEY CAPITAL MANAGEMENT INVESTIMENTOS LTDA | H31: BTG Pactual Serviços Financeiros | I31: Banco BTG Pactual | J31: KPMG | K31: Geral | L31: Investidores em geral | M31: Ações | N31: Ações Livre | O31: Renda Variável Long Only | P31: Renda Variável - Alíquota de IR de 15% incidida sobre o lucro obtido no momento do resgate._x000D_ | Q31: 1000 | R31: ABERTO | S31: - | T31: 1000 | U31: 1000 | V31: Fechamento | W31: D+1 (útil) | X31: D+30 (corridos) | Y31: D+2 (útil) | Z31: 32 | AA31: - | AB31: - | AC31: ALPHAKEY INSTITUCIONAL FIF CIC AÇÕES | AD31: 0.0189 | AE31: 0.1289 | AF31: 0.0235 | AG31: 0.2 | AH31: Janeiro / Julho | AI31: Junho | AJ31: Ibovespa | AK31: 44000 | AL31: https://www.xpi.com.br/investimentos/fundos-de-investimento/lista/#/detalhes/c5e92b06-8749-4f35-bf57-218dbaf3f62f | AM31: -0.017841527 | AN31: 0.075637136 | AO31: 0.28464072 | AP31: 0.23402702 | AQ31: 0.24878371 | AR31: -0.075605608 | AS31: 0.25779357 | AT31: -0.17936287 | AU31: - | AV31: - | AW31: 0.051998334 | AX31: - | AY31: 1.6659299 | AZ31: 1.9196823 | BA31: 1.8655526 | BB31: 2.1583305 | BC31: - | BD31: 1.9758173 | BE31: - | BF31: - | BG31: - | BH31: 0.44459784 | BI31: -0.028750908 | BJ31: 0.030234784 | BK31: 0.13636581 | BL31: 0.096477741 | BM31: 0.11971753 | BN31: -0.18434534 | BO31: 0.12731917 | BP31: -0.30309291 | BQ31: - | BR31: - | BS31: -0.058155879 | BT31: 0.17318692 | BU31: 0.22095882 | BV31: 0.7347665 | BW31: -0.10465481 | BX31: -0.08728993 | BY31: -0.48131424 | BZ31: 1.0187571 | CA31: 0.91387854 | CB31: -0.44420309 | CC31: 0.67119794 | CD31: 0.557161 | CE31: 0.14848068 | CF31: 0.76729233 | CG31: 1.344879 | CH31: 0.25 | CI31: 0.15 | CJ31: 0.004725 | CK31: - | CL31: 0.004725 | CM31: 15594410 | CN31: 13206818 | CO31: 3308265.8 | CP31: - | CQ31: - | CR31: - | CS31: - | CT31: - | CU31: - | CV31: BR04DSCTF008 | CW31: - | CX31: 25569.626
B32: 52304477000164 | C32: AlphaKey LS FIF em Cotas FIM RL | D32: 13 | G32: ALPHAKEY CAPITAL MANAGEMENT INVESTIMENTOS LTDA | H32: BTG Pactual Serviços Financeiros | I32: Banco BTG Pactual | J32: KPMG | K32: Geral | L32: Investidores em geral | M32: Multimercado | N32: Multimercados Livre | O32: Multiestratégia | P32: Longo Prazo | Q32: 1000 | R32: ABERTO | S32: - | T32: 1000 | U32: 1000 | V32: Fechamento | W32: D+1 (útil) | X32: D+30 (corridos) | Y32: D+2 (útil) | Z32: 32 | AA32: - | AB32: - | AC32: ALPHAKEY LONG SHORT FIF CIC MULTIMERCADO | AD32: 0.0187 | AE32: 0.1487 | AF32: 0.0237 | AG32: 0.2 | AH32: Junho / Dezembro | AI32: Maio / Novembro | AJ32: CDI | AK32: 45197 | AL32: https://www.xpi.com.br/investimentos/fundos-de-investimento/lista/#/detalhes/6806aa48-c47d-4e5d-bcc5-95d2e3a3e9e7 | AM32: 0.0079921915 | AN32: 0.049017246 | AO32: 0.18433761 | AP32: 0.16204963 | AQ32: - | AR32: 0.12643342 | AS32: - | AT32: - | AU32: - | AV32: - | AW32: 0.16324673 | AX32: 0.73259804 | AY32: 1.0796191 | AZ32: 1.2432151 | BA32: 1.2501634 | BB32: - | BC32: 1.162716 | BD32: - | BE32: - | BF32: - | BG32: - | BH32: 1.3084469 | BI32: -0.00291719 | BJ32: 0.0036148943 | BK32: 0.036062699 | BL32: 0.028705932 | BM32: - | BN32: 0.017693688 | BO32: - | BP32: - | BQ32: - | BR32: - | BS32: 0.034214287 | BT32: 0.024528755 | BU32: 0.024488416 | BV32: 1.2736607 | BW32: 1.2671514 | BX32: -0.0063694808 | BY32: -0.0091660998 | BZ32: 0.050039444 | CA32: 0.38623952 | CB32: -0.14762106 | CC32: 0.33830555 | CD32: 0.30111337 | CE32: 0.20245718 | CF32: 0.42391748 | CG32: 1.4752664 | CH32: 0.24 | CI32: 0.15 | CJ32: 0.004488 | CK32: 0.00094217941 | CL32: 0.0054301794 | CM32: 1.6468241e+08 | CN32: 1.2638527e+08 | CO32: 49535285 | CP32: - | CQ32: - | CR32: - | CS32: - | CT32: - | CU32: - | CV32: BR0H0MCTF007 | CW32: - | CX32: 25569.626
B33: 64154430000140 | C33: AP LB II FIF em Cotas de FIA | D33: 26 | G33: Absoluto Partners Investimentos | H33: BTG Pactual Serviços Financeiros | I33: Banco BTG Pactual | J33: EY | K33: Intranet | L33: Não definido | M33: Ações | N33: - | O33: Renda Variável Long Biased | P33: Ações | Q33: 200000 | R33: ABERTO | S33: - | T33: 50000 | U33: 50000 | V33: Fechamento | W33: D+1 (útil) | X33: D+60 (corridos) | Y33: D+2 (útil) | Z33: 62 | AA33: - | AB33: - | AC33: - | AD33: 0.0185 | AE33: - | AF33: 0.0189 | AG33: 0.2 | AH33: Janeiro / Julho | AI33: Junho | AJ33: CDI | AK33: 46126 | AL33: https://www.xpi.com.br/investimentos/fundos-de-investimento/lista/#/detalhes/3518c3f7-7b7c-4a9a-9ad4-87317a405c1c | AM33: - | AN33: - | AO33: - | AP33: - | AQ33: - | AR33: - | AS33: - | AT33: - | AU33: - | AV33: - | AW33: - | AX33: - | AY33: - | AZ33: - | BA33: - | BB33: - | BC33: - | BD33: - | BE33: - | BF33: - | BG33: - | BH33: - | BI33: - | BJ33: - | BK33: - | BL33: - | BM33: - | BN33: - | BO33: - | BP33: - | BQ33: - | BR33: - | BS33: - | BT33: - | BU33: 0.15567095 | BV33: - | BW33: -7.2603242 | BX33: - | BY33: -0.050906282 | BZ33: 0.8723754 | CA33: - | CB33: - | CC33: - | CD33: - | CE33: - | CF33: - | CG33: 0.96077857 | CH33: 0.03 | CI33: - | CJ33: 0.000555 | CK33: - | CL33: 0.000555 | CM33: 2882335.7 | CN33: - | CO33: - | CP33: - | CQ33: - | CR33: - | CS33: - | CT33: - | CU33: - | CV33: BR0R3FCTF003 | CW33: - | CX33: 25569.626
B34: 15862830000103 | C34: Apex Ações 30 FIC FIF Ações RL | D34: 26 | F34: ««« | G34: Apex Capital | H34: BNY Mellon Serviços Financeiros | I34: BNY Mellon Banco | J34: Deloitte Touche Tohmatsu | K34: Geral | L34: Investidores em geral | M34: Ações | N34: Ações Livre | O34: Renda Variável Long Only | P34: Renda Variável - Alíquota de IR de 15% incidida sobre o lucro obtido no momento do resgate. | Q34: 500 | R34: ABERTO | S34: - | T34: 100 | U34: 100 | V34: Fechamento | W34: D+1 (útil) | X34: D+30 (corridos) | Y34: D+2 (útil) | Z34: 32 | AA34: - | AB34: - | AC34: APEX AÇÕES 30 RESP LIMITADA FIF CIC AÇÕES | AD34: 0.019 | AE34: 0.119 | AF34: 0.025 | AG34: 0.2 | AH34: Janeiro / Julho | AI34: Junho | AJ34: Ibovespa | AK34: 41141 | AL34: https://www.xpi.com.br/investimentos/fundos-de-investimento/lista/#/detalhes/dab61957-9811-4171-b39e-c7f7ecbda712 | AM34: -0.011181407 | AN34: 0.053294666 | AO34: 0.29313268 | AP34: 0.2138557 | AQ34: 0.20170774 | AR34: -0.14274623 | AS34: 0.17092933 | AT34: 0.066246175 | AU34: - | AV34: - | AW34: 0.096752188 | AX34: - | AY34: 1.1738305 | AZ34: 1.9769541 | BA34: 1.6893639 | BB34: 1.6752812 | BC34: - | BD34: 1.3100603 | BE34: 0.53540901 | BF34: - | BG34: - | BH34: 0.99067716 | BI34: -0.022090789 | BJ34: 0.0078923141 | BK34: 0.14485778 | BL34: 0.077460533 | BM34: 0.072568058 | BN34: -0.25148596 | BO34: 0.040454933 | BP34: -0.05748386 | BQ34: - | BR34: - | BS34: -0.00082948417 | BT34: 0.19163452 | BU34: 0.21499397 | BV34: 0.71643318 | BW34: 0.1064052 | BX34: -0.099437768 | BY34: -0.50391836 | BZ34: 0.88268432 | CA34: 0.93438459 | CB34: -0.48301978 | CC34: 0.65367456 | CD34: 0.55136107 | CE34: 0.052306226 | CF34: 0.7687686 | CG34: 3.5239968 | CH34: 0.21 | CI34: 0.1 | CJ34: 0.00399 | CK34: - | CL34: 0.00399 | CM34: 20830498 | CN34: 20780000 | CO34: 879070.81 | CP34: - | CQ34: - | CR34: - | CS34: - | CT34: - | CU34: - | CV34: BRAPE5CTF000 | CW34: - | CX34: 25569.626
B35: 40634864000180 | C35: Apex Equity Hedge Advisory FIC FIF Multi RL | D35: 13 | G35: Apex Capital | H35: BNY Mellon Serviços Financeiros | I35: BNY Mellon Banco | J35: KPMG | K35: Geral | L35: Exclusivo | M35: Multimercado | N35: Multimercados Long and Short Direcional | O35: Long Short Direcional | P35: Renda Variável - Alíquota de IR de 15% incidida sobre o lucro obtido no momento do resgate._x000D_ | Q35: 500 | R35: ABERTO | S35: - | T35: 100 | U35: 100 | V35: Fechamento | W35: D+1 (útil) | X35: D+29 (corridos) | Y35: D+1 (útil) | Z35: 30 | AA35: - | AB35: - | AC35: APEX EQUITY HEDGE ADVISORY RESP LIMITADA FIF CIC MULTIMERCADO | AD35: 0.019 | AE35: 0.119 | AF35: 0.025 | AG35: 0.2 | AH35: - | AI35: - | AJ35: CDI | AK35: 44333 | AL35: https://www.xpi.com.br/investimentos/fundos-de-investimento/lista/#/detalhes/0faf6731-b37a-4550-bdb9-fe5a2884f023 | AM35: 0.0094083645 | AN35: -0.00038516515 | AO35: 0.15363831 | AP35: 0.14318887 | AQ35: 0.11394876 | AR35: 0.045790139 | AS35: 0.070249056 | AT35: 0.07842564 | AU35: - | AV35: - | AW35: 0.073370976 | AX35: 0.86241044 | AY35: - | AZ35: 1.036172 | BA35: 1.0950219 | BB35: 0.87086612 | BC35: 0.42109853 | BD35: 0.53841259 | BE35: 0.63384481 | BF35: - | BG35: - | BH35: 0.56384008 | BI35: -0.001501017 | BJ35: -0.045787517 | BK35: 0.0053633994 | BL35: 0.010988495 | BM35: -0.014941534 | BN35: -0.062949589 | BO35: -0.060225338 | BP35: -0.045304395 | BQ35: - | BR35: - | BS35: -0.050221161 | BT35: 0.041036451 | BU35: 0.046547895 | BV35: 0.13406984 | BW35: -0.87137971 | BX35: -0.033307736 | BY35: -0.073883908 | BZ35: 0.12389591 | CA35: 0.47382871 | CB35: -0.33526577 | CC35: 0.386355 | CD35: 0.35646596 | CE35: 0.013710838 | CF35: 0.52607202 | CG35: 1.4187925 | CH35: 0.25 | CI35: 0.15 | CJ35: 0.00475 | CK35: 0.00014012496 | CL35: 0.004890125 | CM35: 10886332 | CN35: 10654399 | CO35: 1091426.9 | CP35: - | CQ35: - | CR35: - | CS35: - | CT35: - | CU35: - | CV35: BR07Y8CTF004 | CW35: - | CX35: 25569.626
B36: 33345956000184 | C36: Apex Long Biased Advisory FIC FIF Multimercado RL | D36: 22 | F36: ««« | G36: Apex Capital | H36: BNY Mellon Serviços Financeiros | I36: BNY Mellon Banco | J36: Deloitte Touche Tohmatsu | K36: Geral | L36: Investidores em geral | M36: Multimercado | N36: Multimercados Livre | O36: Renda Variável Long Biased | P36: Renda Variável - Alíquota de IR de 15% incidida sobre o lucro obtido no momento do resgate. | Q36: 500 | R36: ABERTO | S36: - | T36: 100 | U36: 100 | V36: Fechamento | W36: D+1 (útil) | X36: D+30 (corridos) | Y36: D+2 (útil) | Z36: 32 | AA36: - | AB36: - | AC36: APEX LONG BIASED ADVISORY RESP LIMITADA FIF CIC MULTIMERCADO | AD36: 0.019 | AE36: 0.119 | AF36: 0.025 | AG36: 0.2 | AH36: Abril / Outubro | AI36: Março / Setembro | AJ36: CDI | AK36: 43686 | AL36: https://www.xpi.com.br/investimentos/fundos-de-investimento/lista/#/detalhes/52bb8fa7-2c11-487e-8c16-c35bbc6bc024 | AM36: -0.01934829 | AN36: -0.022180842 | AO36: 0.21377245 | AP36: 0.17511808 | AQ36: 0.14106053 | AR36: -0.081789933 | AS36: 0.10986366 | AT36: 0.070658638 | AU36: - | AV36: - | AW36: 0.035294249 | AX36: - | AY36: - | AZ36: 1.4417305 | BA36: 1.3591485 | BB36: 1.1064296 | BC36: - | BD36: 0.84203232 | BE36: 0.57107102 | BF36: - | BG36: - | BH36: 0.31024292 | BI36: -0.030257671 | BJ36: -0.067583194 | BK36: 0.065497543 | BL36: 0.040992478 | BM36: 0.012034573 | BN36: -0.19052966 | BO36: -0.020610737 | BP36: -0.053071398 | BQ36: - | BR36: - | BS36: -0.070453948 | BT36: 0.16313048 | BU36: 0.19261948 | BV36: 0.42197287 | BW36: -0.19587231 | BX36: -0.12060636 | BY36: -0.43889708 | BZ36: 0.71357406 | CA36: 0.88754974 | CB36: -0.46572177 | CC36: 0.63512026 | CD36: 0.52666424 | CE36: 0.072568151 | CF36: 0.76675744 | CG36: 1.2615474 | CH36: 0.25 | CI36: 0.15 | CJ36: 0.00475 | CK36: 0.0017111985 | CL36: 0.0064611985 | CM36: 10121463 | CN36: 11173619 | CO36: -796152.4 | CP36: - | CQ36: - | CR36: - | CS36: - | CT36: - | CU36: - | CV36: BR0232CTF001 | CW36: - | CX36: 25569.626
B37: 44544223000195 | C37: Aqua Capital PE Agro FIP Multi - Classe A | D37: 50 | G37: Aqua Capital | H37: TMF Group | I37: Banco Daycoval | J37: RSM Brasil | K37: Geral | L37: Investidores qualificados | M37: Participações | N37: Fundos de Participações | O37: Alternativo Ilíquido | P37: FIP | Q37: 25000 | R37: FECHADO | S37: - | T37: 0.01 | U37: 0.01 | V37: Fechamento | W37: D+0 | X37: D+0 | Y37: D+0 | Z37: 0 | AA37: - | AB37: - | AC37: - | AD37: 0.02 | AE37: - | AF37: - | AG37: 0.2 | AH37: - | AI37: - | AJ37: - | AK37: 44683 | AL37: https://www.xpi.com.br/investimentos/fundos-de-investimento/lista/#/detalhes/cefd5c4e-2b5b-48b0-ad1d-1ebb2aeea400 | AM37: - | AN37: - | AO37: - | AP37: - | AQ37: - | AR37: - | AS37: - | AT37: - | AU37: - | AV37: - | AW37: - | AX37: - | AY37: - | AZ37: - | BA37: - | BB37: - | BC37: - | BD37: - | BE37: - | BF37: - | BG37: - | BH37: - | BI37: - | BJ37: - | BK37: - | BL37: - | BM37: - | BN37: - | BO37: - | BP37: - | BQ37: - | BR37: - | BS37: - | BT37: 0.0547621 | BU37: 0.92482994 | BV37: -2.5890689 | BW37: 0.11554968 | BX37: -0.038120819 | BY37: -0.73080646 | BZ37: 0.7371755 | CA37: -0.0038412672 | CB37: 0.10698222 | CC37: -0.052872562 | CD37: -0.040308065 | CE37: 0.05119309 | CF37: 0.016057241 | CG37: 834.08177 | CH37: 0.15 | CI37: 0.05 | CJ37: 0.003 | CK37: - | CL37: 0.003 | CM37: 24850390 | CN37: 22679169 | CO37: 2736795.3 | CP37: - | CQ37: - | CR37: - | CS37: - | CT37: - | CU37: - | CV37: BR0BXFCTF004 | CW37: - | CX37: 25569.605
B38: 44544223000195 | C38: Aqua Capital PE Agro FIP Multi - Classe B | D38: 50 | G38: Aqua Capital | H38: TMF Group | I38: Banco Daycoval | J38: RSM Brasil | K38: Geral | L38: Investidores qualificados | M38: Participações | N38: Fundos de Participações | O38: Alternativo Ilíquido | P38: FIP | Q38: 25000 | R38: FECHADO | S38: - | T38: 0.01 | U38: 0.01 | V38: Fechamento | W38: D+0 | X38: D+0 | Y38: D+0 | Z38: 0 | AA38: - | AB38: - | AC38: - | AD38: 0.02 | AE38: - | AF38: - | AG38: 0.2 | AH38: Maio / Maio | AI38: Abril / Abril | AJ38: - | AK38: 44742 | AL38: https://www.xpi.com.br/investimentos/fundos-de-investimento/lista/#/detalhes/80643c51-8fa6-47dd-a76f-f93b08459936 | AM38: - | AN38: - | AO38: - | AP38: - | AQ38: - | AR38: - | AS38: - | AT38: - | AU38: - | AV38: - | AW38: - | AX38: - | AY38: - | AZ38: - | BA38: - | BB38: - | BC38: - | BD38: - | BE38: - | BF38: - | BG38: - | BH38: - | BI38: - | BJ38: - | BK38: - | BL38: - | BM38: - | BN38: - | BO38: - | BP38: - | BQ38: - | BR38: - | BS38: - | BT38: 0.0547621 | BU38: 0.92482994 | BV38: -2.5890689 | BW38: 0.11554968 | BX38: -0.038120819 | BY38: -0.73080646 | BZ38: 0.7371755 | CA38: -0.0038412672 | CB38: 0.10698222 | CC38: -0.052872562 | CD38: -0.040308065 | CE38: 0.05119309 | CF38: 0.016057241 | CG38: 834.08177 | CH38: 0.15 | CI38: 0.05 | CJ38: 0.003 | CK38: - | CL38: 0.003 | CM38: 24850390 | CN38: 22679169 | CO38: 2736795.3 | CP38: - | CQ38: - | CR38: - | CS38: - | CT38: - | CU38: - | CV38: BR0BXFCTF004 | CW38: - | CX38: 25569.605
B39: 21689246000192 | C39: Arbor FIC FIA RL | D39: 40 | E39: Sim | F39: ««««« | G39: Arbor Capital | H39: BTG Pactual Serviços Financeiros | I39: Banco BTG Pactual | J39: PriceWaterhouseCoopers | K39: Geral | L39: Investidores qualificados | M39: Ações | N39: Ações Livre | O39: Internacional Ações Hedgeado | P39: Renda Variavel | Q39: 1000 | R39: ABERTO | S39: - | T39: 1000 | U39: 1000 | V39: Fechamento | W39: D+0 | X39: D+10 (útil) | Y39: D+2 (útil) | Z39: 12 | AA39: Sim | AB39: 0.1 | AC39: ARBOR FIC AÇÕES | AD39: 0.0187 | AE39: 0.1487 | AF39: 0.02 | AG39: 0.2 | AH39: Dezembro / Junho | AI39: Novembro / Maio | AJ39: - | AK39: 42086 | AL39: https://www.xpi.com.br/investimentos/fundos-de-investimento/lista/#/detalhes/30813569-17e1-442b-b5cd-f1bde5308c79 | AM39: 0.10515689 | AN39: 0.0071518636 | AO39: 0.33025541 | AP39: 0.22626185 | AQ39: 0.31579467 | AR39: 0.28919683 | AS39: 0.55843799 | AT39: -0.3000415 | AU39: - | AV39: - | AW39: 0.2088146 | AX39: 9.639125 | AY39: 0.15752187 | AZ39: 2.2273183 | BA39: 1.7973831 | BB39: 2.9115283 | BC39: 2.6595324 | BD39: 4.2800582 | BE39: - | BF39: - | BG39: - | BH39: 3.9233715 | BI39: 0.094247511 | BJ39: -0.038250489 | BK39: 0.1819805 | BL39: 0.089154661 | BM39: 0.1870437 | BN39: 0.1804571 | BO39: 0.4279636 | BP39: -0.42377154 | BQ39: - | BR39: - | BS39: 0.14772874 | BT39: 0.15889969 | BU39: 0.22442211 | BV39: 1.0054391 | BW39: 0.54018912 | BX39: -0.1425049 | BY39: -0.46102129 | BZ39: 0.48862946 | CA39: 0.37925941 | CB39: -0.28901369 | CC39: 0.39288099 | CD39: 0.30312038 | CE39: 0.63216642 | CF39: 0.51837919 | CG39: 8.1382718 | CH39: 0.3 | CI39: 0.2 | CJ39: 0.00561 | CK39: - | CL39: 0.00561 | CM39: 2.8794484e+08 | CN39: 2.9095341e+08 | CO39: -20458446 | CP39: - | CQ39: - | CR39: - | CS39: - | CT39: - | CU39: - | CV39: BRLBF4CTF005 | CW39: - | CX39: 25569.626
B40: 47756349000111 | C40: Arbor II FIC FIA RL | D40: 26 | G40: Arbor Capital | H40: BTG Pactual Serviços Financeiros | I40: Banco BTG Pactual | J40: EY | K40: Geral | L40: Investidores em geral | M40: Ações | N40: Ações Livre | O40: Internacional Ações Hedgeado | P40: Ações | Q40: 1000 | R40: ABERTO | S40: - | T40: 100 | U40: 1000 | V40: Fechamento | W40: D+0 | X40: D+10 (útil) | Y40: D+2 (útil) | Z40: 12 | AA40: - | AB40: - | AC40: ARBOR II FIC AÇÕES | AD40: 0.0187 | AE40: 0.1487 | AF40: 0.02 | AG40: 0.2 | AH40: Março / Setembro | AI40: Fevereiro / Agosto | AJ40: MSCI World | AK40: 44825 | AL40: https://www.xpi.com.br/investimentos/fundos-de-investimento/lista/#/detalhes/ae1bc073-b77c-4821-9748-94f1027e29a8 | AM40: 0.10520909 | AN40: 0.0071488932 | AO40: 0.33266812 | AP40: 0.22918407 | AQ40: 0.30556231 | AR40: 0.28068198 | AS40: 0.51045611 | AT40: - | AU40: - | AV40: - | AW40: 0.28869751 | AX40: 9.6439096 | AY40: 0.15745645 | AZ40: 2.2435902 | BA40: 1.8229864 | BB40: 2.7913952 | BC40: 2.5812275 | BD40: 3.9123087 | BE40: - | BF40: - | BG40: - | BH40: 2.6919213 | BI40: 0.094299707 | BJ40: -0.038253459 | BK40: 0.18439322 | BL40: 0.091910188 | BM40: 0.17674858 | BN40: 0.17194225 | BO40: 0.37998171 | BP40: - | BQ40: - | BR40: - | BS40: 0.16387653 | BT40: 0.16278997 | BU40: 0.18829547 | BV40: 0.99647103 | BW40: 0.79117489 | BX40: -0.14621573 | BY40: -0.22162938 | BZ40: 0.36983508 | CA40: 0.3828837 | CB40: -0.29745119 | CC40: 0.39381101 | CD40: 0.30428892 | CE40: 0.63817676 | CF40: 0.53140969 | CG40: 248.39613 | CH40: 0.3 | CI40: 0.2 | CJ40: 0.00561 | CK40: 0.0074438169 | CL40: 0.013053817 | CM40: 1.9089401e+08 | CN40: 1.793622e+08 | CO40: 18247533 | CP40: - | CQ40: - | CR40: - | CS40: - | CT40: - | CU40: - | CV40: BR0DDMCTF008 | CW40: - | CX40: 25569.626
B41: 34172497000147 | C41: ARMOR AXE FIC FIM RL | D41: 13 | G41: Armor Gestora de Investimentos | H41: BTG Pactual Serviços Financeiros | I41: Banco BTG Pactual | J41: PriceWaterhouseCoopers | K41: Intranet | L41: Investidores em geral | M41: Multimercado | N41: Multimercados Livre | O41: Macro Média Vol | P41: Longo Prazo | Q41: 5000 | R41: FECHADO | S41: - | T41: 1000 | U41: 1000 | V41: Fechamento | W41: D+0 | X41: D+20 (corridos) | Y41: D+2 (útil) | Z41: 22 | AA41: - | AB41: - | AC41: ARMOR AXE FIF CIC MULTIMERCADO | AD41: 0.02 | AE41: 0.22 | AF41: 0.022 | AG41: 0.2 | AH41: Janeiro / Julho | AI41: Junho | AJ41: CDI | AK41: 43761 | AL41: https://www.xpi.com.br/investimentos/fundos-de-investimento/lista/#/detalhes/3919a50f-ccc4-4f28-9aeb-6a41a79df1e4 | AM41: 0.02104036 | AN41: 0.044299876 | AO41: 0.13356507 | AP41: 0.13955449 | AQ41: 0.14750658 | AR41: 0.14372159 | AS41: 0.15480006 | AT41: 0.21885702 | AU41: - | AV41: - | AW41: 0.15220898 | AX41: 1.9286483 | AY41: 0.97571765 | AZ41: 0.90079349 | BA41: 1.0654186 | BB41: 1.1641134 | BC41: 1.3217027 | BD41: 1.1864402 | BE41: 1.7688269 | BF41: - | BG41: - | BH41: 1.8343026 | BI41: 0.010130978 | BJ41: -0.001102476 | BK41: -0.014709836 | BL41: 0.007576479 | BM41: 0.018456422 | BN41: 0.034981859 | BO41: 0.024325671 | BP41: 0.095126981 | BQ41: - | BR41: - | BS41: 0.063925299 | BT41: 0.025069798 | BU41: 0.11292966 | BV41: -0.50207113 | BW41: 0.4932093 | BX41: -0.012397159 | BY41: -0.22209324 | BZ41: 0.24713115 | CA41: 0.6334116 | CB41: -0.49478314 | CC41: 0.61876492 | CD41: 0.54996125 | CE41: 0.18233506 | CF41: 0.73323113 | CG41: 2.5073828 | CH41: 0.24 | CI41: - | CJ41: 0.0048 | CK41: - | CL41: 0.0048 | CM41: 1.02782e+09 | CN41: 9.7601868e+08 | CO41: 51367727 | CP41: - | CQ41: - | CR41: - | CS41: - | CT41: - | CU41: - | CV41: BR0DO4CTF001 | CW41: - | CX41: 25569.605
B42: 20441301000168 | C42: Artesanal CP FIDC RL | D42: 14 | F42: ««««« | G42: Artesanal Investimentos | H42: Genial Investimentos | I42: Banco B3 | J42: Grant Thornton | K42: Geral | L42: Investidores qualificados | M42: Direito Creditório | N42: Multimercados Dinâmico | O42: Crédito High Yield | P42: FIDC_x000D_ | Q42: 5019 | R42: FECHADO | S42: - | T42: 5000 | U42: 5000 | V42: Fechamento | W42: D+0 | X42: D+90 (corridos) | Y42: D+1 (útil) | Z42: 91 | AA42: - | AB42: - | AC42: ARTESANAL CRÉDITO PRIVADO RESP LIMITADA FIDC 1 | AD42: 0.02 | AE42: 0.125 | AF42: 0.02 | AG42: 0.2 | AH42: - | AI42: - | AJ42: CDI | AK42: 41838 | AL42: https://www.xpi.com.br/investimentos/fundos-de-investimento/lista/#/detalhes/325a6d9d-31e8-44c0-9957-dee802d81154 | AM42: 0.013345741 | AN42: 0.05514073 | AO42: - | AP42: 0.19298327 | AQ42: 0.17799578 | AR42: 0.13781446 | AS42: 0.16031954 | AT42: 0.15152839 | AU42: - | AV42: - | AW42: 0.13886164 | AX42: 1.223327 | AY42: 1.2144906 | AZ42: - | BA42: - | BB42: - | BC42: 1.2673791 | BD42: 1.2287433 | BE42: 1.2246694 | BF42: - | BG42: - | BH42: - | BI42: 0.0024363591 | BJ42: 0.0097383781 | BK42: - | BL42: - | BM42: - | BN42: 0.029074732 | BO42: 0.029845145 | BP42: 0.027798352 | BQ42: - | BR42: - | BS42: - | BT42: - | BU42: - | BV42: - | BW42: - | BX42: - | BY42: - | BZ42: - | CA42: - | CB42: - | CC42: - | CD42: - | CE42: - | CF42: - | CG42: 4.4332986 | CH42: 0.3 | CI42: - | CJ42: 0.006 | CK42: - | CL42: 0.006 | CM42: 2.4989446e+09 | CN42: 2.4746921e+09 | CO42: -2.6991795e+08 | CP42: - | CQ42: - | CR42: - | CS42: - | CT42: - | CU42: - | CV42: BRATS8CTF004 | CW42: - | CX42: 25569.605
B43: 41888219000156 | C43: Arx Denali Advisory FIC de FIF RF CP RL | D43: 2 | G43: ARX Investimentos | H43: BNY Mellon Serviços Financeiros | I43: BNY Mellon Banco | J43: KPMG | K43: Geral | L43: Investidores em geral | M43: Renda Fixa | N43: Renda Fixa Duração Baixa Grau de Investimento | O43: Crédito Liquidez | P43: Longo Prazo_x000D_ | Q43: 500 | R43: ABERTO | S43: - | T43: 100 | U43: 500 | V43: Fechamento | W43: D+0 | X43: D+0 | Y43: D+1 (útil) | Z43: 1 | AA43: - | AB43: - | AC43: ARX DENALI ADVISORY RESP LIMITADA FIF CIC RENDA FIXA CRÉDITO PRIVADO | AD43: 0.004 | AE43: 0.004 | AF43: 0.007 | AG43: - | AH43: - | AI43: - | AJ43: CDI | AK43: 44413 | AL43: https://www.xpi.com.br/investimentos/fundos-de-investimento/lista/#/detalhes/c218eb09-7b3b-4491-b242-280898b46a76 | AM43: 0.011376612 | AN43: 0.041909179 | AO43: 0.14567562 | AP43: 0.13416932 | AQ43: 0.13342269 | AR43: 0.11520677 | AS43: 0.12415098 | AT43: 0.13582748 | AU43: - | AV43: - | AW43: 0.12735 | AX43: 1.0428283 | AY43: 0.92306185 | AZ43: 0.98246978 | BA43: 1.0217277 | BB43: 1.0389192 | BC43: 1.0594726 | BD43: 0.95153519 | BE43: 1.0977729 | BF43: - | BG43: - | BH43: 1.0436044 | BI43: 0.0004672307 | BJ43: -0.003493173 | BK43: -0.0025992921 | BL43: 0.0025220161 | BM43: 0.004429346 | BN43: 0.0064670372 | BO43: -0.006323417 | BP43: 0.01209744 | BQ43: - | BR43: - | BS43: 0.0047422992 | BT43: 0.0028617715 | BU43: 0.0037126778 | BV43: -0.79090002 | BW43: 1.0420605 | BX43: -0.00030029316 | BY43: -0.0041200067 | BZ43: 0.0014116837 | CA43: 0.039172081 | CB43: -0.095496519 | CC43: -0.0052860785 | CD43: -0.063356032 | CE43: -0.046826404 | CF43: -0.014702571 | CG43: 1.7596242 | CH43: 0.28 | CI43: - | CJ43: 0.00112 | CK43: - | CL43: 0.00112 | CM43: 1.6075966e+09 | CN43: 1.7169669e+09 | CO43: -2.8755061e+08 | CP43: - | CQ43: - | CR43: - | CS43: - | CT43: - | CU43: - | CV43: BR0967CTF002 | CW43: - | CX43: 25569.626
B44: 32319627000104 | C44: ARX Elbrus Advisory FIC Incentivado FIF em Infra RF RL | D44: 10 | F44: «««« | G44: ARX Investimentos | H44: BNY Mellon Serviços Financeiros | I44: BNY Mellon Banco | J44: Deloitte Touche Tohmatsu | K44: Geral | L44: Investidores em geral | M44: Renda Fixa | N44: Renda Fixa Duração Livre Grau de Investimento | O44: Debêntures Incentivadas Não Hedgeado | P44: Debêntures Incentivadas - Isento de IR para pessoa física. | Q44: 500 | R44: ABERTO | S44: - | T44: 100 | U44: 100 | V44: Fechamento | W44: D+0 | X44: D+30 (corridos) | Y44: D+1 (útil) | Z44: 31 | AA44: - | AB44: - | AC44: ARX ELBRUS ADVISORY RESP LIMITADA FIF CIC FI INFRA RENDA FIXA | AD44: 0.007 | AE44: 0.007 | AF44: 0.01 | AG44: - | AH44: Janeiro / Julho | AI44: Junho | AJ44: IMA-B 5 | AK44: 43549 | AL44: https://www.xpi.com.br/investimentos/fundos-de-investimento/lista/#/detalhes/4bf42f19-0b78-42e0-a410-dad4e0518f8c | AM44: -0.0067399533 | AN44: 0.025621486 | AO44: 0.1108459 | AP44: 0.10177527 | AQ44: 0.12580231 | AR44: 0.086278181 | AS44: 0.14983915 | AT44: 0.073428149 | AU44: - | AV44: - | AW44: 0.1021373 | AX44: - | AY44: 0.56432068 | AZ44: 0.7475702 | BA44: 0.76327605 | BB44: 0.9724639 | BC44: 0.79343752 | BD44: 1.1484181 | BE44: 0.59345452 | BF44: - | BG44: - | BH44: 1.1170127 | BI44: -0.017649335 | BJ44: -0.019780866 | BK44: -0.037429005 | BL44: -0.027851116 | BM44: -0.0031541581 | BN44: -0.022461548 | BO44: 0.019364757 | BP44: -0.050301886 | BQ44: - | BR44: - | BS44: 0.0098030245 | BT44: 0.026529444 | BU44: 0.03569554 | BV44: -1.2365298 | BW44: 0.22973662 | BX44: -0.016466144 | BY44: -0.063215073 | BZ44: 0.079619575 | CA44: 0.51331188 | CB44: -0.3835592 | CC44: 0.71648362 | CD44: 0.75487543 | CE44: 0.0072024716 | CF44: 0.61410322 | CG44: 1.9906823 | CH44: 0.28 | CI44: - | CJ44: 0.00196 | CK44: - | CL44: 0.00196 | CM44: 1.2775703e+09 | CN44: 1.2047337e+09 | CO44: 1.1919653e+08 | CP44: - | CQ44: - | CR44: - | CS44: - | CT44: - | CU44: - | CV44: BR01A8CTF008 | CW44: - | CX44: 25569.626
B45: 39959156000130 | C45: ARX Elbrus Pro Advisory I FIC Incentivado FIF Infra RF RL | D45: 10 | G45: ARX Investimentos | H45: BNY Mellon Serviços Financeiros | I45: BNY Mellon Banco | J45: KPMG | K45: Geral | L45: Investidores em geral | M45: Renda Fixa | N45: Renda Fixa Duração Livre Grau de Investimento | O45: Debêntures Incentivadas Não Hedgeado | P45: Debêntures Incentivadas - Isento de IR para pessoa física._x000D_ | Q45: 100 | R45: ABERTO | S45: - | T45: 100 | U45: 100 | V45: Fechamento | W45: D+0 | X45: D+30 (corridos) | Y45: D+1 (útil) | Z45: 31 | AA45: - | AB45: - | AC45: ARX ELBRUS PRO ADVISORY I RESP LIMITADA FIF CIC FI INFRA RENDA FIXA | AD45: 0.007 | AE45: 0.007 | AF45: 0.01 | AG45: - | AH45: - | AI45: - | AJ45: IMA-B | AK45: 44295 | AL45: https://www.xpi.com.br/investimentos/fundos-de-investimento/lista/#/detalhes/4f0eb578-dc8b-492c-a593-b762779f1e6a | AM45: -0.0004810625 | AN45: 0.026759721 | AO45: 0.12174266 | AP45: 0.082488396 | AQ45: 0.10910766 | AR45: 0.0049421645 | AS45: 0.17351828 | AT45: 0.038910849 | AU45: - | AV45: - | AW45: 0.086508738 | AX45: - | AY45: 0.58939062 | AZ45: 0.82106045 | BA45: 0.61295492 | BB45: 0.82998918 | BC45: 0.045449483 | BD45: 1.329903 | BE45: 0.31448184 | BF45: - | BG45: - | BH45: 0.69437089 | BI45: -0.011390444 | BJ45: -0.018642632 | BK45: -0.026532246 | BL45: -0.045908455 | BM45: -0.019752471 | BN45: -0.10379756 | BO45: 0.043043891 | BP45: -0.084819187 | BQ45: - | BR45: - | BS45: -0.033858724 | BT45: 0.050617374 | BU45: 0.058159969 | BV45: -0.43686411 | BW45: -0.44922537 | BX45: -0.030963355 | BY45: -0.071854298 | BZ45: 0.15145554 | CA45: 0.53496521 | CB45: -0.41094371 | CC45: 0.79679248 | CD45: 0.92221415 | CE45: 0.016347299 | CF45: 0.65949499 | CG45: 1.5191337 | CH45: 0.28 | CI45: - | CJ45: 0.00196 | CK45: - | CL45: 0.00196 | CM45: 1.2608775e+08 | CN45: 1.0553399e+08 | CO45: 36488491 | CP45: - | CQ45: - | CR45: - | CS45: - | CT45: - | CU45: - | CV45: BR07V3CTF008 | CW45: - | CX45: 25569.626
B46: 35789436000196 | C46: ARX Everest Advisory FIC de FIF RF CP RL | D46: 5 | F46: «««« | G46: ARX Investimentos | H46: BNY Mellon Serviços Financeiros | I46: BNY Mellon Banco | J46: Deloitte Touche Tohmatsu | K46: Geral | L46: Investidores qualificados | M46: Renda Fixa | N46: Renda Fixa Duração Baixa Grau de Investimento | O46: Crédito High Grade | P46: Longo Prazo - Alíquota regressiva de IR de 22,5% a 15,0% incidida sobre o lucro obtido no momento do resgate. | Q46: 500 | R46: ABERTO | S46: - | T46: 100 | U46: 100 | V46: Fechamento | W46: D+0 | X46: D+60 (corridos) | Y46: D+1 (útil) | Z46: 61 | AA46: - | AB46: - | AC46: ARX EVEREST ADVISORY RESP LIMITADA FIF CIC RENDA FIXA CRÉDITO PRIVADO | AD46: 0.007 | AE46: 0.007 | AF46: 0.01 | AG46: - | AH46: - | AI46: - | AJ46: CDI | AK46: 43866 | AL46: https://www.xpi.com.br/investimentos/fundos-de-investimento/lista/#/detalhes/9afa4e37-49f6-48fc-9819-72df92d3cbf8 | AM46: 0.012434786 | AN46: 0.035181686 | AO46: 0.13522744 | AP46: 0.13765475 | AQ46: 0.13419328 | AR46: 0.14159295 | AS46: 0.09449047 | AT46: 0.15370109 | AU46: - | AV46: - | AW46: 0.11210102 | AX46: 1.139825 | AY46: 0.77488685 | AZ46: 0.91200487 | BA46: 1.049982 | BB46: 1.0456894 | BC46: 1.3021271 | BD46: 0.72420701 | BE46: 1.2422294 | BF46: - | BG46: - | BH46: 1.1688697 | BI46: 0.0015254045 | BJ46: -0.010220666 | BK46: -0.01304747 | BL46: 0.0057932379 | BM46: 0.0051964535 | BN46: 0.03285322 | BO46: -0.035983924 | BP46: 0.02997105 | BQ46: - | BR46: - | BS46: 0.014778218 | BT46: 0.0089743636 | BU46: 0.010976359 | BV46: -1.269576 | BW46: 1.0672654 | BX46: -0.0019808393 | BY46: -0.035932459 | BZ46: 0.00099498953 | CA46: 0.028177225 | CB46: -0.058872934 | CC46: -0.046314131 | CD46: -0.081629651 | CE46: -0.012768384 | CF46: -0.046086023 | CG46: 1.9328767 | CH46: 0.28 | CI46: - | CJ46: 0.00196 | CK46: - | CL46: 0.00196 | CM46: 4.3349713e+08 | CN46: 4.5922952e+08 | CO46: -64387286 | CP46: - | CQ46: - | CR46: - | CS46: - | CT46: - | CU46: - | CV46: BR03O2CTF003 | CW46: - | CX46: 25569.626
B47: 6041290000106 | C47: ARX Extra FIC de FIF Multimercado RL | D47: 16 | F47: ««« | G47: ARX Investimentos | H47: BNY Mellon Serviços Financeiros | I47: BNY Mellon Banco | J47: KPMG | K47: Intranet | L47: Investidores em geral | M47: Multimercado | N47: Multimercados Livre | O47: Macro Alta Vol | P47: Longo Prazo - Alíquota regressiva de IR de 22,5% a 15,0% incidida sobre o lucro obtido no momento do resgate. | Q47: 1000 | R47: FECHADO | S47: - | T47: 1000 | U47: 1000 | V47: Fechamento | W47: D+1 (útil) | X47: D+4 (corridos) | Y47: D+1 (útil) | Z47: 5 | AA47: - | AB47: - | AC47: ARX EXTRA RESP LIMITADA FIF CIC MULTIMERCADO | AD47: 0.02 | AE47: 0.02 | AF47: 0.025 | AG47: 0.2 | AH47: Janeiro / Julho | AI47: Junho | AJ47: CDI | AK47: 37978 | AL47: https://www.xpi.com.br/investimentos/fundos-de-investimento/lista/#/detalhes/aa21add5-f0c2-4cb0-9eb4-e722ba30a557 | AM47: 0.0042173361 | AN47: 0.022192921 | AO47: 0.085409585 | AP47: 0.093798088 | AQ47: 0.079357185 | AR47: 0.051444718 | AS47: -0.030797252 | AT47: -0.047607734 | AU47: - | AV47: - | AW47: 0.12363336 | AX47: 0.38657884 | AY47: 0.48880554 | AZ47: 0.57602184 | BA47: 0.70078028 | BB47: 0.58652658 | BC47: 0.47309957 | BD47: - | BE47: - | BF47: - | BG47: - | BH47: 1.360495 | BI47: -0.0066920454 | BJ47: -0.023209431 | BK47: -0.062865323 | BL47: -0.035322177 | BM47: -0.049275997 | BN47: -0.05729501 | BO47: -0.16127165 | BP47: -0.17133777 | BQ47: - | BR47: - | BS47: 0.030030563 | BT47: 0.039953274 | BU47: 0.073792119 | BV47: -1.38995 | BW47: 0.20829386 | BX47: -0.027278943 | BY47: -0.21720449 | BZ47: 0.12474597 | CA47: 0.4510457 | CB47: -0.26422165 | CC47: 0.63060823 | CD47: 0.44570929 | CE47: 0.082886772 | CF47: 0.61001116 | CG47: 13.384396 | CH47: 0.21 | CI47: 0.1 | CJ47: 0.0042 | CK47: - | CL47: 0.0042 | CM47: 21421420 | CN47: 22728146 | CO47: -3910193.1 | CP47: - | CQ47: - | CR47: - | CS47: - | CT47: - | CU47: - | CV47: BRARXECTF006 | CW47: - | CX47: 25569.626
B48: 58198613000165 | C48: ARX FII Portfólio Renda CDI+ RL | D48: 15 | G48: ARX Investimentos | H48: XP Investimentos | I48: Oliveira Trust | J48: PriceWaterhouseCoopers | K48: Geral | L48: Não definido | M48: Investimento Imobiliário | N48: - | O48: Fundo Listado | P48: FII | Q48: 100 | R48: FECHADO | S48: - | T48: 0.01 | U48: 0.01 | V48: Fechamento | W48: D+0 | X48: D+0 | Y48: D+0 | Z48: 0 | AA48: - | AB48: - | AC48: - | AD48: 0.01 | AE48: - | AF48: - | AG48: 0.2 | AH48: Janeiro / Julho | AI48: Junho | AJ48: CDI | AK48: 45663 | AL48: https://www.xpi.com.br/investimentos/fundos-de-investimento/lista/#/detalhes/60f4711e-ecf8-49fa-9bf7-834852160680 | AM48: - | AN48: - | AO48: - | AP48: - | AQ48: - | AR48: - | AS48: - | AT48: - | AU48: - | AV48: - | AW48: - | AX48: - | AY48: - | AZ48: - | BA48: - | BB48: - | BC48: - | BD48: - | BE48: - | BF48: - | BG48: - | BH48: - | BI48: - | BJ48: - | BK48: - | BL48: - | BM48: - | BN48: - | BO48: - | BP48: - | BQ48: - | BR48: - | BS48: - | BT48: - | BU48: - | BV48: - | BW48: - | BX48: - | BY48: - | BZ48: - | CA48: - | CB48: - | CC48: - | CD48: - | CE48: - | CF48: - | CG48: - | CH48: 0.15 | CI48: 0.1 | CJ48: 0.0015 | CK48: - | CL48: 0.0015 | CM48: - | CN48: - | CO48: - | CP48: - | CQ48: - | CR48: - | CS48: - | CT48: - | CU48: - | CV48: - | CW48: - | CX48: 25569.626
B49: 52286231000107 | C49: ARX Fuji FIC de FIF RF CP RL | D49: 4 | G49: ARX Investimentos | H49: BNY Mellon Serviços Financeiros | I49: BNY Mellon Banco | J49: KPMG | K49: Geral | L49: Investidores em geral | M49: Renda Fixa | N49: Renda Fixa Duração Baixa Crédito Livre | O49: Crédito Liquidez | P49: Longo Prazo | Q49: 1000 | R49: ABERTO | S49: - | T49: 1000 | U49: 1000 | V49: Fechamento | W49: D+0 | X49: D+0 | Y49: D+1 (útil) | Z49: 1 | AA49: - | AB49: - | AC49: ARX FUJI RESP LIMITADA FIF CIC RENDA FIXA CRÉDITO PRIVADO | AD49: 0.003 | AE49: 0.003 | AF49: 0.006 | AG49: - | AH49: - | AI49: - | AJ49: CDI | AK49: 45198 | AL49: https://www.xpi.com.br/investimentos/fundos-de-investimento/lista/#/detalhes/01494874-9d83-402f-8178-dd36996d6882 | AM49: 0.010728661 | AN49: 0.045782647 | AO49: 0.15366279 | AP49: 0.13942868 | AQ49: - | AR49: 0.12332949 | AS49: - | AT49: - | AU49: - | AV49: - | AW49: 0.13976531 | AX49: 0.98343439 | AY49: 1.0083761 | AZ49: 1.0363371 | BA49: 1.0643955 | BB49: - | BC49: 1.1341714 | BD49: - | BE49: - | BF49: - | BG49: - | BH49: 1.1009078 | BI49: -0.00018072052 | BJ49: 0.00038029504 | BK49: 0.0053878859 | BL49: 0.0074583764 | BM49: - | BN49: 0.014589759 | BO49: - | BP49: - | BQ49: - | BR49: - | BS49: 0.01136755 | BT49: 0.0018831795 | BU49: 0.0020391586 | BV49: 2.4881091 | BW49: 5.0644429 | BX49: - | BY49: - | BZ49: 0.00011847252 | CA49: 0.0070054938 | CB49: -0.029093535 | CC49: -0.0049348175 | CD49: 0.036747365 | CE49: -0.02085536 | CF49: 0.007230332 | CG49: 1.3991729 | CH49: 0.28 | CI49: - | CJ49: 0.00084 | CK49: - | CL49: 0.00084 | CM49: 8.2944621e+09 | CN49: 6.3277387e+09 | CO49: 3.2923975e+09 | CP49: - | CQ49: - | CR49: - | CS49: - | CT49: - | CU49: - | CV49: BR0H1QCTF006 | CW49: - | CX49: 25569.626
B50: 32225663000109 | C50: ARX Hedge FIC Incentivado Financeiro em Infra RF RL | D50: 11 | F50: ««« | G50: ARX Investimentos | H50: BNY Mellon Serviços Financeiros | I50: BNY Mellon Banco | J50: Deloitte Touche Tohmatsu | K50: Geral | L50: Investidores em geral | M50: Renda Fixa | N50: Renda Fixa Duração Livre Crédito Livre | O50: Debêntures Incentivadas Hedgeado | P50: Debêntures Incentivadas - Isento de IR para pessoa física. | Q50: 3000 | R50: ABERTO | S50: - | T50: 1000 | U50: 1000 | V50: Fechamento | W50: D+0 | X50: D+30 (corridos) | Y50: D+2 (útil) | Z50: 32 | AA50: - | AB50: - | AC50: ARX HEDGE INCENTIVADO RESP LIMITADA FIF CIC FI INFRA RENDA FIXA | AD50: 0.007 | AE50: 0.007 | AF50: 0.012 | AG50: - | AH50: - | AI50: - | AJ50: CDI | AK50: 43462 | AL50: https://www.xpi.com.br/investimentos/fundos-de-investimento/lista/#/detalhes/aa6627fa-ee2d-4c0c-8ffd-fb82f8997c69 | AM50: -0.010804545 | AN50: 0.01980202 | AO50: 0.14292083 | AP50: 0.1377871 | AQ50: 0.16475629 | AR50: 0.16395051 | AS50: 0.14973439 | AT50: 0.11889242 | AU50: - | AV50: - | AW50: 0.10579889 | AX50: - | AY50: 0.43614525 | AZ50: 0.96389085 | BA50: 1.0510566 | BB50: 1.3216918 | BC50: 1.5077333 | BD50: 1.1476151 | BE50: 0.96090182 | BF50: - | BG50: - | BH50: 1.1878065 | BI50: -0.021713927 | BJ50: -0.025600332 | BK50: -0.0053540812 | BL50: 0.0059174666 | BM50: 0.03565597 | BN50: 0.055210786 | BO50: 0.019259997 | BP50: -0.0048376189 | BQ50: - | BR50: - | BS50: 0.015359951 | BT50: 0.01845461 | BU50: 0.016473405 | BV50: -0.24419847 | BW50: 0.72157741 | BX50: -0.021430799 | BY50: -0.021430799 | BZ50: -0.0056113641 | CA50: -0.094439918 | CB50: -0.019265373 | CC50: -0.17137058 | CD50: -0.26440458 | CE50: -0.042084481 | CF50: -0.1183976 | CG50: 2.0857 | CH50: 0.28 | CI50: - | CJ50: 0.00196 | CK50: - | CL50: 0.00196 | CM50: 1.9943773e+09 | CN50: 2.1378558e+09 | CO50: -3.1620341e+08 | CP50: - | CQ50: - | CR50: - | CS50: - | CT50: - | CU50: - | CV50: BR00U9CTF003 | CW50: - | CX50: 25569.626
B51: 3168062000103 | C51: ARX Income FIC de FIF em Ações RL | D51: 26 | F51: «««« | G51: ARX Investimentos | H51: BNY Mellon Serviços Financeiros | I51: BNY Mellon Banco | J51: KPMG | K51: Geral | L51: Investidores em geral | M51: Ações | N51: Ações Dividendos | O51: Renda Variável Dividendos | P51: Renda Variável - Alíquota de IR de 15% incidida sobre o lucro obtido no momento do resgate. | Q51: 500 | R51: ABERTO | S51: - | T51: 100 | U51: 100 | V51: Fechamento | W51: D+0 | X51: D+1 (útil) | Y51: D+2 (útil) | Z51: 3 | AA51: - | AB51: - | AC51: ARX INCOME RESP LIMITADA FIF CIC AÇÕES | AD51: 0.0294 | AE51: 0.0944 | AF51: 0.0325 | AG51: - | AH51: - | AI51: - | AJ51: Ibovespa | AK51: 36328 | AL51: https://www.xpi.com.br/investimentos/fundos-de-investimento/lista/#/detalhes/04a40ccf-24a2-4fec-9a0b-e3c42c750732 | AM51: -0.013918338 | AN51: 0.13130428 | AO51: 0.34349361 | AP51: 0.22589109 | AQ51: 0.24598798 | AR51: -0.066449197 | AS51: 0.16143678 | AT51: -0.02826069 | AU51: - | AV51: - | AW51: 0.19283559 | AX51: - | AY51: 2.892015 | AZ51: 2.3165997 | BA51: 1.7941391 | BB51: 2.1286009 | BC51: - | BD51: 1.2373063 | BE51: - | BF51: - | BG51: - | BH51: 5.2038079 | BI51: -0.024827719 | BJ51: 0.085901931 | BK51: 0.19521871 | BL51: 0.088805081 | BM51: 0.11691382 | BN51: -0.17518893 | BO51: 0.030962391 | BP51: -0.15199073 | BQ51: - | BR51: - | BS51: 0.15021259 | BT51: 0.17671472 | BU51: 0.21740356 | BV51: 0.97734649 | BW51: 0.38658835 | BX51: -0.10059689 | BY51: -0.53933643 | BZ51: 0.70107058 | CA51: 0.97017618 | CB51: -0.47812128 | CC51: 0.66133737 | CD51: 0.53293375 | CE51: 0.076883917 | CF51: 0.76555025 | CG51: 111.66652 | CH51: 0.24 | CI51: 0.15 | CJ51: 0.007056 | CK51: - | CL51: 0.007056 | CM51: 2.5362858e+08 | CN51: 2.3654252e+08 | CO51: 6636475.8 | CP51: - | CQ51: - | CR51: - | CS51: - | CT51: - | CU51: - | CV51: BRINCOCTF001 | CW51: - | CX51: 25569.626
B52: 57134507000155 | C52: Arx Infra Renda CDI FI Incentivado Infraestrutura RF CP RL | D52: 11 | G52: ARX Investimentos | H52: XP Investimentos | I52: Banco Bradesco | J52: PriceWaterhouseCoopers | K52: Geral | L52: Investidores em geral | M52: Renda Fixa | N52: Renda Fixa Duração Livre Crédito Livre | O52: Debêntures Incentivadas Hedgeado | P52: Debêntures Incentivadas | Q52: 500 | R52: ABERTO | S52: - | T52: 500 | U52: 500 | V52: Fechamento | W52: D+0 | X52: D+30 (corridos) | Y52: D+1 (útil) | Z52: 31 | AA52: - | AB52: - | AC52: - | AD52: 0.009 | AE52: - | AF52: 0.0099 | AG52: - | AH52: - | AI52: - | AJ52: CDI | AK52: 45580 | AL52: https://www.xpi.com.br/investimentos/fundos-de-investimento/lista/#/detalhes/b055d9de-9ac9-4f7d-844e-1ec7f5c1af5e | AM52: -0.018924789 | AN52: -0.027032033 | AO52: -0.020308295 | AP52: - | AQ52: - | AR52: - | AS52: - | AT52: - | AU52: - | AV52: - | AW52: -0.010590871 | AX52: - | AY52: - | AZ52: - | BA52: - | BB52: - | BC52: - | BD52: - | BE52: - | BF52: - | BG52: - | BH52: - | BI52: -0.029834171 | BJ52: -0.072434385 | BK52: -0.1685832 | BL52: - | BM52: - | BN52: - | BO52: - | BP52: - | BQ52: - | BR52: - | BS52: -0.13619893 | BT52: 0.044465674 | BU52: 0.041018614 | BV52: -3.5493391 | BW52: -3.4330264 | BX52: -0.050686499 | BY52: -0.050686499 | BZ52: -0.019372437 | CA52: -0.062300099 | CB52: 0.091691455 | CC52: -0.069682831 | CD52: -0.087526603 | CE52: 0.044158115 | CF52: -0.10588869 | CG52: 0.9838648 | CH52: 0.27 | CI52: - | CJ52: 0.00243 | CK52: - | CL52: 0.00243 | CM52: 3.2137263e+08 | CN52: 2.7792701e+08 | CO52: 1.192676e+08 | CP52: - | CQ52: - | CR52: - | CS52: - | CT52: - | CU52: - | CV52: BR0LWQCTF002 | CW52: - | CX52: 25569.626
B53: 10237480000162 | C53: Arx Long Term FIC de FIF em Ações RL | D53: 31 | F53: « | G53: ARX Investimentos | H53: BNY Mellon Serviços Financeiros | I53: BNY Mellon Banco | J53: KPMG | K53: Geral | L53: Investidores em geral | M53: Ações | N53: Ações Livre | O53: Renda Variável Long Only | P53: Renda Variável - Alíquota de IR de 15% incidida sobre o lucro obtido no momento do resgate. | Q53: 1000 | R53: ABERTO | S53: - | T53: 1000 | U53: 1000 | V53: Fechamento | W53: D+0 | X53: D+30 (corridos) | Y53: D+2 (útil) | Z53: 32 | AA53: - | AB53: - | AC53: ARX LONG TERM RESP LIMITADA FIF CIC AÇÕES | AD53: 0.02 | AE53: 0.02 | AF53: 0.025 | AG53: 0.2 | AH53: Janeiro / Julho | AI53: Junho | AJ53: Ibovespa | AK53: 39696 | AL53: https://www.xpi.com.br/investimentos/fundos-de-investimento/lista/#/detalhes/a5a19209-bc81-4ec7-b0f7-b5b847d1eb7b | AM53: -0.016250175 | AN53: 0.11018965 | AO53: 0.38319718 | AP53: 0.19290001 | AQ53: 0.23795113 | AR53: -0.10978473 | AS53: 0.15410937 | AT53: -0.045623474 | AU53: - | AV53: - | AW53: 0.15630388 | AX53: - | AY53: 2.4269591 | AZ53: 2.5843697 | BA53: 1.5093994 | BB53: 2.0438778 | BC53: - | BD53: 1.1811465 | BE53: - | BF53: - | BG53: - | BH53: 2.7832917 | BI53: -0.027159557 | BJ53: 0.064787301 | BK53: 0.23492227 | BL53: 0.057723776 | BM53: 0.10885649 | BN53: -0.21852446 | BO53: 0.023634981 | BP53: -0.16935351 | BQ53: - | BR53: - | BS53: 0.094821008 | BT53: 0.18777152 | BU53: 0.21507929 | BV53: 1.0857527 | BW53: 0.34492689 | BX53: -0.098731618 | BY53: -0.47930848 | BZ53: 0.73048659 | CA53: 0.94455923 | CB53: -0.47287457 | CC53: 0.65577265 | CD53: 0.52090347 | CE53: 0.10105263 | CF53: 0.76341556 | CG53: 12.860741 | CH53: 0.2 | CI53: 0.1 | CJ53: 0.004 | CK53: - | CL53: 0.004 | CM53: 18078763 | CN53: 15206656 | CO53: 3200852 | CP53: - | CQ53: - | CR53: - | CS53: - | CT53: - | CU53: - | CV53: BRARX4CTF008 | CW53: - | CX53: 25569.626
B54: 17414721000140 | C54: ARX Macro FIC de FIF Multimercado RL | D54: 13 | F54: ««« | G54: ARX Investimentos | H54: BNY Mellon Serviços Financeiros | I54: BNY Mellon Banco | J54: KPMG | K54: Intranet | L54: Investidores em geral | M54: Multimercado | N54: Multimercados Macro | O54: Macro Alta Vol | P54: Longo Prazo - Alíquota regressiva de IR de 22,5% a 15,0% incidida sobre o lucro obtido no momento do resgate. | Q54: 1000 | R54: FECHADO | S54: - | T54: 1000 | U54: 1000 | V54: Fechamento | W54: D+0 | X54: D+0 | Y54: D+1 (útil) | Z54: 1 | AA54: - | AB54: - | AC54: ARX MACRO RESP LIMITADA FIF CIC MULTIMERCADO | AD54: 0.02 | AE54: 0.02 | AF54: 0.025 | AG54: 0.2 | AH54: Janeiro / Julho | AI54: Junho | AJ54: CDI | AK54: 42185 | AL54: https://www.xpi.com.br/investimentos/fundos-de-investimento/lista/#/detalhes/524cc1fb-2751-43bc-965f-7b77627ef9f1 | AM54: 0.0045185752 | AN54: 0.022915772 | AO54: 0.088566051 | AP54: 0.10676361 | AQ54: 0.085073044 | AR54: 0.10675593 | AS54: 0.01146729 | AT54: -0.021992193 | AU54: - | AV54: - | AW54: 0.090314823 | AX54: 0.4141917 | AY54: 0.50472654 | AZ54: 0.59730977 | BA54: 0.80258701 | BB54: 0.63227775 | BC54: 0.98175644 | BD54: 0.087889197 | BE54: - | BF54: - | BG54: - | BH54: 0.89187125 | BI54: -0.0063908062 | BJ54: -0.02248658 | BK54: -0.059708857 | BL54: -0.023177554 | BM54: -0.043609419 | BN54: -0.0019838 | BO54: -0.1190071 | BP54: -0.14572223 | BQ54: - | BR54: - | BS54: -0.0099427481 | BT54: 0.040540681 | BU54: 0.080122481 | BV54: -1.2975769 | BW54: -0.041954738 | BX54: -0.027841671 | BY54: -0.14147056 | BZ54: 0.12344134 | CA54: 0.45391084 | CB54: -0.26323674 | CC54: 0.63609262 | CD54: 0.45182183 | CE54: 0.083680939 | CF54: 0.61521103 | CG54: 2.5419866 | CH54: 0.21 | CI54: 0.1 | CJ54: 0.0042 | CK54: - | CL54: 0.0042 | CM54: 41746732 | CN54: 46830275 | CO54: -13638831 | CP54: - | CQ54: - | CR54: - | CS54: - | CT54: - | CU54: - | CV54: BRARI0CTF005 | CW54: - | CX54: 25569.626
B55: 41888492000180 | C55: Arx Vinson Advisory FIC de FIF RF CP RL | D55: 3 | G55: ARX Investimentos | H55: BNY Mellon Serviços Financeiros | I55: BNY Mellon Banco | J55: KPMG | K55: Geral | L55: Investidores em geral | M55: Renda Fixa | N55: Renda Fixa Duração Baixa Grau de Investimento | O55: Crédito High Grade | P55: Longo Prazo_x000D_ | Q55: 500 | R55: ABERTO | S55: - | T55: 100 | U55: 500 | V55: Fechamento | W55: D+0 | X55: D+30 (corridos) | Y55: D+1 (útil) | Z55: 31 | AA55: - | AB55: - | AC55: ARX VINSON ADVISORY RESP LIMITADA FIF CIC RENDA FIXA CRÉDITO PRIVADO | AD55: 0.005 | AE55: 0.005 | AF55: 0.008 | AG55: - | AH55: - | AI55: - | AJ55: CDI | AK55: 44393 | AL55: https://www.xpi.com.br/investimentos/fundos-de-investimento/lista/#/detalhes/137f457b-2121-4c4f-9211-69826f456ddd | AM55: 0.011915693 | AN55: 0.039276923 | AO55: 0.14083532 | AP55: 0.13650378 | AQ55: 0.13878909 | AR55: 0.12871685 | AS55: 0.11294629 | AT55: 0.14342579 | AU55: - | AV55: - | AW55: 0.12925725 | AX55: 1.0922428 | AY55: 0.86508564 | AZ55: 0.94982571 | BA55: 1.0406422 | BB55: 1.0862576 | BC55: 1.183715 | BD55: 0.86565869 | BE55: 1.1591833 | BF55: - | BG55: - | BH55: 1.0736936 | BI55: 0.0010063117 | BJ55: -0.0061254295 | BK55: -0.0074395882 | BL55: 0.0047129373 | BM55: 0.0097723775 | BN55: 0.019977117 | BO55: -0.017528101 | BP55: 0.019695755 | BQ55: - | BR55: - | BS55: 0.0079183921 | BT55: 0.0046617071 | BU55: 0.0052965321 | BV55: -1.3927672 | BW55: 1.2168359 | BX55: -0.000893358 | BY55: -0.0067786543 | BZ55: 0.0021877825 | CA55: 0.019888131 | CB55: -0.069927664 | CC55: -0.039912041 | CD55: -0.085238355 | CE55: -0.030641195 | CF55: -0.044379039 | CG55: 1.7857214 | CH55: 0.27 | CI55: - | CJ55: 0.00135 | CK55: - | CL55: 0.00135 | CM55: 1.2649022e+09 | CN55: 1.2868858e+09 | CO55: -98253542 | CP55: - | CQ55: - | CR55: - | CS55: - | CT55: - | CU55: - | CV55: BR08ZWCTF004 | CW55: - | CX55: 25569.626
B56: 61184038000156 | C56: ARZ Alpine Bain Capital Private Credit II FIC FIM CP RL | D56: 50 | G56: ARZ Capital Gestora de Recursos Ltda | H56: BTG Pactual Serviços Financeiros | I56: Banco BTG Pactual | J56: EY | K56: Intranet | L56: Investidores qualificados | M56: Multimercado | N56: Multimercados Investimento no Exterior | O56: Alternativo Ilíquido | P56: Longo Prazo | Q56: 1000 | R56: FECHADO | S56: - | T56: 0.01 | U56: 0.01 | V56: Fechamento | W56: D+1 (útil) | X56: D+0 | Y56: D+2 (útil) | Z56: 2 | AA56: - | AB56: - | AC56: ARZ ALPINE BAIN CAPITAL PRIVATE CREDIT II FIF CIC MULTIMERCADO | AD56: 0.0105 | AE56: 0.0905 | AF56: 0.0118 | AG56: - | AH56: - | AI56: - | AJ56: - | AK56: 45841 | AL56: https://www.xpi.com.br/investimentos/fundos-de-investimento/lista/#/detalhes/396cc046-d8ac-431b-bc66-0db7083e630a | AM56: - | AN56: - | AO56: - | AP56: - | AQ56: - | AR56: - | AS56: - | AT56: - | AU56: - | AV56: - | AW56: - | AX56: - | AY56: - | AZ56: - | BA56: - | BB56: - | BC56: - | BD56: - | BE56: - | BF56: - | BG56: - | BH56: - | BI56: - | BJ56: - | BK56: - | BL56: - | BM56: - | BN56: - | BO56: - | BP56: - | BQ56: - | BR56: - | BS56: - | BT56: - | BU56: 0.024752447 | BV56: - | BW56: 0.42619529 | BX56: - | BY56: -0.0022704565 | BZ56: 0.012350053 | CA56: - | CB56: - | CC56: - | CD56: - | CE56: - | CF56: - | CG56: 1.1307156 | CH56: 0.15 | CI56: - | CJ56: 0.001575 | CK56: - | CL56: 0.001575 | CM56: 2.1037807e+08 | CN56: 2.0151237e+08 | CO56: - | CP56: - | CQ56: - | CR56: - | CS56: - | CT56: - | CU56: - | CV56: BR0OFJCTF006 | CW56: - | CX56: 25569.626
B57: 25307278000137 | C57: ASA Gauss | D57: 13 | F57: «««« | G57: ASA Investments | H57: Santander Caceis | I57: Santander Caceis | J57: EY | K57: Geral | L57: Investidores qualificados | M57: Multimercado | N57: Multimercados Macro | O57: Macro Alta Vol | P57: Longo Prazo - Alíquota regressiva de IR de 22,5% a 15,0% incidida sobre o lucro obtido no momento do resgate. | Q57: 500 | R57: ABERTO | S57: - | T57: 100 | U57: 100 | V57: Fechamento | W57: D+1 (útil) | X57: D+29 (corridos) | Y57: D+1 (útil) | Z57: 30 | AA57: - | AB57: - | AC57: ASA GAUSS RESP LIMITADA FIF CIC MULTIMERCADO | AD57: 0.0195 | AE57: 0.0695 | AF57: 0.02 | AG57: 0.2 | AH57: Janeiro / Julho | AI57: Junho | AJ57: CDI | AK57: 41949 | AL57: https://www.xpi.com.br/investimentos/fundos-de-investimento/lista/#/detalhes/d3e60b58-0aef-4927-966b-697bc2feb40b | AM57: 0.0058123717 | AN57: 0.02289323 | AO57: 0.1570431 | AP57: 0.077735193 | AQ57: 0.07232551 | AR57: -0.03452849 | AS57: 0.063473105 | AT57: 0.12778549 | AU57: - | AV57: - | AW57: 0.089546923 | AX57: 0.53278655 | AY57: 0.50423005 | AZ57: 1.0591347 | BA57: 0.57631638 | BB57: 0.53090424 | BC57: - | BD57: 0.4864794 | BE57: 1.0327767 | BF57: - | BG57: - | BH57: 0.96023958 | BI57: -0.0050970097 | BJ57: -0.022509122 | BK57: 0.0087681954 | BL57: -0.050355552 | BM57: -0.05624323 | BN57: -0.14326822 | BO57: -0.067001289 | BP57: 0.0040554586 | BQ57: - | BR57: - | BS57: -0.0033915688 | BT57: 0.084528784 | BU57: 0.08733159 | BV57: 0.1321472 | BW57: 0.016328217 | BX57: -0.053986537 | BY57: -0.19070654 | BZ57: 0.19968658 | CA57: 0.61831794 | CB57: -0.46961158 | CC57: 0.64097222 | CD57: 0.51129262 | CE57: 0.073568289 | CF57: 0.79532847 | CG57: 2.9136981 | CH57: 0.25 | CI57: 0.05 | CJ57: 0.004875 | CK57: 7.6359723e-05 | CL57: 0.0049513597 | CM57: 30073781 | CN57: 62668619 | CO57: -1.2140296e+08 | CP57: - | CQ57: - | CR57: - | CS57: - | CT57: - | CU57: - | CV57: BRGSS2CTF002 | CW57: - | CX57: 25569.626
B58: 31608422000178 | C58: ASA Hedge CIC CI Multimercado CP RL | D58: 13 | G58: ASA Investments | H58: Santander Caceis | I58: Santander Caceis | J58: EY | K58: Geral | L58: Investidores em geral | M58: Multimercado | N58: Multimercados Macro | O58: Macro Média Vol | P58: Longo Prazo | Q58: 500 | R58: ABERTO | S58: - | T58: 100 | U58: 500 | V58: Fechamento | W58: D+0 | X58: D+2 (útil) | Y58: D+1 (útil) | Z58: 3 | AA58: - | AB58: - | AC58: ASA HEDGE RESP LIMITADA FIF CIC MULTIMERCADO CRÉDITO PRIVADO | AD58: 0.015 | AE58: 0.035 | AF58: 0.0155 | AG58: 0.2 | AH58: Junho / Dezembro | AI58: Maio / Novembro | AJ58: CDI | AK58: 44239 | AL58: https://www.xpi.com.br/investimentos/fundos-de-investimento/lista/#/detalhes/6fd5d5b0-5570-4fcd-b35e-d861b217c6bd | AM58: 0.005842679 | AN58: 0.012587954 | AO58: 0.13409898 | AP58: 0.1061513 | AQ58: 0.10266202 | AR58: 0.035295076 | AS58: 0.11028885 | AT58: 0.13483084 | AU58: - | AV58: - | AW58: 0.087878521 | AX58: 0.53556464 | AY58: 0.27725334 | AZ58: 0.90439431 | BA58: 0.79775215 | BB58: 0.77611513 | BC58: 0.32458308 | BD58: 0.84529112 | BE58: 1.089718 | BF58: - | BG58: - | BH58: 0.72731077 | BI58: -0.0050667025 | BJ58: -0.032814398 | BK58: -0.014175925 | BL58: -0.023751289 | BM58: -0.026155065 | BN58: -0.073444652 | BO58: -0.020185548 | BP58: 0.011100806 | BQ58: - | BR58: - | BS58: -0.029396272 | BT58: 0.056714075 | BU58: 0.053851998 | BV58: -0.19092564 | BW58: -0.41939511 | BX58: -0.036490562 | BY58: -0.062179057 | BZ58: 0.10074698 | CA58: 0.62510025 | CB58: -0.43495253 | CC58: 0.64207171 | CD58: 0.51405743 | CE58: 0.1172853 | CF58: 0.78744132 | CG58: 2.3260224 | CH58: 0.25 | CI58: 0.15 | CJ58: 0.00375 | CK58: - | CL58: 0.00375 | CM58: 97030167 | CN58: 53652430 | CO58: 87435612 | CP58: - | CQ58: - | CR58: - | CS58: - | CT58: - | CU58: - | CV58: BR06SZCTF006 | CW58: - | CX58: 25569.626
B59: 20458815000126 | C59: ASA Hedge FIC FIM RL | D59: 13 | F59: ««««« | G59: ASA Investments | H59: BTG Pactual Serviços Financeiros | I59: Banco BTG Pactual | J59: EY | K59: Intranet | L59: Investidores em geral | M59: Multimercado | N59: Multimercados Livre | O59: Macro Alta Vol | P59: Longo Prazo - Alíquota regressiva de IR de 22,5% a 15,0% incidida sobre o lucro obtido no momento do resgate._x000D_ | Q59: 10000 | R59: FECHADO | S59: - | T59: 5000 | U59: 5000 | V59: Fechamento | W59: D+0 | X59: D+30 (corridos) | Y59: D+1 (útil) | Z59: 31 | AA59: - | AB59: - | AC59: ASA HEDGE FIC MULTIMERCADO | AD59: 0.019 | AE59: 0.089 | AF59: 0.022 | AG59: 0.2 | AH59: Janeiro / Julho | AI59: Junho | AJ59: CDI | AK59: 41883 | AL59: https://www.xpi.com.br/investimentos/fundos-de-investimento/lista/#/detalhes/0c5027b8-6cf0-4c40-8fd7-8ab4e7107cdb | AM59: 0.0052875982 | AN59: 0.013531055 | AO59: 0.090212197 | AP59: 0.049548061 | AQ59: 0.03177456 | AR59: -0.018073854 | AS59: 0.0073401597 | AT59: 0.39402795 | AU59: - | AV59: - | AW59: 0.10481623 | AX59: 0.4846836 | AY59: 0.29802543 | AZ59: 0.60841176 | BA59: 0.362358 | BB59: 0.2241292 | BC59: - | BD59: 0.056257473 | BE59: 3.184578 | BF59: - | BG59: - | BH59: 1.0937935 | BI59: -0.0056217832 | BJ59: -0.031871297 | BK59: -0.058062711 | BL59: -0.076701771 | BM59: -0.096336816 | BN59: -0.12681358 | BO59: -0.12313423 | BP59: 0.27029791 | BQ59: - | BR59: - | BS59: 0.0082020705 | BT59: 0.053273792 | BU59: 0.069443768 | BV59: -0.94791937 | BW59: 0.10975344 | BX59: -0.037325614 | BY59: -0.1283117 | BZ59: 0.10328963 | CA59: 0.48638502 | CB59: -0.36834925 | CC59: 0.54726167 | CD59: 0.39554099 | CE59: 0.14625202 | CF59: 0.67680937 | CG59: 318.28585 | CH59: 0.25 | CI59: 0.15 | CJ59: 0.00475 | CK59: - | CL59: 0.00475 | CM59: 25803986 | CN59: 27636118 | CO59: -5915818 | CP59: - | CQ59: - | CR59: - | CS59: - | CT59: - | CU59: - | CV59: BR04ZKCTF008 | CW59: - | CX59: 25569.626
B60: 26434293000109 | C60: Asa Income CIC de CIRF CP RL | D60: 10 | F60: « | G60: ASA Investments | H60: Santander Caceis | I60: Santander Caceis | J60: Deloitte Touche Tohmatsu | K60: Geral | L60: Investidores em geral | M60: Renda Fixa | N60: Renda Fixa Duração Livre Grau de Investimento | O60: Crédito Liquidez | P60: Longo Prazo - Alíquota regressiva de IR de 22,5% a 15,0% incidida sobre o lucro obtido no momento do resgate. | Q60: 1000 | R60: ABERTO | S60: - | T60: 500 | U60: 1000 | V60: Fechamento | W60: D+0 | X60: D+0 | Y60: D+1 (útil) | Z60: 1 | AA60: - | AB60: - | AC60: ASA INCOME RESP LIMITADA FIF CIC RENDA FIXA CRÉDITO PRIVADO | AD60: 0.0045 | AE60: 0.0245 | AF60: 0.01 | AG60: - | AH60: - | AI60: - | AJ60: CDI | AK60: 42759 | AL60: https://www.xpi.com.br/investimentos/fundos-de-investimento/lista/#/detalhes/21a756e2-717c-46cb-b9bd-758d62d4a8eb | AM60: 0.010114521 | AN60: 0.042458902 | AO60: 0.14526699 | AP60: 0.12970515 | AQ60: 0.13432407 | AR60: 0.11120159 | AS60: 0.1397028 | AT60: 0.12995777 | AU60: - | AV60: - | AW60: 0.087620917 | AX60: 0.92713971 | AY60: 0.93516965 | AZ60: 0.97971391 | BA60: 0.98566601 | BB60: 1.0468393 | BC60: 1.0226399 | BD60: 1.0707296 | BE60: 1.0503333 | BF60: - | BG60: - | BH60: 0.95787961 | BI60: -0.00079486073 | BJ60: -0.0029434505 | BK60: -0.0030079178 | BL60: -0.0016668821 | BM60: 0.0053266543 | BN60: 0.0024618619 | BO60: 0.0092284073 | BP60: 0.0062277369 | BQ60: - | BR60: - | BS60: -0.0035300096 | BT60: 0.0011053533 | BU60: 0.0087528085 | BV60: -2.3736915 | BW60: -0.28634816 | BX60: - | BY60: -0.059437521 | BZ60: 0.00093085701 | CA60: 0.037412801 | CB60: 0.04556826 | CC60: 0.054381801 | CD60: -0.085951762 | CE60: 0.097834649 | CF60: 0.028540452 | CG60: 2.1689989 | CH60: 0.3 | CI60: - | CJ60: 0.00135 | CK60: - | CL60: 0.00135 | CM60: 32240261 | CN60: 31925419 | CO60: -3014377.7 | CP60: - | CQ60: - | CR60: - | CS60: - | CT60: - | CU60: - | CV60: BRSHG0CTF009 | CW60: - | CX60: 25569.626
B61: 35602471000154 | C61: Ashmore Emerging Markets Equity Advisory CIC de Classes de Ações IE RL | D61: 28 | G61: XP Allocation Asset Management LTDA. | H61: BNP Paribas | I61: BNP Paribas | J61: EY | K61: Geral | L61: Investidores qualificados | M61: Ações | N61: Ações Investimento no Exterior | O61: Internacional Ações Hedgeado | P61: Renda Variável: Haverá cobrança de IR no momento do resgate sob a alíquota de 15% sobre o rendimento bruto obtido._x000D_ | Q61: 500 | R61: ABERTO | S61: - | T61: 100 | U61: 100 | V61: Fechamento | W61: D+1 (útil) | X61: D+1 (útil) | Y61: D+5 (útil) | Z61: 6 | AA61: - | AB61: - | AC61: - | AD61: 0.01 | AE61: - | AF61: 0.012 | AG61: - | AH61: - | AI61: - | AJ61: CDI | AK61: 44071 | AL61: https://www.xpi.com.br/investimentos/fundos-de-investimento/lista/#/detalhes/0d17e8c3-a72d-482f-a4eb-0688788372bb | AM61: 0.12408951 | AN61: 0.14533135 | AO61: 0.49525691 | AP61: 0.30128717 | AQ61: 0.2289619 | AR61: 0.088581547 | AS61: 0.10710882 | AT61: -0.19753828 | AU61: - | AV61: - | AW61: 0.10134178 | AX61: 11.374569 | AY61: 3.2009651 | AZ61: 3.3401262 | BA61: 2.4740276 | BB61: 1.9504095 | BC61: 0.81461991 | BD61: 0.82091835 | BE61: - | BF61: - | BG61: - | BH61: 0.94308796 | BI61: 0.11318013 | BJ61: 0.099928994 | BK61: 0.346982 | BL61: 0.1600199 | BM61: 0.099848774 | BN61: -0.020158181 | BO61: -0.023365569 | BP61: -0.32126831 | BQ61: - | BR61: - | BS61: -0.0055222169 | BT61: 0.15750509 | BU61: 0.17729222 | BV61: 1.756571 | BW61: 0.063515367 | BX61: -0.12934565 | BY61: -0.38900732 | BZ61: 0.44866508 | CA61: 0.39836989 | CB61: -0.44351777 | CC61: 0.38032161 | CD61: 0.29260725 | CE61: 0.32096595 | CF61: 0.57874896 | CG61: 172.47528 | CH61: 0.5 | CI61: - | CJ61: 0.005 | CK61: - | CL61: 0.005 | CM61: 28008304 | CN61: 25159989 | CO61: 248675.93 | CP61: - | CQ61: - | CR61: - | CS61: - | CT61: - | CU61: - | CV61: BR04ZCCTF005 | CW61: - | CX61: 25569.647
B62: 17627210000107 | C62: Atena Tapyr FIF em Cotas FIRF CP RL | D62: 10 | G62: Atena Capital | H62: BTG Pactual Serviços Financeiros | I62: Banco BTG Pactual | J62: EY | K62: Geral | L62: Investidores em geral | M62: Renda Fixa | N62: Renda Fixa Duração Livre Grau de Investimento | O62: Crédito Liquidez | P62: Longo Prazo | Q62: 1000 | R62: ABERTO | S62: - | T62: 1000 | U62: 1000 | V62: Fechamento | W62: D+0 | X62: D+0 | Y62: D+1 (útil) | Z62: 1 | AA62: - | AB62: - | AC62: ATENA TAPYR FIF CIC RENDA FIXA | AD62: 0.005 | AE62: 0.175 | AF62: 0.0067 | AG62: 0.15 | AH62: Junho / Dezembro | AI62: Maio / Novembro | AJ62: CDI | AK62: 38418 | AL62: https://www.xpi.com.br/investimentos/fundos-de-investimento/lista/#/detalhes/e49dd3e7-f65c-4a49-9669-606b304f8b21 | AM62: 0.010772983 | AN62: 0.046140356 | AO62: 0.15180306 | AP62: 0.13293648 | AQ62: 0.13212328 | AR62: 0.10793385 | AS62: 0.13603951 | AT62: 0.12991083 | AU62: - | AV62: - | AW62: 0.10246155 | AX62: 0.9874971 | AY62: 1.0162548 | AZ62: 1.0237947 | BA62: 1.0117546 | BB62: 1.027524 | BC62: 0.99258894 | BD62: 1.0426529 | BE62: 1.0499539 | BF62: - | BG62: - | BH62: 1.0578888 | BI62: -0.00013639892 | BJ62: 0.00073800422 | BK62: 0.0035281552 | BL62: 0.0013650951 | BM62: 0.0031359152 | BN62: -0.00080587669 | BO62: 0.0055651129 | BP62: 0.0061807917 | BQ62: - | BR62: - | BS62: 0.0051117142 | BT62: 0.0011947986 | BU62: 0.0068083351 | BV62: 2.569696 | BW62: 0.46038154 | BX62: - | BY62: -0.006473558 | BZ62: 0.0039504592 | CA62: -0.012513978 | CB62: 0.051101928 | CC62: -0.0054047856 | CD62: -0.024755269 | CE62: -0.0070864655 | CF62: 0.011444327 | CG62: 9.8474762 | CH62: 0.27 | CI62: 0.15 | CJ62: 0.00135 | CK62: 6.9132827e-05 | CL62: 0.0014191328 | CM62: 1.1360922e+08 | CN62: 1.014469e+08 | CO62: 2283488.1 | CP62: - | CQ62: - | CR62: - | CS62: - | CT62: - | CU62: - | CV62: BR0A7HCTF009 | CW62: - | CX62: 25569.626
B63: 31340838000158 | C63: Atena Yield D30 FIC de FIF RF CP RL | D63: 11 | F63: ««« | G63: Atena Capital | H63: BTG Pactual Serviços Financeiros | I63: Banco BTG Pactual | J63: PriceWaterhouseCoopers | K63: Geral | L63: Investidores qualificados | M63: Renda Fixa | N63: Renda Fixa Duração Livre Crédito Livre | O63: Crédito High Grade | P63: Longo Prazo | Q63: 1000 | R63: ABERTO | S63: - | T63: 1000 | U63: 1000 | V63: Fechamento | W63: D+0 | X63: D+29 (corridos) | Y63: D+1 (útil) | Z63: 30 | AA63: - | AB63: - | AC63: ATENA YIELD D30 FIF CIC RENDA FIXA | AD63: 0.0085 | AE63: 0.1585 | AF63: 0.01 | AG63: 0.15 | AH63: Junho / Dezembro | AI63: Maio / Novembro | AJ63: CDI | AK63: 43444 | AL63: https://www.xpi.com.br/investimentos/fundos-de-investimento/lista/#/detalhes/b5394707-02a7-40d1-9d43-418a40ac41cb | AM63: 0.011021312 | AN63: 0.046357511 | AO63: 0.15348457 | AP63: 0.13545804 | AQ63: 0.13637317 | AR63: 0.11123098 | AS63: 0.14328044 | AT63: 0.13385433 | AU63: - | AV63: - | AW63: 0.10216761 | AX63: 1.01026 | AY63: 1.0210377 | AZ63: 1.0351352 | BA63: 1.0321645 | BB63: 1.0648909 | BC63: 1.0229102 | BD63: 1.0981499 | BE63: 1.0818257 | BF63: - | BG63: - | BH63: 1.1371727 | BI63: 0.00011193061 | BJ63: 0.00095515879 | BK63: 0.005209667 | BL63: 0.0037314606 | BM63: 0.0073667182 | BN63: 0.0024912505 | BO63: 0.012806048 | BP63: 0.010124299 | BQ63: - | BR63: - | BS63: 0.011308118 | BT63: 0.0012708 | BU63: 0.0033955465 | BV63: 3.564696 | BW63: 2.5487266 | BX63: - | BY63: -0.0027346869 | BZ63: 0.0023018719 | CA63: 0.010444815 | CB63: 0.025490863 | CC63: 0.078385051 | CD63: 0.05754462 | CE63: 0.014326161 | CF63: 0.075197768 | CG63: 2.0463956 | CH63: 0.27 | CI63: 0.15 | CJ63: 0.002295 | CK63: 0.0001020814 | CL63: 0.0023970814 | CM63: 2.0600212e+08 | CN63: 1.9273334e+08 | CO63: -7811399.4 | CP63: - | CQ63: - | CR63: - | CS63: - | CT63: - | CU63: - | CV63: BR0A7KCTF003 | CW63: - | CX63: 25569.626
B64: 17249227000178 | C64: Athena Total Return FIF em Cotas de FIA RL | D64: 26 | F64: «««« | G64: SulAmérica Investimentos | H64: BTG Pactual Serviços Financeiros | I64: Banco BTG Pactual | J64: EY | K64: Intranet | L64: Investidores qualificados | M64: Ações | N64: Ações Investimento no Exterior | O64: Renda Variável Long Only | P64: Renda Variável - Alíquota de IR de 15% incidida sobre o lucro obtido no momento do resgate. | Q64: 1000 | R64: FECHADO | S64: - | T64: 1000 | U64: 100 | V64: Fechamento | W64: D+1 (útil) | X64: D+30 (corridos) | Y64: D+2 (útil) | Z64: 32 | AA64: - | AB64: - | AC64: ATHENA TOTAL RETURN FIF CIC AÇÕES | AD64: 0.02 | AE64: 0.02 | AF64: 0.025 | AG64: 0.2 | AH64: Janeiro / Julho | AI64: Junho | AJ64: - | AK64: 41779 | AL64: https://www.xpi.com.br/investimentos/fundos-de-investimento/lista/#/detalhes/c2d8343d-1826-4a2f-a225-d056c0d91199 | AM64: 0.0001942494 | AN64: 0.049727109 | AO64: 0.21023403 | AP64: 0.11451401 | AQ64: 0.17785265 | AR64: -0.11640399 | AS64: 0.21918456 | AT64: 0.088408323 | AU64: - | AV64: - | AW64: 0.10777243 | AX64: 0.017805721 | AY64: 1.095254 | AZ64: 1.4178665 | BA64: 0.864017 | BB64: 1.4444887 | BC64: - | BD64: 1.6799048 | BE64: 0.71452597 | BF64: - | BG64: - | BH64: 1.1750473 | BI64: -0.010715132 | BJ64: 0.004324757 | BK64: 0.061959121 | BL64: -0.015913608 | BM64: 0.04872803 | BN64: -0.22514372 | BO64: 0.08871017 | BP64: -0.035321712 | BQ64: - | BR64: - | BS64: 0.014706097 | BT64: 0.14303744 | BU64: 0.1788743 | BV64: 0.43893603 | BW64: 0.14019361 | BX64: -0.068930776 | BY64: -0.46740752 | BZ64: 0.65304089 | CA64: 0.88608095 | CB64: -0.4347719 | CC64: 0.68216445 | CD64: 0.55303755 | CE64: 0.17968461 | CF64: 0.76817768 | CG64: 3.8859661 | CH64: 0.25 | CI64: 0.15 | CJ64: 0.005 | CK64: - | CL64: 0.005 | CM64: 75374774 | CN64: 79331867 | CO64: -10827629 | CP64: - | CQ64: - | CR64: - | CS64: - | CT64: - | CU64: - | CV64: BRXPT2CTF003 | CW64: - | CX64: 25569.626
B65: 23186344000132 | C65: Athena Total Return II FIF FIA | D65: 26 | F65: ««« | G65: SulAmérica Investimentos | H65: BTG Pactual Serviços Financeiros | I65: Banco BTG Pactual | J65: KPMG | K65: Intranet | L65: Investidores em geral | M65: Ações | N65: Ações Livre | O65: Renda Variável Long Only | P65: Renda Variável - Alíquota de IR de 15% incidida sobre o lucro obtido no momento do resgate. | Q65: 1000 | R65: FECHADO | S65: - | T65: 1000 | U65: 100 | V65: Fechamento | W65: D+1 (útil) | X65: D+30 (corridos) | Y65: D+2 (útil) | Z65: 32 | AA65: - | AB65: - | AC65: ATHENA TOTAL RETURN INSTITUCIONAL II FIF AÇÕES | AD65: 0.03 | AE65: 0.03 | AF65: 0.035 | AG65: - | AH65: - | AI65: - | AJ65: - | AK65: 42276 | AL65: https://www.xpi.com.br/investimentos/fundos-de-investimento/lista/#/detalhes/24d25e2e-01c0-4c23-9a7a-59fa5effd45e | AM65: -0.0023233411 | AN65: 0.042623923 | AO65: 0.19281707 | AP65: 0.09963387 | AQ65: 0.16512991 | AR65: -0.12759926 | AS65: 0.20897022 | AT65: 0.080874423 | AU65: - | AV65: - | AW65: 0.1220191 | AX65: - | AY65: 0.9388043 | AZ65: 1.3004026 | BA65: 0.74645504 | BB65: 1.325157 | BC65: - | BD65: 1.6016186 | BE65: 0.65363614 | BF65: - | BG65: - | BH65: 1.44128 | BI65: -0.013232723 | BJ65: -0.0027784289 | BK65: 0.044542165 | BL65: -0.029856987 | BM65: 0.036028734 | BN65: -0.23633899 | BO65: 0.078495826 | BP65: -0.042855612 | BQ65: - | BR65: - | BS65: 0.034442923 | BT65: 0.14944575 | BU65: 0.20010547 | BV65: 0.32929503 | BW65: 0.21664989 | BX65: -0.074116454 | BY65: -0.48274397 | BZ65: 0.74154877 | CA65: 0.8870547 | CB65: -0.43695852 | CC65: 0.68524912 | CD65: 0.5550477 | CE65: 0.17764924 | CF65: 0.77053143 | CG65: 3.363476 | CH65: 0.3 | CI65: - | CJ65: 0.009 | CK65: - | CL65: 0.009 | CM65: 40572146 | CN65: 42459474 | CO65: -6924521.8 | CP65: - | CQ65: - | CR65: - | CS65: - | CT65: - | CU65: - | CV65: BRATH5CTF003 | CW65: - | CX65: 25569.626
B66: 13083227000190 | C66: Atlas One FIC FIA | D66: 48 | F66: « | G66: Atlas One Investimentos | H66: BTG Pactual Serviços Financeiros | I66: Banco BTG Pactual | J66: EY | K66: Intranet | L66: Investidores em geral | M66: Ações | N66: Ações Livre | O66: Renda Variável Long Only | P66: Renda Variável: Haverá cobrança de IR no momento do resgate sob a alíquota de 15% sobre o rendimento bruto obtido._x000D_ | Q66: 500 | R66: ABERTO | S66: - | T66: 500 | U66: 500 | V66: Fechamento | W66: D+0 | X66: D+30 (corridos) | Y66: D+2 (útil) | Z66: 32 | AA66: Sim | AB66: 0.075 | AC66: ATLAS ONE FIF CIC AÇÕES | AD66: 0.02 | AE66: 0.02 | AF66: 0.025 | AG66: 0.2 | AH66: Junho / Dezembro | AI66: Maio / Novembro | AJ66: IBX | AK66: 40786 | AL66: https://www.xpi.com.br/investimentos/fundos-de-investimento/lista/#/detalhes/cb7fbdd4-2684-4ecd-95eb-559861af729a | AM66: 0.0040416496 | AN66: 0.10833401 | AO66: 0.45958546 | AP66: 0.24959066 | AQ66: 0.17798781 | AR66: -0.24759137 | AS66: 0.079619077 | AT66: -0.15712256 | AU66: - | AV66: - | AW66: 0.087816321 | AX66: 0.37047468 | AY66: 2.3860881 | AZ66: 3.0995498 | BA66: 2.0034796 | BB66: 1.4457703 | BC66: - | BD66: 0.61022761 | BE66: - | BF66: - | BG66: - | BH66: 0.83772619 | BI66: -0.0068677318 | BJ66: 0.062931661 | BK66: 0.31131056 | BL66: 0.11116348 | BM66: 0.048862992 | BN66: -0.3563311 | BO66: -0.050855316 | BP66: -0.28085259 | BQ66: - | BR66: - | BS66: -0.015396688 | BT66: 0.22684246 | BU66: 0.20820198 | BV66: 1.1717455 | BW66: 0.06288288 | BX66: -0.148939 | BY66: -0.53854769 | BZ66: 0.76356454 | CA66: 0.89749071 | CB66: -0.46666958 | CC66: 0.66130562 | CD66: 0.52235933 | CE66: 0.11778219 | CF66: 0.79356417 | CG66: 3.4195774 | CH66: 0.25 | CI66: 0.15 | CJ66: 0.005 | CK66: 0.0015074962 | CL66: 0.0065074962 | CM66: 45513774 | CN66: 43688263 | CO66: -501862.87 | CP66: - | CQ66: - | CR66: - | CS66: - | CT66: - | CU66: - | CV66: BRMTR4CTF000 | CW66: - | CX66: 25569.647
B67: 36182298000145 | C67: Atlas One Long Bias FIF CIC em Ações RL | D67: 31 | F67: «« | G67: Atlas One Investimentos | H67: BTG Pactual Serviços Financeiros | I67: Banco BTG Pactual | J67: Deloitte Touche Tohmatsu | K67: Intranet | L67: Investidores qualificados | M67: Ações | N67: Ações Livre | O67: Renda Variável Long Biased | P67: Renda Variavel | Q67: 500 | R67: ABERTO | S67: - | T67: 500 | U67: 500 | V67: Fechamento | W67: D+0 | X67: D+30 (corridos) | Y67: D+2 (útil) | Z67: 32 | AA67: Sim | AB67: 0.075 | AC67: ATLAS ONE LONG BIAS RESP LIMITADA FIF CIC AÇÕES | AD67: 0.02 | AE67: 0.02 | AF67: 0.02 | AG67: 0.2 | AH67: Junho / Dezembro | AI67: Maio / Novembro | AJ67: - | AK67: 43895 | AL67: https://www.xpi.com.br/investimentos/fundos-de-investimento/lista/#/detalhes/0a6092d2-43f4-499f-bf43-082a26121593 | AM67: 0.0013336311 | AN67: 0.018733441 | AO67: 0.30469192 | AP67: 0.22418634 | AQ67: 0.18887555 | AR67: -0.12421001 | AS67: 0.11090698 | AT67: -0.1620648 | AU67: - | AV67: - | AW67: 0.073896121 | AX67: 0.12224626 | AY67: 0.41260949 | AZ67: 2.0549122 | BA67: 1.7792354 | BB67: 1.5499828 | BC67: - | BD67: 0.85002868 | BE67: - | BF67: - | BG67: - | BH67: 0.69111756 | BI67: -0.0095757504 | BJ67: -0.026668911 | BK67: 0.15641701 | BL67: 0.08719778 | BM67: 0.05973937 | BN67: -0.23294973 | BO67: -0.019567417 | BP67: -0.28579484 | BQ67: - | BR67: - | BS67: -0.029836348 | BT67: 0.17437366 | BU67: 0.20486004 | BV67: 0.81981902 | BW67: -0.014273646 | BX67: -0.089553219 | BY67: -0.3876088 | BZ67: 0.74427261 | CA67: 0.87200346 | CB67: -0.43899535 | CC67: 0.64835337 | CD67: 0.51784846 | CE67: 0.16090883 | CF67: 0.75425063 | CG67: 1.5477662 | CH67: 0.27 | CI67: 0.15 | CJ67: 0.0054 | CK67: - | CL67: 0.0054 | CM67: 1.3161939e+08 | CN67: 1.2931775e+08 | CO67: 2827992.5 | CP67: - | CQ67: - | CR67: - | CS67: - | CT67: - | CU67: - | CV67: BR03Y8CTF008 | CW67: - | CX67: 25569.647
B68: 36326771000110 | C68: ATMR II FIC de FIA | D68: 33 | F68: ««« | G68: Atmos Capital | H68: BTG Pactual Serviços Financeiros | I68: Banco BTG Pactual | J68: EY | K68: Intranet | L68: Investidores qualificados | M68: Ações | N68: Ações Livre | O68: Renda Variável Long Only | P68: Renda Variável - Alíquota de IR de 15% incidida sobre o lucro obtido no momento do resgate. | Q68: 200000 | R68: FECHADO | S68: - | T68: 20000 | U68: 20000 | V68: Fechamento | W68: D+1 (útil) | X68: D+60 (corridos) | Y68: D+2 (útil) | Z68: 62 | AA68: Sim | AB68: 0.1 | AC68: ATMR II FIC AÇÕES | AD68: 0.0135 | AE68: 0.1635 | AF68: 0.015 | AG68: 0.2 | AH68: - | AI68: - | AJ68: - | AK68: 43908 | AL68: https://www.xpi.com.br/investimentos/fundos-de-investimento/lista/#/detalhes/027a7b09-6742-4ec2-aa62-9debfdc07a23 | AM68: 0.038714025 | AN68: 0.065068945 | AO68: 0.21854156 | AP68: 0.16730362 | AQ68: 0.20675515 | AR68: -0.11970042 | AS68: 0.30658445 | AT68: -0.18619906 | AU68: - | AV68: - | AW68: 0.14220017 | AX68: 3.5486911 | AY68: 1.4331624 | AZ68: 1.4738944 | BA68: 1.2938328 | BB68: 1.7253054 | BC68: - | BD68: 2.3497672 | BE68: - | BF68: - | BG68: - | BH68: 1.5793114 | BI68: 0.027804644 | BJ68: 0.019666593 | BK68: 0.070266648 | BL68: 0.033644563 | BM68: 0.077616941 | BN68: -0.22844015 | BO68: 0.17611006 | BP68: -0.3099291 | BQ68: - | BR68: - | BS68: 0.047852234 | BT68: 0.19704274 | BU68: 0.21515635 | BV68: 0.39986165 | BW68: 0.2811024 | BX68: -0.11181686 | BY68: -0.39768091 | BZ68: 0.87836308 | CA68: 0.87573535 | CB68: -0.44345425 | CC68: 0.66049196 | CD68: 0.55147781 | CE68: 0.18299928 | CF68: 0.76430501 | CG68: 224.76229 | CH68: - | CI68: - | CJ68: - | CK68: - | CL68: - | CM68: 9.1412761e+08 | CN68: 8.9967675e+08 | CO68: -47737571 | CP68: - | CQ68: - | CR68: - | CS68: - | CT68: - | CU68: - | CV68: BR048QCTF002 | CW68: - | CX68: 25569.626
B69: 55296764000168 | C69: AUGM11 - Augme Crédito Estruturado FII RL | D69: 50 | G69: Augme Capital | H69: XP Investimentos | I69: Oliveira Trust | J69: PriceWaterhouseCoopers | K69: Intranet | L69: Investidores qualificados | M69: Investimento Imobiliário | N69: - | O69: Alternativo Ilíquido | P69: FII | Q69: 10 | R69: FECHADO | S69: - | T69: 0.01 | U69: 0.01 | V69: Fechamento | W69: D+0 | X69: D+0 | Y69: D+0 | Z69: 0 | AA69: - | AB69: - | AC69: - | AD69: 0.0113 | AE69: - | AF69: 0.0113 | AG69: 0.2 | AH69: Julho / Janeiro | AI69: Junho | AJ69: IPCA | AK69: 45439 | AL69: https://www.xpi.com.br/investimentos/fundos-de-investimento/lista/#/detalhes/99727d40-33a4-4d07-8027-1f7a454edf29 | AM69: - | AN69: - | AO69: - | AP69: - | AQ69: - | AR69: - | AS69: - | AT69: - | AU69: - | AV69: - | AW69: - | AX69: - | AY69: - | AZ69: - | BA69: - | BB69: - | BC69: - | BD69: - | BE69: - | BF69: - | BG69: - | BH69: - | BI69: - | BJ69: - | BK69: - | BL69: - | BM69: - | BN69: - | BO69: - | BP69: - | BQ69: - | BR69: - | BS69: - | BT69: - | BU69: - | BV69: - | BW69: - | BX69: - | BY69: - | BZ69: - | CA69: - | CB69: - | CC69: - | CD69: - | CE69: - | CF69: - | CG69: - | CH69: 0.15 | CI69: 0.05 | CJ69: 0.001695 | CK69: - | CL69: 0.001695 | CM69: - | CN69: - | CO69: - | CP69: - | CQ69: - | CR69: - | CS69: - | CT69: - | CU69: - | CV69: BRAUGMCTF008 | CW69: - | CX69: 25569.626
B70: 34218678000167 | C70: Augme 180 FIC FIM CP | D70: 13 | E70: Sim | F70: «««« | G70: Augme Capital | H70: BTG Pactual Serviços Financeiros | I70: Banco BTG Pactual | J70: PriceWaterhouseCoopers | K70: Geral | L70: Investidores qualificados | M70: Multimercado | N70: Multimercados Estratégia Específica | O70: Crédito High Yield | P70: Longo Prazo - Alíquota regressiva de IR de 22,5% a 15,0% incidida sobre o lucro obtido no momento do resgate. | Q70: 5000 | R70: ABERTO | S70: - | T70: 5000 | U70: 5000 | V70: Fechamento | W70: D+0 | X70: D+90 (corridos) | Y70: D+1 (útil) | Z70: 91 | AA70: - | AB70: - | AC70: - | AD70: 0.011 | AE70: - | AF70: 0.013 | AG70: 0.2 | AH70: Janeiro / Julho | AI70: Junho | AJ70: CDI | AK70: 43826 | AL70: https://www.xpi.com.br/investimentos/fundos-de-investimento/lista/#/detalhes/114686c9-8044-4db1-bb7a-0823fdff4c96 | AM70: 0.011281303 | AN70: 0.043988311 | AO70: 0.1466371 | AP70: 0.14277053 | AQ70: 0.14328166 | AR70: 0.13855527 | AS70: 0.098591003 | AT70: 0.14553969 | AU70: - | AV70: - | AW70: 0.11142088 | AX70: 1.0340919 | AY70: 0.96885532 | AZ70: 0.98895424 | BA70: 1.0916096 | BB70: 1.1262324 | BC70: 1.2741918 | BD70: 0.75563489 | BE70: 1.1762681 | BF70: - | BG70: - | BH70: 1.17492 | BI70: 0.00037192188 | BJ70: -0.0014140416 | BK70: -0.0016378093 | BL70: 0.010595719 | BM70: 0.014247021 | BN70: 0.029815541 | BO70: -0.03188339 | BP70: 0.021809659 | BQ70: - | BR70: - | BS70: 0.015151304 | BT70: 0.0088796331 | BU70: 0.010505657 | BV70: -0.15641037 | BW70: 1.1396834 | BX70: -0.0046294511 | BY70: -0.028435117 | BZ70: 0.0020885402 | CA70: -0.037248505 | CB70: 0.056277797 | CC70: -0.070705295 | CD70: -0.12181627 | CE70: 0.02318526 | CF70: -0.12371895 | CG70: 1.9474746 | CH70: 0.24 | CI70: - | CJ70: 0.00264 | CK70: - | CL70: 0.00264 | CM70: 2.2351366e+08 | CN70: 2.2723191e+08 | CO70: -76917938 | CP70: - | CQ70: - | CR70: - | CS70: - | CT70: - | CU70: - | CV70: BR02WGCTF007 | CW70: - | CX70: 25569.626
B71: 30568495000110 | C71: Augme 30 Advisory CIC RF CP LP RL | D71: 11 | F71: ««« | G71: Augme Capital | H71: BTG Pactual Serviços Financeiros | I71: Banco BTG Pactual | J71: PriceWaterhouseCoopers | K71: Geral | L71: Investidores em geral | M71: Renda Fixa | N71: Renda Fixa Duração Livre Crédito Livre | O71: Crédito High Grade | P71: Longo Prazo - Alíquota regressiva de IR de 22,5% a 15,0% incidida sobre o lucro obtido no momento do resgate. | Q71: 500 | R71: ABERTO | S71: - | T71: 500 | U71: 500 | V71: Fechamento | W71: D+0 | X71: D+30 (corridos) | Y71: D+1 (útil) | Z71: 31 | AA71: - | AB71: - | AC71: - | AD71: 0.006 | AE71: - | AF71: 0.009 | AG71: 0.2 | AH71: Janeiro / Julho | AI71: Junho | AJ71: CDI | AK71: 43612 | AL71: https://www.xpi.com.br/investimentos/fundos-de-investimento/lista/#/detalhes/3f464683-0789-448a-bbf3-621890bdada5 | AM71: 0.010061531 | AN71: 0.037386741 | AO71: 0.14182913 | AP71: 0.13280381 | AQ71: 0.14152114 | AR71: 0.12774033 | AS71: 0.12090316 | AT71: 0.14007118 | AU71: - | AV71: - | AW71: 0.10184668 | AX71: 0.92228247 | AY71: 0.82345385 | AZ71: 0.9565282 | BA71: 1.010682 | BB71: 1.1105299 | BC71: 1.1747347 | BD71: 0.92664285 | BE71: 1.132071 | BF71: - | BG71: - | BH71: 1.1007126 | BI71: -0.00084785022 | BJ71: -0.0080156106 | BK71: -0.0064457766 | BL71: 0.0012405998 | BM71: 0.012493349 | BN71: 0.019000599 | BO71: -0.0095712294 | BP71: 0.016341147 | BQ71: - | BR71: - | BS71: 0.0085295122 | BT71: 0.0079950405 | BU71: 0.0085026227 | BV71: -0.70049213 | BW71: 0.78226502 | BX71: -0.0045086538 | BY71: -0.030474688 | BZ71: 0.0026310655 | CA71: -0.012902361 | CB71: 0.091963961 | CC71: -0.043274812 | CD71: -0.10472514 | CE71: 6.2664342e-05 | CF71: -0.075549045 | CG71: 1.9543564 | CH71: 0.24 | CI71: 0.15 | CJ71: 0.00144 | CK71: - | CL71: 0.00144 | CM71: 1.7869978e+08 | CN71: 1.8459548e+08 | CO71: -43931844 | CP71: - | CQ71: - | CR71: - | CS71: - | CT71: - | CU71: - | CV71: BR01HKCTF002 | CW71: - | CX71: 25569.626
B72: 52285852000176 | C72: Augme 30 II CIC de CIRF CP LP RL | D72: 11 | G72: Augme Capital | H72: BNY Mellon Serviços Financeiros | I72: BNY Mellon Banco | J72: KPMG | K72: Geral | L72: Investidores em geral | M72: Renda Fixa | N72: Renda Fixa Duração Livre Crédito Livre | O72: Crédito High Grade | P72: Longo Prazo | Q72: 500 | R72: ABERTO | S72: - | T72: 100 | U72: 500 | V72: Fechamento | W72: D+0 | X72: D+30 (corridos) | Y72: D+1 (útil) | Z72: 31 | AA72: - | AB72: - | AC72: - | AD72: 0.006 | AE72: - | AF72: 0.008 | AG72: 0.2 | AH72: Junho / Dezembro | AI72: Maio / Novembro | AJ72: CDI | AK72: 45197 | AL72: https://www.xpi.com.br/investimentos/fundos-de-investimento/lista/#/detalhes/20af3314-fd6b-4573-9910-a49cf0713967 | AM72: 0.010133453 | AN72: 0.037881852 | AO72: 0.14577817 | AP72: 0.1350209 | AQ72: - | AR72: 0.12677808 | AS72: - | AT72: - | AU72: - | AV72: - | AW72: 0.13703174 | AX72: 0.92887515 | AY72: 0.8343588 | AZ72: 0.98316142 | BA72: 1.028623 | BB72: - | BC72: 1.1658856 | BD72: - | BE72: - | BF72: - | BG72: - | BH72: 1.0772316 | BI72: -0.00077592807 | BJ72: -0.0075205 | BK72: -0.0024967386 | BL72: 0.0033212028 | BM72: - | BN72: 0.018038354 | BO72: - | BP72: - | BQ72: - | BR72: - | BS72: 0.0087157259 | BT72: 0.0076879531 | BU72: 0.0052516185 | BV72: -0.27946143 | BW72: 1.511639 | BX72: -0.0023221546 | BY72: -0.0023221546 | BZ72: 0.0012305315 | CA72: -0.029297978 | CB72: 0.077651406 | CC72: -0.023422652 | CD72: -0.073707555 | CE72: -0.028596632 | CF72: -0.045306634 | CG72: 1.3912822 | CH72: 0.24 | CI72: 0.15 | CJ72: 0.00144 | CK72: - | CL72: 0.00144 | CM72: 3.5918171e+08 | CN72: 3.2698612e+08 | CO72: 60683572 | CP72: - | CQ72: - | CR72: - | CS72: - | CT72: - | CU72: - | CV72: BR0GXPCTF002 | CW72: - | CX72: 25569.626
B73: 49598896000141 | C73: Augme CI RF Incentivado Infraestrutura RL | D73: 11 | E73: Sim | G73: Augme Capital | H73: Santander Caceis | I73: Santander Caceis | J73: PriceWaterhouseCoopers | K73: Geral | L73: Investidores em geral | M73: Renda Fixa | N73: Renda Fixa Duração Livre Crédito Livre | O73: Debêntures Incentivadas Não Hedgeado | P73: Debêntures Incentivadas | Q73: 500 | R73: ABERTO | S73: - | T73: 500 | U73: 500 | V73: Fechamento | W73: D+0 | X73: D+30 (corridos) | Y73: D+1 (útil) | Z73: 31 | AA73: - | AB73: - | AC73: AUGME RESP LIMITADA FIF FI INFRA RENDA FIXA | AD73: 0.0075 | AE73: 0.0875 | AF73: 0.01 | AG73: 0.2 | AH73: Junho / Dezembro | AI73: Maio / Novembro | AJ73: IMA-B 5 | AK73: 44987 | AL73: https://www.xpi.com.br/investimentos/fundos-de-investimento/lista/#/detalhes/fdb2b0b0-3733-4a45-974b-a49eafb77ae3 | AM73: 0.0014205512 | AN73: 0.026542043 | AO73: 0.10716377 | AP73: 0.10178704 | AQ73: 0.12884928 | AR73: 0.095942121 | AS73: - | AT73: - | AU73: - | AV73: - | AW73: 0.12345218 | AX73: 0.13021372 | AY73: 0.58459622 | AZ73: 0.72273705 | BA73: 0.76336858 | BB73: 0.9989282 | BC73: 0.88230973 | BD73: - | BE73: - | BF73: - | BG73: - | BH73: 0.94884656 | BI73: -0.0094888303 | BJ73: -0.018860309 | BK73: -0.041111138 | BL73: -0.027840091 | BM73: -0.00012245436 | BN73: -0.012797607 | BO73: - | BP73: - | BQ73: - | BR73: - | BS73: -0.0058892208 | BT73: 0.03418729 | BU73: 0.033788081 | BV73: -1.0499379 | BW73: -0.13740037 | BX73: -0.020979381 | BY73: -0.026892943 | BZ73: 0.077031938 | CA73: 0.52380601 | CB73: -0.35937835 | CC73: 0.77826459 | CD73: 0.82530532 | CE73: 0.029270868 | CF73: 0.65654267 | CG73: 1.4424025 | CH73: 0.24 | CI73: 0.15 | CJ73: 0.0018 | CK73: - | CL73: 0.0018 | CM73: 95290189 | CN73: 80289158 | CO73: 23993213 | CP73: - | CQ73: - | CR73: - | CS73: - | CT73: - | CU73: - | CV73: BR0ET3CTF007 | CW73: - | CX73: 25569.626
B74: 40107402000104 | C74: Auster Fitness I FIP Multiestratégia RL | D74: 50 | G74: Leste Investimentos | H74: Banco Genial | I74: Banco Genial | J74: EY | K74: Intranet | L74: Investidores qualificados | M74: Participações - Multiestratégia | N74: Fundos de Participações | O74: Alternativo Ilíquido | P74: FIP_x000D_ | Q74: 1103.49 | R74: FECHADO | S74: - | T74: 1103.49 | U74: 1103.49 | V74: Fechamento | W74: D+0 | X74: D+0 | Y74: D+0 | Z74: 0 | AA74: - | AB74: - | AC74: - | AD74: 0.02 | AE74: - | AF74: - | AG74: 0.2 | AH74: - | AI74: - | AJ74: IPCA | AK74: 44270 | AL74: https://www.xpi.com.br/investimentos/fundos-de-investimento/lista/#/detalhes/d751b167-b1c8-4007-a7dd-929ccbd6bcf2 | AM74: - | AN74: - | AO74: - | AP74: - | AQ74: - | AR74: - | AS74: - | AT74: - | AU74: - | AV74: - | AW74: - | AX74: - | AY74: - | AZ74: - | BA74: - | BB74: - | BC74: - | BD74: - | BE74: - | BF74: - | BG74: - | BH74: - | BI74: - | BJ74: - | BK74: - | BL74: - | BM74: - | BN74: - | BO74: - | BP74: - | BQ74: - | BR74: - | BS74: - | BT74: 0.032005081 | BU74: 0.20390598 | BV74: -3.9386423 | BW74: -0.065247187 | BX74: -0.015411602 | BY74: -0.17209752 | BZ74: -0.018004018 | CA74: -0.0015949068 | CB74: -0.018635166 | CC74: -0.0088170023 | CD74: 0.0021654086 | CE74: -0.083066664 | CF74: -0.016391694 | CG74: 1436.8609 | CH74: 0.1 | CI74: 0.05 | CJ74: 0.002 | CK74: - | CL74: 0.002 | CM74: 87415745 | CN74: 86712099 | CO74: - | CP74: - | CQ74: - | CR74: - | CS74: - | CT74: - | CU74: - | CV74: BR07JNCTF009 | CW74: - | CX74: 25569.605
B75: 45338646000111 | C75: AVBI11 - VBI Crédito | D75: 16 | G75: VBI Securities | H75: BRL Trust Investimentos | I75: BRL Trust Investimentos | J75: KPMG | K75: Intranet | L75: Investidores em geral | M75: Investimento Imobiliário | N75: FII TVM Gestão Ativa | O75: Fundo Listado | P75: FII | Q75: 10 | R75: FECHADO | S75: - | T75: 0.01 | U75: 0.01 | V75: Fechamento | W75: D+0 | X75: D+0 | Y75: D+3 (útil) | Z75: 3 | AA75: - | AB75: - | AC75: - | AD75: 0.011 | AE75: - | AF75: - | AG75: 0.2 | AH75: Dezembro / Junho | AI75: Novembro / Maio | AJ75: CDI | AK75: 44746 | AL75: https://www.xpi.com.br/investimentos/fundos-de-investimento/lista/#/detalhes/78040a1a-b961-4dc5-8c12-d8d0ff57c896 | AM75: - | AN75: - | AO75: - | AP75: - | AQ75: - | AR75: - | AS75: - | AT75: - | AU75: - | AV75: - | AW75: - | AX75: - | AY75: - | AZ75: - | BA75: - | BB75: - | BC75: - | BD75: - | BE75: - | BF75: - | BG75: - | BH75: - | BI75: - | BJ75: - | BK75: - | BL75: - | BM75: - | BN75: - | BO75: - | BP75: - | BQ75: - | BR75: - | BS75: - | BT75: - | BU75: - | BV75: - | BW75: - | BX75: - | BY75: - | BZ75: - | CA75: - | CB75: - | CC75: - | CD75: - | CE75: - | CF75: - | CG75: - | CH75: 0.1 | CI75: 0.05 | CJ75: 0.0011 | CK75: - | CL75: 0.0011 | CM75: - | CN75: - | CO75: - | CP75: - | CQ75: - | CR75: - | CS75: - | CT75: - | CU75: - | CV75: BR0C9JCTF009 | CW75: - | CX75: 25569.605
B76: 35002482000101 | C76: AXA WF Framlington Digital Economy Advisory CIC CIA IE RL | D76: 32 | F76: «« | G76: XP Allocation Asset Management LTDA. | H76: BNP Paribas | I76: BNP Paribas | J76: PriceWaterhouseCoopers | K76: Geral | L76: Investidores qualificados | M76: Ações | N76: Ações Investimento no Exterior | O76: Internacional Ações Hedgeado | P76: Renda Variável - Alíquota de IR de 15% incidida sobre o lucro obtido no momento do resgate. | Q76: 500 | R76: ABERTO | S76: - | T76: 100 | U76: 100 | V76: Fechamento | W76: D+1 (útil) | X76: D+1 (útil) | Y76: D+5 (útil) | Z76: 6 | AA76: - | AB76: - | AC76: AXA WF FRAMLINGTON DIGITAL ECONOMY ADVISORY INVESTIMENTO NO EXTERIOR RESP LIMITADA FIF CIC AÇÕES | AD76: 0.008 | AE76: 0.208 | AF76: 0.012 | AG76: - | AH76: - | AI76: - | AJ76: - | AK76: 43822 | AL76: https://www.xpi.com.br/investimentos/fundos-de-investimento/lista/#/detalhes/8406a81e-28fd-4587-bedb-0f3efac85e40 | AM76: 0.077815708 | AN76: -0.12333496 | AO76: -0.013427121 | AP76: 0.068649765 | AQ76: 0.14376366 | AR76: 0.17567926 | AS76: 0.42310706 | AT76: -0.35799428 | AU76: - | AV76: - | AW76: 0.089240121 | AX76: 7.1329166 | AY76: - | AZ76: - | BA76: 0.50673291 | BB76: 1.13054 | BC76: 1.6155941 | BD76: 3.242836 | BE76: - | BF76: - | BG76: - | BH76: 0.88762922 | BI76: 0.066906327 | BJ76: -0.16873731 | BK76: -0.16170203 | BL76: -0.058852432 | BM76: 0.014727185 | BN76: 0.066939535 | BO76: 0.29263267 | BP76: -0.48172432 | BQ76: - | BR76: - | BS76: -0.010265429 | BT76: 0.20304541 | BU76: 0.23869126 | BV76: -0.64625834 | BW76: 0.085433262 | BX76: -0.28103541 | BY76: -0.42422724 | BZ76: 0.45765508 | CA76: 0.24409253 | CB76: -0.19319478 | CC76: 0.24823964 | CD76: 0.18258967 | CE76: 0.56759209 | CF76: 0.38797252 | CG76: 171.66208 | CH76: 0.63 | CI76: - | CJ76: 0.00504 | CK76: - | CL76: 0.00504 | CM76: 1.5041489e+08 | CN76: 1.7317273e+08 | CO76: -19925718 | CP76: - | CQ76: - | CR76: - | CS76: - | CT76: - | CU76: - | CV76: BR037WCTF003 | CW76: - | CX76: 25569.647
B77: 35002463000177 | C77: AXA WF Framlington Robotech Adv Classe de FIC CIA IE RL | D77: 28 | F77: «««« | G77: XP Allocation Asset Management LTDA. | H77: BNP Paribas | I77: BNP Paribas | J77: PriceWaterhouseCoopers | K77: Geral | L77: Investidores qualificados | M77: Ações | N77: Ações Investimento no Exterior | O77: Internacional Ações Hedgeado | P77: Renda Variável - Alíquota de IR de 15% incidida sobre o lucro obtido no momento do resgate. | Q77: 500 | R77: ABERTO | S77: - | T77: 100 | U77: 100 | V77: Fechamento | W77: D+1 (útil) | X77: D+1 (útil) | Y77: D+5 (útil) | Z77: 6 | AA77: - | AB77: - | AC77: AXA WF FRAMLINGTON ROBOTECH ADV INVESTIMENTO NO EXTERIOR RESP LIMITADA FIF CIC AÇÕES | AD77: 0.008 | AE77: 0.208 | AF77: 0.012 | AG77: - | AH77: - | AI77: - | AJ77: - | AK77: 43822 | AL77: https://www.xpi.com.br/investimentos/fundos-de-investimento/lista/#/detalhes/fc1c00aa-39ae-4c71-8586-3cd1e465afe3 | AM77: 0.19762114 | AN77: 0.15764204 | AO77: 0.53289359 | AP77: 0.21980506 | AQ77: 0.22120671 | AR77: 0.1500605 | AS77: 0.31810585 | AT77: -0.30225871 | AU77: - | AV77: - | AW77: 0.14512442 | AX77: 18.114788 | AY77: 3.4721118 | AZ77: 3.5939566 | BA77: 1.7410274 | BB77: 1.8708635 | BC77: 1.379997 | BD77: 2.4380711 | BE77: - | BF77: - | BG77: - | BH77: 1.6786285 | BI77: 0.18671175 | BJ77: 0.11223969 | BK77: 0.38461868 | BL77: 0.083067563 | BM77: 0.092081445 | BN77: 0.041320776 | BO77: 0.18763146 | BP77: -0.42598874 | BQ77: - | BR77: - | BS77: 0.054001599 | BT77: 0.20550826 | BU77: 0.25213421 | BV77: 1.5094735 | BW77: 0.29231666 | BX77: -0.15433682 | BY77: -0.39229685 | BZ77: 0.49518643 | CA77: 0.45483578 | CB77: -0.42536151 | CC77: 0.44178099 | CD77: 0.31381001 | CE77: 0.55222922 | CF77: 0.59341305 | CG77: 235.52282 | CH77: 0.63 | CI77: - | CJ77: 0.00504 | CK77: - | CL77: 0.00504 | CM77: 71868824 | CN77: 64636297 | CO77: -4769268.3 | CP77: - | CQ77: - | CR77: - | CS77: - | CT77: - | CU77: - | CV77: BR036WCTF005 | CW77: - | CX77: 25569.647
B78: 54886474000101 | C78: Axa WF US Dynamic High Yield Bonds Classe FIC Classes FIM CP RL | D78: 26 | G78: XP VISTA ASSET MANAGMENT LTDA | H78: BNP Paribas | I78: BNP Paribas | J78: PriceWaterhouseCoopers | K78: Geral | L78: Investidores em geral | M78: Multimercado | N78: Multimercados Investimento no Exterior | O78: Internacional Renda Fixa Hedgeado | P78: Longo Prazo | Q78: 100 | R78: ABERTO | S78: - | T78: 100 | U78: 100 | V78: Fechamento | W78: D+1 (útil) | X78: D+1 (útil) | Y78: D+5 (útil) | Z78: 6 | AA78: - | AB78: - | AC78: AXA WF US DYNAMIC HIGH YIELD BONDS INVESTIMENTO NO EXTERIOR RESP LIMITADA FIF CIC MULTIMERCADO CRÉDITO PRIVADO | AD78: 0.007 | AE78: 0.207 | AF78: 0.011 | AG78: - | AH78: - | AI78: - | AJ78: - | AK78: 45412 | AL78: https://www.xpi.com.br/investimentos/fundos-de-investimento/lista/#/detalhes/cb8a2a9e-80bb-4b1f-afec-4ddd44e7ddfe | AM78: 0.029543276 | AN78: 0.030712563 | AO78: 0.16875431 | AP78: 0.12833898 | AQ78: - | AR78: - | AS78: - | AT78: - | AU78: - | AV78: - | AW78: 0.12833898 | AX78: 2.7080615 | AY78: 0.67645312 | AZ78: 1.1381178 | BA78: - | BB78: - | BC78: - | BD78: - | BE78: - | BF78: - | BG78: - | BH78: 0.97426931 | BI78: 0.018633895 | BJ78: -0.014689789 | BK78: 0.020479401 | BL78: - | BM78: - | BN78: - | BO78: - | BP78: - | BQ78: - | BR78: - | BS78: -0.0029949449 | BT78: 0.038556364 | BU78: 0.04095457 | BV78: 0.47792885 | BW78: -0.048578711 | BX78: -0.018058838 | BY78: -0.051770141 | BZ78: 0.080460744 | CA78: 0.3430584 | CB78: -0.34243257 | CC78: 0.37145664 | CD78: 0.24678689 | CE78: 0.41741937 | CF78: 0.51847857 | CG78: 127.2539 | CH78: - | CI78: - | CJ78: - | CK78: - | CL78: - | CM78: 23385422 | CN78: 19361229 | CO78: 9523769.5 | CP78: - | CQ78: - | CR78: - | CS78: - | CT78: - | CU78: - | CV78: BR0JBFCTF003 | CW78: - | CX78: 25569.647
B79: 35142453000137 | C79: AXA WF US HIGH YIELD BONDS ADV FIC CI MULT CP IE RL | D79: 26 | G79: XP Allocation Asset Management LTDA. | H79: BNP Paribas | I79: BNP Paribas | J79: PriceWaterhouseCoopers | K79: Geral | L79: Investidores em geral | M79: Multimercado | N79: Multimercados Investimento no Exterior | O79: Internacional Renda Fixa Hedgeado | P79: Longo Prazo - Alíquota regressiva de IR de 22,5% a 15,0% incidida sobre o lucro obtido no momento do resgate. | Q79: 100 | R79: ABERTO | S79: - | T79: 100 | U79: 100 | V79: Fechamento | W79: D+1 (útil) | X79: D+1 (útil) | Y79: D+5 (útil) | Z79: 6 | AA79: - | AB79: - | AC79: AXA WF US HIGH YIELD BONDS ADV INVESTIMENTO NO EXTERIOR RESP LIMITADA FIF CIC MULTIMERCADO CRÉDITO PRIVADO | AD79: 0.006 | AE79: 0.156 | AF79: 0.0095 | AG79: - | AH79: - | AI79: - | AJ79: CDI | AK79: 43822 | AL79: https://www.xpi.com.br/investimentos/fundos-de-investimento/lista/#/detalhes/33671e36-8aee-4af6-825f-88a3595d09af | AM79: 0.021011994 | AN79: 0.02868101 | AO79: 0.15538886 | AP79: 0.13522834 | AQ79: 0.13312561 | AR79: 0.10641731 | AS79: 0.17262172 | AT79: -0.020869072 | AU79: - | AV79: - | AW79: 0.089055651 | AX79: 1.9260481 | AY79: 0.63170757 | AZ79: 1.0479781 | BA79: 1.0303034 | BB79: 1.0363117 | BC79: 0.97864244 | BD79: 1.3230314 | BE79: - | BF79: - | BG79: - | BH79: 0.88535392 | BI79: 0.010102613 | BJ79: -0.016721342 | BK79: 0.0071139544 | BL79: 0.0035158903 | BM79: 0.0041336275 | BN79: -0.0023224157 | BO79: 0.042147328 | BP79: -0.14459911 | BQ79: - | BR79: - | BS79: -0.010478019 | BT79: 0.028108343 | BU79: 0.054797584 | BV79: 0.23383709 | BW79: -0.1245001 | BX79: -0.013229457 | BY79: -0.16739559 | BZ79: 0.093211067 | CA79: 0.37425218 | CB79: -0.34376618 | CC79: 0.43904786 | CD79: 0.33261689 | CE79: 0.44375407 | CF79: 0.56000699 | CG79: 171.47839 | CH79: 0.63 | CI79: - | CJ79: 0.00378 | CK79: - | CL79: 0.00378 | CM79: 22900498 | CN79: 31357164 | CO79: -13394545 | CP79: - | CQ79: - | CR79: - | CS79: - | CT79: - | CU79: - | CV79: BR03CFCTF009 | CW79: - | CX79: 25569.647
B80: 7279657000189 | C80: AZ Quest Ações FIF CIC Ações RL | D80: 26 | F80: ««« | G80: AZ Quest Investimentos | H80: Intrag DTVM | I80: Itaú Unibanco | J80: EY | K80: Geral | L80: Investidores em geral | M80: Ações | N80: Ações Livre | O80: Renda Variável Long Only | P80: Renda Variável - Alíquota de IR de 15% incidida sobre o lucro obtido no momento do resgate. | Q80: 1000 | R80: ABERTO | S80: - | T80: 1000 | U80: 1000 | V80: Fechamento | W80: D+1 (útil) | X80: D+1 (útil) | Y80: D+2 (útil) | Z80: 3 | AA80: - | AB80: - | AC80: AZ QUEST AÇÕES RESP LIMITADA FIF CIC AÇÕES | AD80: 0.02 | AE80: 0.02 | AF80: 0.025 | AG80: 0.2 | AH80: Junho / Dezembro | AI80: Maio / Novembro | AJ80: Ibovespa | AK80: 38504 | AL80: https://www.xpi.com.br/investimentos/fundos-de-investimento/lista/#/detalhes/36839d9c-7833-4544-96d2-a543004783df | AM80: -0.0093589272 | AN80: 0.07899511 | AO80: 0.27903229 | AP80: 0.16799203 | AQ80: 0.18401612 | AR80: -0.057699811 | AS80: 0.16577874 | AT80: -0.0034799358 | AU80: - | AV80: - | AW80: 0.14941592 | AX80: - | AY80: 1.7398903 | AZ80: 1.8818578 | BA80: 1.2995693 | BB80: 1.5032336 | BC80: - | BD80: 1.2705845 | BE80: - | BF80: - | BG80: - | BH80: 2.4247237 | BI80: -0.020268309 | BJ80: 0.033592758 | BK80: 0.13075738 | BL80: 0.034291761 | BM80: 0.054884046 | BN80: -0.16643954 | BO80: 0.035304343 | BP80: -0.12720997 | BQ80: - | BR80: - | BS80: 0.082698081 | BT80: 0.20613836 | BU80: 0.22775878 | BV80: 0.6266714 | BW80: 0.28513057 | BX80: -0.10937981 | BY80: -0.49017667 | BZ80: 0.80535563 | CA80: 0.93416262 | CB80: -0.46371022 | CC80: 0.66619996 | CD80: 0.5520741 | CE80: 0.075375692 | CF80: 0.77146091 | CG80: 18.204629 | CH80: 0.24 | CI80: 0.15 | CJ80: 0.0048 | CK80: - | CL80: 0.0048 | CM80: 1.5061365e+08 | CN80: 2.0673276e+08 | CO80: -70413500 | CP80: - | CQ80: - | CR80: - | CS80: - | CT80: - | CU80: - | CV80: BRQAFICTF006 | CW80: - | CX80: 25569.626
B81: 32240069000189 | C81: AZ Quest Advisory Total Return FIC FIF Multimercado | D81: 13 | E81: Sim | F81: «««« | G81: AZ Quest Investimentos | H81: BTG Pactual Serviços Financeiros | I81: Banco BTG Pactual | J81: Deloitte Touche Tohmatsu | K81: Geral | L81: Investidores em geral | M81: Multimercado | N81: Multimercados Long and Short Direcional | O81: Long Short Direcional | P81: Renda Variável - Alíquota de IR de 15% incidida sobre o lucro obtido no momento do resgate. | Q81: 500 | R81: ABERTO | S81: - | T81: 100 | U81: 100 | V81: Fechamento | W81: D+1 (útil) | X81: D+27 (corridos) | Y81: D+2 (útil) | Z81: 29 | AA81: Sim | AB81: 0.05 | AC81: AZ QUEST ADVISORY TOTAL RETURN FIF CIC MULTIMERCADO | AD81: 0.0195 | AE81: 0.0195 | AF81: 0.025 | AG81: 0.25 | AH81: Janeiro / Julho | AI81: Junho | AJ81: CDI | AK81: 43480 | AL81: https://www.xpi.com.br/investimentos/fundos-de-investimento/lista/#/detalhes/7b955fbb-fb65-4478-b5ff-ee135f63ef85 | AM81: 0.0087560057 | AN81: 0.05275474 | AO81: 0.20082439 | AP81: 0.16623876 | AQ81: 0.15905343 | AR81: 0.1887641 | AS81: 0.14443746 | AT81: 0.11632418 | AU81: - | AV81: - | AW81: 0.095321874 | AX81: 0.80261248 | AY81: 1.1619385 | AZ81: 1.3544057 | BA81: 1.2849662 | BB81: 1.2690747 | BC81: 1.7359258 | BD81: 1.1070177 | BE81: 0.94014508 | BF81: - | BG81: - | BH81: 1.0318227 | BI81: -0.0021533758 | BJ81: 0.0073523879 | BK81: 0.052549478 | BL81: 0.032643516 | BM81: 0.029967381 | BN81: 0.080024375 | BO81: 0.013963064 | BP81: -0.0074058511 | BQ81: - | BR81: - | BS81: 0.0026912223 | BT81: 0.03706815 | BU81: 0.052871102 | BV81: 1.2264058 | BW81: 0.065530025 | BX81: -0.012168215 | BY81: -0.10755602 | BZ81: 0.053807231 | CA81: 0.73052898 | CB81: -0.42536682 | CC81: 0.5355414 | CD81: 0.47448491 | CE81: 0.079504684 | CF81: 0.64925312 | CG81: 1.9377842 | CH81: 0.2 | CI81: 0.2 | CJ81: 0.0039 | CK81: 0.0022881924 | CL81: 0.0061881924 | CM81: 1.2134663e+08 | CN81: 1.0976509e+08 | CO81: 7851853 | CP81: - | CQ81: - | CR81: - | CS81: - | CT81: - | CU81: - | CV81: BR010ZCTF003 | CW81: - | CX81: 25569.626
B82: 34370777000160 | C82: AZ Quest Altro Advisory FIC de FIF Multimercado CP | D82: 13 | E82: Sim | G82: AZ Quest MZK Investimentos | H82: BNY Mellon Serviços Financeiros | I82: BNY Mellon Banco | J82: Deloitte Touche Tohmatsu | K82: Geral | L82: Investidores em geral | M82: Multimercado | N82: Multimercados Dinâmico | O82: Crédito High Grade | P82: Longo Prazo - Alíquota regressiva de IR de 22,5% a 15,0% incidida sobre o lucro obtido no momento do resgate. | Q82: 500 | R82: ABERTO | S82: - | T82: 100 | U82: 100 | V82: Fechamento | W82: D+0 | X82: D+44 (corridos) | Y82: D+1 (útil) | Z82: 45 | AA82: - | AB82: - | AC82: AZ QUEST ALTRO ADVISORY FIF CIC MULTIMERCADO CRÉDITO PRIVADO | AD82: 0.008 | AE82: 0.008 | AF82: 0.012 | AG82: 0.2 | AH82: Janeiro / Julho | AI82: Junho | AJ82: CDI | AK82: 43733 | AL82: https://www.xpi.com.br/investimentos/fundos-de-investimento/lista/#/detalhes/bdc1e948-87e9-494c-b25c-90af01f23357 | AM82: 0.0085160165 | AN82: 0.024568324 | AO82: 0.132118 | AP82: 0.1310335 | AQ82: 0.15047098 | AR82: 0.13301821 | AS82: 0.12929383 | AT82: 0.13902608 | AU82: - | AV82: - | AW82: 0.10354908 | AX82: 0.78061405 | AY82: 0.54112449 | AZ82: 0.89103408 | BA82: 0.99638164 | BB82: 1.1908596 | BC82: 1.2232715 | BD82: 0.99095175 | BE82: 1.1236244 | BF82: - | BG82: - | BH82: 1.0971815 | BI82: -0.002393365 | BJ82: -0.020834028 | BK82: -0.016156911 | BL82: -0.00042054266 | BM82: 0.0214107 | BN82: 0.024278478 | BO82: -0.0011805645 | BP82: 0.015296049 | BQ82: - | BR82: - | BS82: 0.0083807739 | BT82: 0.00845556 | BU82: 0.010087369 | BV82: -1.6725405 | BW82: 0.65576016 | BX82: -0.010210292 | BY82: -0.065412208 | BZ82: 0.0072793124 | CA82: 0.23466887 | CB82: -0.096920512 | CC82: 0.40762711 | CD82: 0.19906322 | CE82: 0.14510533 | CF82: 0.43366993 | CG82: 1.9099961 | CH82: 0.29 | CI82: 0.2 | CJ82: 0.00232 | CK82: - | CL82: 0.00232 | CM82: 6.1323751e+08 | CN82: 6.2044208e+08 | CO82: -36367233 | CP82: - | CQ82: - | CR82: - | CS82: - | CT82: - | CU82: - | CV82: BR02W0CTF008 | CW82: - | CX82: 25569.626
B83: 36499625000197 | C83: AZ Quest Bayes LB Sistemático FIF Multimercado | D83: 16 | G83: AZ Quest Investimentos | H83: BTG Pactual Serviços Financeiros | I83: Banco BTG Pactual | J83: EY | K83: Geral | L83: Investidores em geral | M83: Multimercado | N83: Multimercados Livre | O83: Renda Variável Long Biased | P83: Renda Variavel | Q83: 500 | R83: ABERTO | S83: - | T83: 100 | U83: 500 | V83: Fechamento | W83: D+1 (útil) | X83: D+14 (útil) | Y83: D+2 (útil) | Z83: 16 | AA83: - | AB83: - | AC83: - | AD83: 0.02 | AE83: - | AF83: 0.025 | AG83: 0.2 | AH83: Junho / Dezembro | AI83: Maio / Novembro | AJ83: IMA-B 5+ | AK83: 43980 | AL83: https://www.xpi.com.br/investimentos/fundos-de-investimento/lista/#/detalhes/042a9a18-1d0b-4534-92ef-58042e02871f | AM83: 0.021458307 | AN83: 0.099129419 | AO83: 0.31997296 | AP83: 0.13625476 | AQ83: 0.16990637 | AR83: -0.096234579 | AS83: 0.25279183 | AT83: 0.038242731 | AU83: - | AV83: - | AW83: 0.15006019 | AX83: 1.9669591 | AY83: 2.1833543 | AZ83: 2.157971 | BA83: 1.0386227 | BB83: 1.3696537 | BC83: - | BD83: 1.9374823 | BE83: 0.30908203 | BF83: - | BG83: - | BH83: 1.64538 | BI83: 0.010548926 | BJ83: 0.053727067 | BK83: 0.17169805 | BL83: 0.0044792096 | BM83: 0.040795104 | BN83: -0.20497431 | BO83: 0.12231744 | BP83: -0.085487305 | BQ83: - | BR83: - | BS83: 0.053939888 | BT83: 0.11117149 | BU83: 0.11605567 | BV83: 1.3099622 | BW83: 0.42169865 | BX83: -0.053814682 | BY83: -0.13073162 | BZ83: 0.50864942 | CA83: 0.86405387 | CB83: -0.38761118 | CC83: 0.59760677 | CD83: 0.5566381 | CE83: 0.065536999 | CF83: 0.6888015 | CG83: 2.2806498 | CH83: 0.24 | CI83: 0.15 | CJ83: 0.0048 | CK83: 0.005196487 | CL83: 0.009996487 | CM83: 13305544 | CN83: 12841703 | CO83: -1128435.6 | CP83: - | CQ83: - | CR83: - | CS83: - | CT83: - | CU83: - | CV83: BR0C8NCTF003 | CW83: - | CX83: 25569.626
B84: 46929688000190 | C84: AZ Quest Bayes LS Sistemático FIF em Cotas de FIM | D84: 14 | G84: Bayes Capital | H84: BTG Pactual Serviços Financeiros | I84: Banco BTG Pactual | J84: EY | K84: Geral | L84: Investidores em geral | M84: Multimercado | N84: Multimercados Long and Short Direcional | O84: Long Short Neutro | P84: Ações | Q84: 500 | R84: ABERTO | S84: - | T84: 100 | U84: 500 | V84: Fechamento | W84: D+1 (útil) | X84: D+14 (útil) | Y84: D+2 (útil) | Z84: 16 | AA84: - | AB84: - | AC84: AZ QUEST BAYES LONG SHORT SISTEMÁTICO FIC MULTIMERCADO | AD84: 0.02 | AE84: 0.02 | AF84: 0.025 | AG84: 0.2 | AH84: Janeiro / Julho | AI84: Junho | AJ84: CDI | AK84: 44771 | AL84: https://www.xpi.com.br/investimentos/fundos-de-investimento/lista/#/detalhes/511f581d-b6b4-4f13-bf34-a3922e033542 | AM84: 0.047080933 | AN84: 0.12675128 | AO84: 0.32853043 | AP84: 0.12183801 | AQ84: 0.14021635 | AR84: 0.02967364 | AS84: 0.16500027 | AT84: - | AU84: - | AV84: - | AW84: 0.14510223 | AX84: 4.3156373 | AY84: 2.7917338 | AZ84: 2.2156846 | BA84: 0.92246116 | BB84: 1.0989233 | BC84: 0.27288683 | BD84: 1.264618 | BE84: - | BF84: - | BG84: - | BH84: 1.1343328 | BI84: 0.036171552 | BJ84: 0.081348929 | BK84: 0.18025552 | BL84: -0.0090464282 | BM84: 0.011193782 | BN84: -0.079066088 | BO84: 0.034525874 | BP84: - | BQ84: - | BR84: - | BS84: 0.015234844 | BT84: 0.077299891 | BU84: 0.079077588 | BV84: 1.9263914 | BW84: 0.2026924 | BX84: -0.030134382 | BY84: -0.095580131 | BZ84: -0.041972533 | CA84: 0.085871536 | CB84: 0.060289086 | CC84: -0.0088453543 | CD84: 0.079035189 | CE84: -0.10516248 | CF84: 0.015444242 | CG84: 1.6585629 | CH84: 0.18 | CI84: 0.1 | CJ84: 0.0036 | CK84: 0.0031395883 | CL84: 0.0067395883 | CM84: 24058925 | CN84: 19819594 | CO84: 2710100.4 | CP84: - | CQ84: - | CR84: - | CS84: - | CT84: - | CU84: - | CV84: BR0D03CTF005 | CW84: - | CX84: 25569.626
B85: 37569846000157 | C85: AZ Quest Bayes Sistemático FIF CIA RL | D85: 26 | G85: Bayes Capital | H85: Intrag DTVM | I85: Itaú Unibanco | J85: PriceWaterhouseCoopers | K85: Geral | L85: Investidores em geral | M85: Ações | N85: Ações Livre | O85: Renda Variável Long Only | P85: Renda Variável | Q85: 500 | R85: ABERTO | S85: - | T85: 100 | U85: 500 | V85: Fechamento | W85: D+1 (útil) | X85: D+14 (útil) | Y85: D+2 (útil) | Z85: 16 | AA85: - | AB85: - | AC85: - | AD85: 0.02 | AE85: - | AF85: 0.025 | AG85: 0.2 | AH85: Junho / Dezembro | AI85: Maio / Novembro | AJ85: Ibovespa | AK85: 44041 | AL85: https://www.xpi.com.br/investimentos/fundos-de-investimento/lista/#/detalhes/ecf2b41e-39a1-4482-a65b-6e1ade9b9f1d | AM85: -0.0013657254 | AN85: 0.07537044 | AO85: 0.29584904 | AP85: 0.16420732 | AQ85: 0.2075676 | AR85: -0.12429808 | AS85: 0.30607901 | AT85: -0.044708322 | AU85: - | AV85: - | AW85: 0.11816482 | AX85: - | AY85: 1.6600558 | AZ85: 1.9952738 | BA85: 1.2680736 | BB85: 1.7333968 | BC85: - | BD85: 2.3458933 | BE85: - | BF85: - | BG85: - | BH85: 1.1621818 | BI85: -0.012275107 | BJ85: 0.029968088 | BK85: 0.14757413 | BL85: 0.030733952 | BM85: 0.078429783 | BN85: -0.23303781 | BO85: 0.17560462 | BP85: -0.16843836 | BQ85: - | BR85: - | BS85: 0.014967963 | BT85: 0.16556215 | BU85: 0.17190954 | BV85: 0.81346491 | BW85: 0.1553504 | BX85: -0.098882907 | BY85: -0.24617252 | BZ85: 0.84289154 | CA85: 0.93811601 | CB85: -0.43993284 | CC85: 0.66597607 | CD85: 0.55284163 | CE85: 0.094169431 | CF85: 0.76101642 | CG85: 1.8964704 | CH85: 0.24 | CI85: 0.15 | CJ85: 0.0048 | CK85: - | CL85: 0.0048 | CM85: 3.482099e+08 | CN85: 3.3431784e+08 | CO85: 24210596 | CP85: - | CQ85: - | CR85: - | CS85: - | CT85: - | CU85: - | CV85: BR0AYKCTF004 | CW85: - | CX85: 25569.626
B86: 64169533000184 | C86: AZ Quest Debêntures Incentivadas 01/2032 FIC FI-Infra RL | D86: 40 | G86: AZ QUEST INFRA LTDA. | H86: Banco Daycoval | I86: Banco Daycoval | J86: EY | K86: Intranet | L86: Não definido | M86: Renda Fixa | N86: Renda Fixa Duração Livre Crédito Livre | O86: Fundo Listado | P86: Debêntures Incentivadas | Q86: 1000 | R86: FECHADO | S86: - | T86: 1000 | U86: 1000 | V86: Abertura | W86: D+0 | X86: D+0 | Y86: D+0 | Z86: 0 | AA86: - | AB86: - | AC86: - | AD86: 0.0125 | AE86: - | AF86: 0.0125 | AG86: - | AH86: - | AI86: - | AJ86: - | AK86: 46056 | AL86: https://www.xpi.com.br/investimentos/fundos-de-investimento/lista/#/detalhes/27c5ffba-11f2-48d7-87ef-0539ab8fae8c | AM86: - | AN86: - | AO86: - | AP86: - | AQ86: - | AR86: - | AS86: - | AT86: - | AU86: - | AV86: - | AW86: - | AX86: - | AY86: - | AZ86: - | BA86: - | BB86: - | BC86: - | BD86: - | BE86: - | BF86: - | BG86: - | BH86: - | BI86: - | BJ86: - | BK86: - | BL86: - | BM86: - | BN86: - | BO86: - | BP86: - | BQ86: - | BR86: - | BS86: - | BT86: - | BU86: 7.2881955e-05 | BV86: - | BW86: -0.4308761 | BX86: - | BY86: - | BZ86: -1.8397143e-05 | CA86: - | CB86: - | CC86: - | CD86: - | CE86: - | CF86: - | CG86: 103.22263 | CH86: 0.15 | CI86: - | CJ86: 0.001875 | CK86: - | CL86: 0.001875 | CM86: 2.0644527e+08 | CN86: - | CO86: 200000000 | CP86: - | CQ86: - | CR86: - | CS86: - | CT86: - | CU86: - | CV86: - | CW86: - | CX86: 25569.626
B87: 25213405000139 | C87: AZ Quest Debêntures Incentivadas CP FIC de FIF Incentivado de Investimento em Infra RF | D87: 11 | E87: Sim | F87: ««« | G87: AZ QUEST INFRA LTDA. | H87: BTG Pactual Serviços Financeiros | I87: Banco BTG Pactual | J87: KPMG | K87: Geral | L87: Investidores em geral | M87: Renda Fixa | N87: Renda Fixa Duração Livre Crédito Livre | O87: Debêntures Incentivadas Não Hedgeado | P87: Debêntures Incentivadas - Isento de IR para pessoa física. | Q87: 1000 | R87: ABERTO | S87: - | T87: 500 | U87: 1000 | V87: Fechamento | W87: D+0 | X87: D+29 (corridos) | Y87: D+1 (útil) | Z87: 30 | AA87: - | AB87: - | AC87: AZ QUEST DEBÊNTURES INCENTIVADAS FIF CIC FI INFRA RENDA FIXA CRÉDITO PRIVADO | AD87: 0.011 | AE87: 0.011 | AF87: 0.015 | AG87: 0.2 | AH87: Janeiro / Julho | AI87: Junho | AJ87: IMA-B 5 | AK87: 42619 | AL87: https://www.xpi.com.br/investimentos/fundos-de-investimento/lista/#/detalhes/4025f2f3-65c9-4376-826a-8b1c800a7b2e | AM87: -0.0020152553 | AN87: 0.01999832 | AO87: 0.10155844 | AP87: 0.10163313 | AQ87: 0.13204329 | AR87: 0.10364712 | AS87: 0.11691606 | AT87: 0.08834295 | AU87: - | AV87: - | AW87: 0.10172285 | AX87: - | AY87: 0.4404688 | AZ87: 0.68493342 | BA87: 0.7621585 | BB87: 1.0268234 | BC87: 0.95316703 | BD87: 0.8960843 | BE87: 0.71399761 | BF87: - | BG87: - | BH87: 1.1514956 | BI87: -0.012924637 | BJ87: -0.025404032 | BK87: -0.046716469 | BL87: -0.027984268 | BM87: 0.0030563028 | BN87: -0.005092604 | BO87: -0.013558338 | BP87: -0.035387086 | BQ87: - | BR87: - | BS87: 0.012296791 | BT87: 0.026282595 | BU87: 0.031080551 | BV87: -1.5679581 | BW87: 0.29381111 | BX87: -0.018909377 | BY87: -0.062322543 | BZ87: 0.066775938 | CA87: 0.53603537 | CB87: -0.35282361 | CC87: 0.79493158 | CD87: 0.75045839 | CE87: 0.02289074 | CF87: 0.67852549 | CG87: 2.5343187 | CH87: 0.25 | CI87: 0.15 | CJ87: 0.00275 | CK87: - | CL87: 0.00275 | CM87: 4.2152673e+08 | CN87: 4.2628524e+08 | CO87: -2090553.8 | CP87: - | CQ87: - | CR87: - | CS87: - | CT87: - | CU87: - | CV87: BRAZQ8CTF008 | CW87: - | CX87: 25569.626
B88: 10320188000109 | C88: AZ Quest Low Vol FIF Multimercado RL | D88: 13 | F88: ««« | G88: AZ Quest Investimentos | H88: BTG Pactual Serviços Financeiros | I88: Banco BTG Pactual | J88: EY | K88: Geral | L88: Investidores em geral | M88: Multimercado | N88: Multimercados Dinâmico | O88: Multiestratégia | P88: Longo Prazo - Alíquota regressiva de IR de 22,5% a 15,0% incidida sobre o lucro obtido no momento do resgate. | Q88: 500 | R88: ABERTO | S88: - | T88: 300 | U88: 500 | V88: Fechamento | W88: D+0 | X88: D+0 | Y88: D+1 (útil) | Z88: 1 | AA88: - | AB88: - | AC88: - | AD88: 0.0085 | AE88: - | AF88: 0.0175 | AG88: 0.2 | AH88: Janeiro / Julho | AI88: Junho | AJ88: CDI | AK88: 39780 | AL88: https://www.xpi.com.br/investimentos/fundos-de-investimento/lista/#/detalhes/a8f3cd37-cbbb-457f-ad7c-1179174eca2b | AM88: 0.011086566 | AN88: 0.044905216 | AO88: 0.15042392 | AP88: 0.13412067 | AQ88: 0.13213927 | AR88: 0.11184689 | AS88: 0.13820539 | AT88: 0.14866207 | AU88: - | AV88: - | AW88: 0.10817386 | AX88: 1.0162415 | AY88: 0.98905044 | AZ88: 1.0144934 | BA88: 1.0213339 | BB88: 1.027664 | BC88: 1.0285743 | BD88: 1.059253 | BE88: 1.2015035 | BF88: - | BG88: - | BH88: 1.2036942 | BI88: 0.0001771845 | BJ88: -0.00049713577 | BK88: 0.0021490115 | BL88: 0.0024763601 | BM88: 0.003151833 | BN88: 0.0031071612 | BO88: 0.0077309998 | BP88: 0.024932036 | BQ88: - | BR88: - | BS88: 0.016796191 | BT88: 0.010663156 | BU88: 0.013322809 | BV88: 0.18074168 | BW88: 0.66299994 | BX88: -0.0028885845 | BY88: -0.020109057 | BZ88: 0.007745587 | CA88: -0.016813259 | CB88: 0.021009091 | CC88: 0.0033247609 | CD88: 0.022037962 | CE88: 0.076017013 | CF88: 0.092621662 | CG88: 5.9417136 | CH88: 0.32 | CI88: 0.1 | CJ88: 0.00272 | CK88: 3.7430261e-05 | CL88: 0.0027574303 | CM88: 2.8110274e+09 | CN88: 2.7275903e+09 | CO88: -30503646 | CP88: - | CQ88: - | CR88: - | CS88: - | CT88: - | CU88: - | CV88: BRLOW4CTF009 | CW88: - | CX88: 25569.626
B89: 52280036000170 | C89: AZ Quest Luce Advisory II FIC FIF RF CP LP | D89: 10 | G89: AZ Quest MZK Investimentos | H89: BNY Mellon Serviços Financeiros | I89: BNY Mellon Banco | J89: KPMG | K89: Geral | L89: Investidores em geral | M89: Renda Fixa | N89: Renda Fixa Duração Livre Grau de Investimento | O89: Crédito Liquidez | P89: Longo Prazo | Q89: 500 | R89: ABERTO | S89: - | T89: 500 | U89: 500 | V89: Fechamento | W89: D+0 | X89: D+0 | Y89: D+1 (útil) | Z89: 1 | AA89: - | AB89: - | AC89: AZ QUEST LUCE ADVISORY II FIF CIC RENDA FIXA CRÉDITO PRIVADO LP | AD89: 0.0065 | AE89: 0.0065 | AF89: 0.0105 | AG89: - | AH89: - | AI89: - | AJ89: CDI | AK89: 45196 | AL89: https://www.xpi.com.br/investimentos/fundos-de-investimento/lista/#/detalhes/d1061c4e-e0eb-40c9-8be6-50067a383dcd | AM89: 0.0097431558 | AN89: 0.033650073 | AO89: 0.13484676 | AP89: 0.12858342 | AQ89: - | AR89: 0.12174591 | AS89: - | AT89: - | AU89: - | AV89: - | AW89: 0.13239949 | AX89: 0.89309883 | AY89: 0.74115264 | AZ89: 0.9094375 | BA89: 0.976627 | BB89: - | BC89: 1.1196084 | BD89: - | BE89: - | BF89: - | BG89: - | BH89: 1.0372638 | BI89: -0.0011662256 | BJ89: -0.011752279 | BK89: -0.013428147 | BL89: -0.0027192831 | BM89: - | BN89: 0.013006185 | BO89: - | BP89: - | BQ89: - | BR89: - | BS89: 0.0042180627 | BT89: 0.0049080427 | BU89: 0.0042330259 | BV89: -2.3955149 | BW89: 0.90987332 | BX89: -0.0030788247 | BY89: -0.0030788247 | BZ89: 0.0014466641 | CA89: -0.040412689 | CB89: 0.072481527 | CC89: -0.052707874 | CD89: -0.16120179 | CE89: 0.036214308 | CF89: 0.01886819 | CG89: 1.3774332 | CH89: 0.25 | CI89: 0.21 | CJ89: 0.001625 | CK89: - | CL89: 0.001625 | CM89: 3.7161729e+08 | CN89: 4.5935315e+08 | CO89: -1.9827236e+08 | CP89: - | CQ89: - | CR89: - | CS89: - | CT89: - | CU89: - | CV89: BR0GZECTF001 | CW89: - | CX89: 25569.626
B90: 4455632000109 | C90: AZ Quest Multi FIC de FIF Multimercado | D90: 13 | F90: «««« | G90: AZ Quest MZK Investimentos | H90: BNY Mellon Serviços Financeiros | I90: BNY Mellon Banco | J90: Deloitte Touche Tohmatsu | K90: Geral | L90: Investidores em geral | M90: Multimercado | N90: Multimercados Macro | O90: Macro Média Vol | P90: Longo Prazo - Alíquota regressiva de IR de 22,5% a 15,0% incidida sobre o lucro obtido no momento do resgate. | Q90: 1000 | R90: ABERTO | S90: - | T90: 500 | U90: 500 | V90: Fechamento | W90: D+0 | X90: D+0 | Y90: D+1 (útil) | Z90: 1 | AA90: - | AB90: - | AC90: - | AD90: 0.015 | AE90: - | AF90: 0.025 | AG90: 0.2 | AH90: Janeiro / Julho | AI90: Junho | AJ90: CDI | AK90: 37074 | AL90: https://www.xpi.com.br/investimentos/fundos-de-investimento/lista/#/detalhes/74fe82e7-b5a6-4f3e-ba33-37d29aca3731 | AM90: 0.0068913019 | AN90: 0.038239132 | AO90: 0.12567048 | AP90: 0.10172723 | AQ90: 0.099481764 | AR90: 0.048586636 | AS90: 0.13844201 | AT90: 0.13481454 | AU90: - | AV90: - | AW90: 0.12147595 | AX90: 0.63168585 | AY90: 0.842228 | AZ90: 0.84755056 | BA90: 0.7628983 | BB90: 0.7497648 | BC90: 0.44681587 | BD90: 1.0610665 | BE90: 1.0895862 | BF90: - | BG90: - | BH90: 1.1517194 | BI90: -0.0040180796 | BJ90: -0.0071632197 | BK90: -0.022604426 | BL90: -0.027896121 | BM90: -0.029312852 | BN90: -0.060153092 | BO90: 0.0079676148 | BP90: 0.011084503 | BQ90: - | BR90: - | BS90: 0.014475594 | BT90: 0.012172464 | BU90: 0.038792578 | BV90: -1.6281226 | BW90: 0.16369937 | BX90: -0.004748659 | BY90: -0.071204201 | BZ90: 0.046796592 | CA90: 0.48885022 | CB90: -0.3801197 | CC90: 0.69596867 | CD90: 0.63092 | CE90: -0.041740013 | CF90: 0.6404769 | CG90: 20.609006 | CH90: 0.25 | CI90: 0.2 | CJ90: 0.00375 | CK90: - | CL90: 0.00375 | CM90: 48635706 | CN90: 51304464 | CO90: -8099951.4 | CP90: - | CQ90: - | CR90: - | CS90: - | CT90: - | CU90: - | CV90: BRQUESCTF006 | CW90: - | CX90: 25569.626
B91: 26323079000185 | C91: AZ Quest Multi Max FIC FIF Multimercado | D91: 13 | F91: «««« | G91: AZ Quest MZK Investimentos | H91: BNY Mellon Serviços Financeiros | I91: BNY Mellon Banco | J91: KPMG | K91: Geral | L91: Investidores em geral | M91: Multimercado | N91: Multimercados Macro | O91: Macro Alta Vol | P91: Longo Prazo - Alíquota regressiva de IR de 22,5% a 15,0% incidida sobre o lucro obtido no momento do resgate. | Q91: 1000 | R91: ABERTO | S91: - | T91: 500 | U91: 500 | V91: Fechamento | W91: D+0 | X91: D+29 (corridos) | Y91: D+1 (útil) | Z91: 30 | AA91: - | AB91: - | AC91: AZ QUEST MULTI MAX FIF CIC MULTIMERCADO | AD91: 0.02 | AE91: 0.02 | AF91: 0.025 | AG91: 0.2 | AH91: Janeiro / Julho | AI91: Junho | AJ91: CDI | AK91: 42790 | AL91: https://www.xpi.com.br/investimentos/fundos-de-investimento/lista/#/detalhes/cea12890-5ac4-49ff-9179-ae777285a8ee | AM91: 0.003703039 | AN91: 0.034747401 | AO91: 0.11634933 | AP91: 0.084884922 | AQ91: 0.082228574 | AR91: 0.0034774144 | AS91: 0.15729086 | AT91: 0.15776293 | AU91: - | AV91: - | AW91: 0.093043476 | AX91: 0.3394362 | AY91: 0.76532161 | AZ91: 0.78468659 | BA91: 0.63148891 | BB91: 0.60944949 | BC91: 0.031979245 | BD91: 1.2055305 | BE91: 1.2750577 | BF91: - | BG91: - | BH91: 1.0471095 | BI91: -0.0072063424 | BJ91: -0.010654951 | BK91: -0.031925576 | BL91: -0.043665798 | BM91: -0.04642971 | BN91: -0.10526231 | BO91: 0.02681647 | BP91: 0.034032898 | BQ91: - | BR91: - | BS91: 0.0038444266 | BT91: 0.024242868 | BU91: 0.073715859 | BV91: -1.1516047 | BW91: 0.075052982 | BX91: -0.010946041 | BY91: -0.11950729 | BZ91: 0.19232493 | CA91: 0.48863257 | CB91: -0.38034199 | CC91: 0.69565157 | CD91: 0.63076406 | CE91: -0.0426464 | CF91: 0.64061803 | CG91: 2.2523883 | CH91: 0.27 | CI91: 0.15 | CJ91: 0.0054 | CK91: - | CL91: 0.0054 | CM91: 47280277 | CN91: 54930201 | CO91: -39877800 | CP91: - | CQ91: - | CR91: - | CS91: - | CT91: - | CU91: - | CV91: BRAZF2CTF004 | CW91: - | CX91: 25569.626
B92: 59482549000102 | C92: AZ Quest Renda Mais Infra-Yield VI FIP-IE | D92: 60 | G92: AZ QUEST INFRA LTDA. | H92: XP Investimentos | I92: Oliveira Trust | J92: PriceWaterhouseCoopers | K92: Intranet | L92: Não definido | M92: Participações - Infraestrutura | N92: - | O92: Fundo Listado | P92: FIP IE | Q92: 100 | R92: FECHADO | S92: - | T92: 0.01 | U92: 0.01 | V92: Fechamento | W92: D+0 | X92: D+0 | Y92: D+0 | Z92: 0 | AA92: - | AB92: - | AC92: - | AD92: 0.0124 | AE92: - | AF92: 0.0124 | AG92: 0.2 | AH92: Janeiro / Janeiro | AI92: - | AJ92: CDI | AK92: 45783 | AL92: https://www.xpi.com.br/investimentos/fundos-de-investimento/lista/#/detalhes/7a3b4967-2518-49c5-abf2-39aca4140b6b | AM92: -0.0017854717 | AN92: 0.014578637 | AO92: - | AP92: - | AQ92: - | AR92: - | AS92: - | AT92: - | AU92: - | AV92: - | AW92: 0.028878033 | AX92: - | AY92: 0.32109872 | AZ92: - | BA92: - | BB92: - | BC92: - | BD92: - | BE92: - | BF92: - | BG92: - | BH92: 0.19478345 | BI92: -0.012694853 | BJ92: -0.030823715 | BK92: - | BL92: - | BM92: - | BN92: - | BO92: - | BP92: - | BQ92: - | BR92: - | BS92: -0.10396546 | BT92: - | BU92: 0.05307873 | BV92: - | BW92: -2.0443213 | BX92: - | BY92: -0.029760066 | BZ92: 0.023699958 | CA92: - | CB92: - | CC92: - | CD92: - | CE92: - | CF92: - | CG92: 102.85294 | CH92: 0.15 | CI92: 0.1 | CJ92: 0.00186 | CK92: - | CL92: 0.00186 | CM92: 3.1616027e+08 | CN92: 3.161608e+08 | CO92: -18904522 | CP92: - | CQ92: - | CR92: - | CS92: - | CT92: - | CU92: - | CV92: - | CW92: - | CX92: 25569.626
B93: 11392165000172 | C93: AZ Quest Small Mid Caps FIF CIC em Ações RL | D93: 28 | F93: ««« | G93: AZ Quest Investimentos | H93: Intrag DTVM | I93: Itaú Unibanco | J93: EY | K93: Geral | L93: Investidores em geral | M93: Ações | N93: Ações Livre | O93: Renda Variável Small/Mid Caps | P93: Renda Variável - Alíquota de IR de 15% incidida sobre o lucro obtido no momento do resgate. | Q93: 1000 | R93: ABERTO | S93: - | T93: 500 | U93: 500 | V93: Fechamento | W93: D+1 (útil) | X93: D+27 (corridos) | Y93: D+2 (útil) | Z93: 29 | AA93: - | AB93: - | AC93: AZ QUEST SMALL MID CAPS RESP LIMITADA FIF CIC AÇÕES | AD93: 0.02 | AE93: 0.02 | AF93: 0.024 | AG93: 0.2 | AH93: Junho / Dezembro | AI93: Maio / Novembro | AJ93: SMLL | AK93: 40177 | AL93: https://www.xpi.com.br/investimentos/fundos-de-investimento/lista/#/detalhes/2b91466c-9bd8-47fe-8649-3254e71d6839 | AM93: -0.02199797 | AN93: 0.048466634 | AO93: 0.22676371 | AP93: 0.15855991 | AQ93: 0.17053446 | AR93: -0.035883421 | AS93: 0.15290819 | AT93: -0.086941615 | AU93: - | AV93: - | AW93: 0.14212726 | AX93: - | AY93: 1.0674917 | AZ93: 1.5293465 | BA93: 1.2212669 | BB93: 1.3755319 | BC93: - | BD93: 1.1719402 | BE93: - | BF93: - | BG93: - | BH93: 2.1395786 | BI93: -0.032907352 | BJ93: 0.0030642819 | BK93: 0.078488799 | BL93: 0.02542642 | BM93: 0.04142198 | BN93: -0.14462315 | BO93: 0.022433796 | BP93: -0.21067165 | BQ93: - | BR93: - | BS93: 0.070984253 | BT93: 0.22061143 | BU93: 0.1978255 | BV93: 0.41023931 | BW93: 0.29834091 | BX93: -0.12177008 | BY93: -0.49660944 | BZ93: 0.72072714 | CA93: 0.90392187 | CB93: -0.44576589 | CC93: 0.66463381 | CD93: 0.53495476 | CE93: 0.079058704 | CF93: 0.76428771 | CG93: 8.6943022 | CH93: 0.2 | CI93: 0.2 | CJ93: 0.004 | CK93: 0.0032970169 | CL93: 0.0072970169 | CM93: 9.7558039e+08 | CN93: 9.5039961e+08 | CO93: 60758418 | CP93: - | CQ93: - | CR93: - | CS93: - | CT93: - | CU93: - | CV93: BRQUE5CTF005 | CW93: - | CX93: 25569.626
B94: 36352498000107 | C94: AZ Quest Supra FIC FIF Multimercado CP | D94: 13 | G94: AZ Quest MZK Investimentos | H94: BNY Mellon Serviços Financeiros | I94: BNY Mellon Banco | J94: Deloitte Touche Tohmatsu | K94: Geral | L94: Investidores qualificados | M94: Multimercado | N94: Multimercados Livre | O94: Crédito Híbrido | P94: Longo Prazo - Alíquota regressiva de IR de 22,5% a 15,0% incidida sobre o lucro obtido no momento do resgate._x000D_ | Q94: 1000 | R94: ABERTO | S94: - | T94: 500 | U94: 500 | V94: Fechamento | W94: D+0 | X94: D+59 (corridos) | Y94: D+1 (útil) | Z94: 60 | AA94: - | AB94: - | AC94: AZ QUEST SUPRA FIF CIC MULTIMERCADO CRÉDITO PRIVADO | AD94: 0.012 | AE94: 0.012 | AF94: 0.02 | AG94: 0.2 | AH94: - | AI94: - | AJ94: CDI | AK94: 43997 | AL94: https://www.xpi.com.br/investimentos/fundos-de-investimento/lista/#/detalhes/00e3d2e1-6eac-4e4b-ab9e-05e5536cfb72 | AM94: 0.013213549 | AN94: 0.022917836 | AO94: 0.13564282 | AP94: 0.13424959 | AQ94: 0.16006272 | AR94: 0.13691891 | AS94: 0.13828506 | AT94: 0.13843695 | AU94: - | AV94: - | AW94: 0.12883938 | AX94: 1.2112097 | AY94: 0.504772 | AZ94: 0.9148063 | BA94: 1.0223774 | BB94: 1.2783493 | BC94: 1.2591434 | BD94: 1.0598636 | BE94: 1.1188629 | BF94: - | BG94: - | BH94: 1.3314703 | BI94: 0.0023041677 | BJ94: -0.022484516 | BK94: -0.012632088 | BL94: 0.0025973442 | BM94: 0.030973978 | BN94: 0.028179179 | BO94: 0.0078106714 | BP94: 0.014706911 | BQ94: - | BR94: - | BS94: 0.029244777 | BT94: 0.014087172 | BU94: 0.012767643 | BV94: -0.77862496 | BW94: 1.8159915 | BX94: -0.017689284 | BY94: -0.028642948 | BZ94: 0.012047126 | CA94: 0.18124076 | CB94: -0.023562108 | CC94: 0.35884917 | CD94: 0.19155563 | CE94: 0.13937359 | CF94: 0.37061769 | CG94: 2.0336397 | CH94: 0.25 | CI94: 0.15 | CJ94: 0.003 | CK94: - | CL94: 0.003 | CM94: 6.394473e+08 | CN94: 5.9181363e+08 | CO94: 1.1381431e+08 | CP94: - | CQ94: - | CR94: - | CS94: - | CT94: - | CU94: - | CV94: BR04L5CTF008 | CW94: - | CX94: 25569.626
B95: 22681798000117 | C95: AZ Quest Termo FIF RF LP | D95: 6 | F95: ««« | G95: AZ Quest Investimentos | H95: BTG Pactual Serviços Financeiros | I95: Banco BTG Pactual | J95: KPMG | K95: Geral | L95: Investidores em geral | M95: Renda Fixa | N95: Renda Fixa Duração Média Grau de Investimento | O95: Renda Fixa Ativo | P95: Longo Prazo - Alíquota regressiva de IR de 22,5% a 15,0% incidida sobre o lucro obtido no momento do resgate. | Q95: 500 | R95: ABERTO | S95: - | T95: 300 | U95: 300 | V95: Fechamento | W95: D+0 | X95: D+6 (corridos) | Y95: D+1 (útil) | Z95: 7 | AA95: - | AB95: - | AC95: - | AD95: 0.004 | AE95: - | AF95: - | AG95: 0.1 | AH95: Janeiro / Julho | AI95: Junho | AJ95: CDI | AK95: 42219 | AL95: https://www.xpi.com.br/investimentos/fundos-de-investimento/lista/#/detalhes/4d7cfe70-61f9-48dd-8e27-9c44beedd4bf | AM95: 0.011201237 | AN95: 0.045059579 | AO95: 0.14535549 | AP95: 0.13060614 | AQ95: 0.12764475 | AR95: 0.10908416 | AS95: 0.12834021 | AT95: 0.12690222 | AU95: - | AV95: - | AW95: 0.10019685 | AX95: 1.0267527 | AY95: 0.99245032 | AZ95: 0.98031079 | BA95: 0.9929328 | BB95: 0.98844925 | BC95: 1.0031675 | BD95: 0.98364286 | BE95: 1.025638 | BF95: - | BG95: - | BH95: 1.0476006 | BI95: 0.00029185593 | BJ95: -0.00034277334 | BK95: -0.0029194165 | BL95: -0.00082152888 | BM95: -0.0013210293 | BN95: 0.00034442906 | BO95: -0.0021341875 | BP95: 0.0031721862 | BQ95: - | BR95: - | BS95: 0.0041552858 | BT95: 0.00082661259 | BU95: 0.0027340618 | BV95: -3.0809131 | BW95: 1.009692 | BX95: - | BY95: -0.0020918341 | BZ95: 0.00012355822 | CA95: -0.025505495 | CB95: -0.064639305 | CC95: -0.063758005 | CD95: -0.089594074 | CE95: -0.10773347 | CF95: -0.0097558347 | CG95: 2.7765331 | CH95: 0.27 | CI95: 0.14 | CJ95: 0.00108 | CK95: - | CL95: 0.00108 | CM95: 2.1499288e+08 | CN95: 2.2585587e+08 | CO95: -51363500 | CP95: - | CQ95: - | CR95: - | CS95: - | CT95: - | CU95: - | CV95: BRAZL4CTF002 | CW95: - | CX95: 25569.626
B96: 13974750000106 | C96: AZ Quest Top Long Biased FIC FIF Ações | D96: 26 | F96: ««« | G96: AZ Quest Investimentos | H96: BTG Pactual Serviços Financeiros | I96: Banco BTG Pactual | J96: EY | K96: Geral | L96: Investidores em geral | M96: Ações | N96: Ações Livre | O96: Renda Variável Long Biased | P96: Renda Variável - Alíquota de IR de 15% incidida sobre o lucro obtido no momento do resgate. | Q96: 1000 | R96: ABERTO | S96: - | T96: 500 | U96: 500 | V96: Fechamento | W96: D+1 (útil) | X96: D+30 (corridos) | Y96: D+2 (útil) | Z96: 32 | AA96: - | AB96: - | AC96: AZ QUEST TOP LONG BIASED FIF CIC AÇÕES | AD96: 0.0195 | AE96: 0.0195 | AF96: 0.025 | AG96: 0.2 | AH96: Janeiro / Julho | AI96: Junho | AJ96: IBX | AK96: 40834 | AL96: https://www.xpi.com.br/investimentos/fundos-de-investimento/lista/#/detalhes/e9f9c7c8-d515-4f8c-af29-ecc4fdf34e27 | AM96: -0.0053596381 | AN96: 0.089991196 | AO96: 0.30742612 | AP96: 0.21003293 | AQ96: 0.21318546 | AR96: 0.10393038 | AS96: 0.26695096 | AT96: -0.1220458 | AU96: - | AV96: - | AW96: 0.14350483 | AX96: - | AY96: 1.9820822 | AZ96: 2.0733523 | BA96: 1.6563008 | BB96: 1.7896446 | BC96: 0.95577193 | BD96: 2.0460027 | BE96: - | BF96: - | BG96: - | BH96: 2.1075353 | BI96: -0.01626902 | BJ96: 0.044588844 | BK96: 0.15915121 | BL96: 0.073858594 | BM96: 0.084051437 | BN96: -0.0048093479 | BO96: 0.13647657 | BP96: -0.24577584 | BQ96: - | BR96: - | BS96: 0.070605876 | BT96: 0.21534702 | BU96: 0.20132825 | BV96: 0.71107948 | BW96: 0.30714124 | BX96: -0.11610906 | BY96: -0.49066535 | BZ96: 0.71351236 | CA96: 0.92061639 | CB96: -0.47305048 | CC96: 0.66362209 | CD96: 0.54045872 | CE96: 0.084384294 | CF96: 0.7706078 | CG96: 6.9710068 | CH96: 0.24 | CI96: 0.15 | CJ96: 0.00468 | CK96: - | CL96: 0.00468 | CM96: 1.6651031e+08 | CN96: 1.6819243e+08 | CO96: -11692045 | CP96: - | CQ96: - | CR96: - | CS96: - | CT96: - | CU96: - | CV96: BRQNY1CTF017 | CW96: - | CX96: 25569.626
B97: 19782311000188 | C97: AZ Quest Valore FIRF CP | D97: 10 | F97: «« | G97: AZ Quest MZK Investimentos | H97: BNY Mellon Serviços Financeiros | I97: BNY Mellon Banco | J97: KPMG | K97: Geral | L97: Investidores em geral | M97: Renda Fixa | N97: Renda Fixa Duração Livre Grau de Investimento | O97: Crédito Liquidez | P97: Longo Prazo - Alíquota regressiva de IR de 22,5% a 15,0% incidida sobre o lucro obtido no momento do resgate. | Q97: 500 | R97: ABERTO | S97: - | T97: 500 | U97: 500 | V97: Fechamento | W97: D+0 | X97: D+4 (corridos) | Y97: D+1 (útil) | Z97: 5 | AA97: - | AB97: - | AC97: - | AD97: 0.01 | AE97: - | AF97: 0.015 | AG97: - | AH97: - | AI97: - | AJ97: CDI | AK97: 41757 | AL97: https://www.xpi.com.br/investimentos/fundos-de-investimento/lista/#/detalhes/113747a8-403a-41b7-8341-e310a44320c9 | AM97: 0.0074821505 | AN97: 0.025279549 | AO97: 0.12813148 | AP97: 0.12267265 | AQ97: 0.13863216 | AR97: 0.1224946 | AS97: 0.1323878 | AT97: 0.13280902 | AU97: - | AV97: - | AW97: 0.10046799 | AX97: 0.68584553 | AY97: 0.5567894 | AZ97: 0.86414813 | BA97: 0.92914576 | BB97: 1.084867 | BC97: 1.1264936 | BD97: 1.014665 | BE97: 1.0733774 | BF97: - | BG97: - | BH97: 1.0184197 | BI97: -0.003427231 | BJ97: -0.020122804 | BK97: -0.020143423 | BL97: -0.0082636676 | BM97: 0.0096161052 | BN97: 0.013754876 | BO97: 0.0019134071 | BP97: 0.0090789863 | BQ97: - | BR97: - | BS97: 0.0016539544 | BT97: 0.0073113064 | BU97: 0.0098980881 | BV97: -2.4182384 | BW97: 0.10951078 | BX97: -0.0079648572 | BY97: -0.077282623 | BZ97: 0.0027133225 | CA97: 0.25776353 | CB97: -0.13248621 | CC97: 0.46911921 | CD97: 0.24935179 | CE97: 0.11214374 | CF97: 0.4598066 | CG97: 3.1437214 | CH97: 0.3 | CI97: - | CJ97: 0.003 | CK97: - | CL97: 0.003 | CM97: 3.5917926e+09 | CN97: 4.2115061e+09 | CO97: -1.0737419e+09 | CP97: - | CQ97: - | CR97: - | CS97: - | CT97: - | CU97: - | CV97: BRAZL6CTF007 | CW97: - | CX97: 25569.626
B98: 16599968000116 | C98: AZ Quest Yield RF Ativo FIF CIC RF LP RL | D98: 10 | F98: ««« | G98: AZ Quest MZK Investimentos | H98: Intrag DTVM | I98: Itaú Unibanco | J98: Deloitte Touche Tohmatsu | K98: Geral | L98: Investidores em geral | M98: Renda Fixa | N98: Renda Fixa Duração Livre Grau de Investimento | O98: Renda Fixa Ativo | P98: Longo Prazo - Alíquota regressiva de IR de 22,5% a 15,0% incidida sobre o lucro obtido no momento do resgate. | Q98: 1000 | R98: ABERTO | S98: - | T98: 1000 | U98: 1000 | V98: Fechamento | W98: D+0 | X98: D+0 | Y98: D+1 (útil) | Z98: 1 | AA98: - | AB98: - | AC98: AZ QUEST YIELD RESP LIMITADA FIF CIC RENDA FIXA LP | AD98: 0.01 | AE98: 0.01 | AF98: 0.015 | AG98: 0.2 | AH98: Junho / Dezembro | AI98: Maio / Novembro | AJ98: CDI | AK98: 41172 | AL98: https://www.xpi.com.br/investimentos/fundos-de-investimento/lista/#/detalhes/818469c7-c5ec-41bc-b41e-a2734f710b0b | AM98: 0.01112815 | AN98: 0.047933561 | AO98: 0.15179657 | AP98: 0.12165284 | AQ98: 0.12016206 | AR98: 0.061715575 | AS98: 0.14834568 | AT98: 0.082541037 | AU98: - | AV98: - | AW98: 0.092724517 | AX98: 1.0200532 | AY98: 1.0557506 | AZ98: 1.0237509 | BA98: 0.92097888 | BB98: 0.92385262 | BC98: 0.56755315 | BD98: 1.1369716 | BE98: 0.6671059 | BF98: - | BG98: - | BH98: 0.92094496 | BI98: 0.00021876818 | BJ98: 0.002531209 | BK98: 0.0035216587 | BL98: -0.009220076 | BM98: -0.0087642693 | BN98: -0.047024153 | BO98: 0.017871288 | BP98: -0.041188999 | BQ98: - | BR98: - | BS98: -0.0072314898 | BT98: 0.0062799284 | BU98: 0.021112372 | BV98: 0.49101548 | BW98: -0.1932989 | BX98: -0.00063254314 | BY98: -0.044532666 | BZ98: 0.027631144 | CA98: 0.40775453 | CB98: -0.23314675 | CC98: 0.64068581 | CD98: 0.57665538 | CE98: 0.055946231 | CF98: 0.48070062 | CG98: 3.3256837 | CH98: 0.25 | CI98: 0.2 | CJ98: 0.0025 | CK98: 0.0001226765 | CL98: 0.0026226765 | CM98: 1.3756007e+08 | CN98: 57649457 | CO98: 1.0127446e+08 | CP98: - | CQ98: - | CR98: - | CS98: - | CT98: - | CU98: - | CV98: BRQTY1CTF003 | CW98: - | CX98: 25569.626
B99: 61258419000132 | C99: AZ-AXS Energia FIP-IE RL - Subclasse Sênior A1 | D99: 40 | G99: AZ QUEST INFRA LTDA. | H99: Banco Daycoval | I99: Banco Daycoval | J99: PriceWaterhouseCoopers | K99: Intranet | L99: Não definido | M99: Participações - Infraestrutura | N99: - | O99: Fundo Listado | P99: FIP IE | Q99: 100 | R99: FECHADO | S99: - | T99: 1000 | U99: 1000 | V99: Fechamento | W99: D+0 | X99: D+0 | Y99: D+0 | Z99: 0 | AA99: - | AB99: - | AC99: - | AD99: 0.009 | AE99: - | AF99: - | AG99: 0.2 | AH99: Dezembro / Junho | AI99: Novembro / Maio | AJ99: - | AK99: 45874 | AL99: https://www.xpi.com.br/investimentos/fundos-de-investimento/lista/#/detalhes/7a098c9d-ebbd-49cc-9fcb-b80f04fb8563 | AM99: 0.010844776 | AN99: 0.032664973 | AO99: - | AP99: - | AQ99: - | AR99: - | AS99: - | AT99: - | AU99: - | AV99: - | AW99: 0.083299668 | AX99: 0.994078 | AY99: 0.71945553 | AZ99: - | BA99: - | BB99: - | BC99: - | BD99: - | BE99: - | BF99: - | BG99: - | BH99: 0.56636604 | BI99: -6.4605382e-05 | BJ99: -0.012737379 | BK99: - | BL99: - | BM99: - | BN99: - | BO99: - | BP99: - | BQ99: - | BR99: - | BS99: -0.055600233 | BT99: - | BU99: 0.024540423 | BV99: - | BW99: -2.3733476 | BX99: - | BY99: - | BZ99: 0.014899255 | CA99: - | CB99: - | CC99: - | CD99: - | CE99: - | CF99: - | CG99: 106.33263 | CH99: 0.15 | CI99: - | CJ99: 0.00135 | CK99: - | CL99: 0.00135 | CM99: 6.3799579e+08 | CN99: 6.200514e+08 | CO99: -29377200 | CP99: - | CQ99: - | CR99: - | CS99: - | CT99: - | CU99: - | CV99: - | CW99: - | CX99: 25569.626
B100: 49998473000119 | C100: Azimut Allocation Balanced FIF CIC Multimercado RL | D100: 26 | G100: AZ Quest Investimentos | H100: Intrag DTVM | I100: Itaú Unibanco | J100: Deloitte Touche Tohmatsu | K100: Geral | L100: Investidores qualificados | M100: Multimercado | N100: Multimercados Investimento no Exterior | O100: Internacional Multimercado Hedgeado | P100: Longo Prazo | Q100: 1000 | R100: ABERTO | S100: - | T100: 1000 | U100: 1000 | V100: Fechamento | W100: D+1 (útil) | X100: D+2 (útil) | Y100: D+3 (útil) | Z100: 5 | AA100: - | AB100: - | AC100: AZ QUEST AZIMUT ALLOCATION BALANCED RESP LIMITADA FIF CIC MULTIMERCADO | AD100: 0.008 | AE100: 0.608 | AF100: 0.014 | AG100: - | AH100: - | AI100: - | AJ100: Ibovespa | AK100: 45016 | AL100: https://www.xpi.com.br/investimentos/fundos-de-investimento/lista/#/detalhes/e0b4fedc-4c21-4782-b21e-cd9ee41658d3 | AM100: 0.040632838 | AN100: 0.067947669 | AO100: 0.19094915 | AP100: 0.1543989 | AQ100: 0.12015911 | AR100: 0.08604765 | AS100: - | AT100: - | AU100: - | AV100: - | AW100: 0.13810498 | AX100: 3.7245776 | AY100: 1.4965672 | AZ100: 1.2878049 | BA100: 1.1869254 | BB100: 0.92382734 | BC100: 0.7913175 | BD100: - | BE100: - | BF100: - | BG100: - | BH100: 1.0790421 | BI100: 0.029723456 | BJ100: 0.022545317 | BK100: 0.042674246 | BL100: 0.02151685 | BM100: -0.0087672013 | BN100: -0.022692079 | BO100: - | BP100: - | BQ100: - | BR100: - | BS100: 0.0089686003 | BT100: 0.05254336 | BU100: 0.06411362 | BV100: 0.72109272 | BW100: 0.15546799 | BX100: -0.042488678 | BY100: -0.042488678 | BZ100: 0.085691714 | CA100: 0.27961209 | CB100: -0.22948141 | CC100: 0.31827251 | CD100: 0.24086785 | CE100: -0.13662252 | CF100: 0.37499135 | CG100: 1.4863261 | CH100: 0.6 | CI100: - | CJ100: 0.0048 | CK100: - | CL100: 0.0048 | CM100: 23888422 | CN100: 22599990 | CO100: 358276.37 | CP100: - | CQ100: - | CR100: - | CS100: - | CT100: - | CU100: - | CV100: BR0F58CTF004 | CW100: - | CX100: 25569.626
...

Sheet Fundos XP Offshore Digital
A10: nan | B10: Fund | C10: ISIN | D10: Management Company | E10: XP Category | F10: Global Broad Category Group | G10: Region | H10: Group Category | I10: Base Currency | J10: Morningstar Rating Overall | K10: Primary Prospectus Benchmark | L10: Start Date | M10: Minimum Initial Investment | N10: Minimum Additional Purchase | O10: Redemption Period (days) | P10: Ongoing Charges | Q10: Management Fee | R10: Performance Fee | S10: ROA | T10: Domicile | U10: Fund Legal Structure | V10: MTD | W10: YTD | X10: 2024 | Y10: 2023 | Z10: 2022
B11: AB American Growth (A) | C11: LU0079474960 | D11: AllianceBernstein L.P. | E11: Internacional Ações Não Hedgeado | F11: Equity | G11: United States of America | H11: US Equity Large Cap Growth | I11: US Dollar | J11: ★★★★ | K11: Russell 1000 Growth TR EUR | L11: 35435 | M11: 2000 | N11: 750 | O11: T + 4 | P11: 0.0171 | Q11: 0.015 | R11: 0 | S11: 0.00375 | T11: Luxembourg | U11: SICAV | V11: 0.1192656 | W11: 0.0109078 | X11: 0.2433 | Y11: 0.335 | Z11: -0.2939
B12: AB American Income (A) | C12: LU0044957727 | D12: AllianceBernstein L.P. | E12: Internacional Renda Fixa Não Hedgeado | F12: Fixed Income | G12: United States of America | H12: US Fixed Income | I12: US Dollar | J12: ★★★ | K12: Bloomberg US Agg Bond TR USD | L12: 35435 | M12: 2000 | N12: 750 | O12: T + 4 | P12: 0.013 | Q12: 0.011 | R12: 0 | S12: 0.0025 | T12: Luxembourg | U12: FCP | V12: 0.0116083 | W12: 0.0002243 | X12: 0.029 | Y12: 0.0829 | Z12: -0.1314
B13: AB International Health Care (A) | C13: LU0058720904 | D13: AllianceBernstein L.P. | E13: Internacional Ações Não Hedgeado | F13: Equity | G13: Global | H13: Healthcare Sector Equity | I13: US Dollar | J13: ★★★★★ | K13: MSCI World/Health Care NR USD | L13: 34884 | M13: 2000 | N13: 750 | O13: T + 4 | P13: 0.0192 | Q13: 0.0176 | R13: 0 | S13: 0.00375 | T13: Luxembourg | U13: SICAV | V13: -0.0051328 | W13: -0.0486608 | X13: -0.0253 | Y13: 0.0937 | Z13: -0.1037
B14: AB Low Volatility Equity (A) | C14: LU0861579265 | D14: AllianceBernstein L.P. | E14: Internacional Ações Não Hedgeado | F14: Equity | G14: Global | H14: Global Equity Large Cap | I14: US Dollar | J14: ★★★★ | K14: MSCI World NR USD | L14: 41224 | M14: 2000 | N14: 750 | O14: T + 4 | P14: 0.0166 | Q14: 0.015 | R14: 0 | S14: 0.00375 | T14: Luxembourg | U14: SICAV | V14: 0.0712969 | W14: 0.0053836 | X14: 0.1573 | Y14: 0.1839 | Z14: -0.1221
B15: AB Select US Equity (A) | C15: LU0683600562 | D15: AllianceBernstein L.P. | E15: Internacional Ações Não Hedgeado | F15: Equity | G15: United States of America | H15: US Equity Large Cap Blend | I15: US Dollar | J15: ★★★★ | K15: S&P 500 TR USD | L15: 40843 | M15: 2000 | N15: 750 | O15: T + 4 | P15: 0.0196 | Q15: 0.018 | R15: 0 | S15: 0.00375 | T15: Luxembourg | U15: SICAV | V15: 0.0879491 | W15: 0.0423091 | X15: 0.2451 | Y15: 0.1771 | Z15: -0.1485
B16: AB Short Duration High Yield (A2) | C16: LU0654559516 | D16: AllianceBernstein L.P. | E16: Internacional Renda Fixa Não Hedgeado | F16: Fixed Income | G16: Global | H16: Global Fixed Income | I16: US Dollar | J16: ★★★ | K16: Bloomberg Global HY Corp TR USD | L16: 40752 | M16: 2000 | N16: 750 | O16: T + 4 | P16: 0.0128 | Q16: 0.011 | R16: 0 | S16: 0.0025 | T16: Luxembourg | U16: SICAV | V16: 0.0157329 | W16: 0.0122371 | X16: 0.067 | Y16: 0.1099 | Z16: -0.0836
B17: AB Sustainable US Thematic (A) | C17: LU0124676726 | D17: AllianceBernstein L.P. | E17: Internacional Ações Não Hedgeado | F17: Equity | G17: United States of America | H17: US Equity Large Cap Growth | I17: US Dollar | J17: ★★ | K17: S&P 500 TR USD | L17: 37004 | M17: 2000 | N17: 750 | O17: T + 4 | P17: 0.0168 | Q17: 0.015 | R17: 0 | S17: 0.00375 | T17: Luxembourg | U17: SICAV | V17: 0.0975772 | W17: 0.0087845 | X17: 0.0958 | Y17: 0.1937 | Z17: -0.2404
B18: Alma Electron Global Fund | C18: LU2164518057 | D18: Electron Capital Partners, LLC | E18: Internacional Ações Não Hedgeado | F18: Equity | G18: Global | H18: Long/Short Equity | I18: US Dollar | K18: MSCI World/Utilities NR USD | L18: 44026 | M18: 5000 | N18: 1000 | O18: T + 4 | P18: 0.0229 | Q18: 0.0197 | R18: 0.15 | S18: 0.00125 | T18: Luxembourg | U18: SICAV | V18: 0.0533141 | W18: 0.0943114 | X18: 0.2235 | Y18: -0.0623 | Z18: 0.1167
B19: BlackRock Continental Europe Flexible (A2) | C19: LU1196525536 | D19: BlackRock Inc | E19: Internacional Ações Não Hedgeado | F19: Equity | G19: Europe ex UK | H19: Europe Equity Large Cap | I19: US Dollar | K19: FTSE World Eur Ex UK TR EUR | L19: 42066 | M19: 1000 | N19: 1000 | O19: T + 4 | P19: 0.018087 | Q19: 0.015 | R19: 0 | S19: 0.003 | T19: Luxembourg | U19: SICAV | V19: 0.0609358 | W19: 0.0124611 | X19: 0.0931 | Y19: 0.2185 | Z19: -0.2187
B20: BlackRock Emerging Markets Corporate Bonds (A2) | C20: LU0843229542 | D20: BlackRock Inc | E20: Internacional Renda Fixa Não Hedgeado | F20: Fixed Income | G20: Global Emerging Mkts | H20: Emerging Markets Fixed Income | I20: US Dollar | J20: ★★★ | K20: JPM CEMBI Broad Diversified TR USD | L20: 41322 | M20: 1000 | N20: 1000 | O20: T + 4 | P20: 0.016235 | Q20: 0.014 | R20: 0 | S20: 0.003 | T20: Luxembourg | U20: SICAV | V20: 0.0210169 | W20: 0.0033311 | X20: 0.0733 | Y20: 0.0623 | Z20: -0.1304
B21: BlackRock ESG Multi-Asset (A2) | C21: LU0494093205 | D21: BlackRock Inc | E21: Internacional Multimercado Não Hedgeado | F21: Allocation | G21: Global | H21: Moderate Allocation | I21: US Dollar | J21: ★★★ | K21: MSCI World NR EUR [50.00%]; FTSE WGBI Hdg EUR [50.00%] | L21: 40283 | M21: 1000 | N21: 1000 | O21: T + 4 | P21: 0.015071 | Q21: 0.012 | R21: 0 | S21: 0.0024 | T21: Luxembourg | U21: SICAV | V21: 0.0557954 | W21: 0.0411004 | X21: 0.0838 | Y21: 0.0754 | Z21: -0.1241
B22: BlackRock European (A2) | C22: LU0526926950 | D22: BlackRock Inc | E22: Internacional Ações Não Hedgeado | F22: Equity | G22: Europe | H22: Europe Equity Large Cap | I22: US Dollar | K22: MSCI Europe NR EUR | L22: 40457 | M22: 1000 | N22: 1000 | O22: T + 4 | P22: 0.018146 | Q22: 0.015 | R22: 0 | S22: 0.00375 | T22: Luxembourg | U22: SICAV | V22: 0.059869 | W22: 0.0077083 | X22: 0.085 | Y22: 0.2048 | Z22: -0.2227
B23: BlackRock Fixed Income Global Opportunities (A2) | C23: LU0278466700 | D23: BlackRock Inc | E23: Internacional Renda Fixa Não Hedgeado | F23: Fixed Income | G23: Global | H23: Global Fixed Income | I23: US Dollar | J23: ★★★ | K23: Not Benchmarked | L23: 39112 | M23: 1000 | N23: 750 | O23: T + 4 | P23: 0.011979 | Q23: 0.01 | R23: 0 | S23: 0.002 | T23: Luxembourg | U23: SICAV | V23: 0.0097421 | W23: 0.0017055 | X23: 0.0442 | Y23: 0.0663 | Z23: -0.0651
B24: BlackRock Global Allocation (A2) | C24: LU0072462426 | D24: BlackRock Inc | E24: Internacional Multimercado Não Hedgeado | F24: Allocation | G24: Global | H24: Moderate Allocation | I24: US Dollar | J24: ★★★★ | K24: FTSE World Ex US TR USD [24.00%]; FTSE WGBI NonUSD USD [16.00%]; ICE BofA Current 5-Y US Trsy TR USD [24.00%]; S&P 500 TR USD [36.00%] | L24: 35432 | M24: 1000 | N24: 750 | O24: T + 4 | P24: 0.017646 | Q24: 0.015 | R24: 0 | S24: 0.003 | T24: Luxembourg | U24: SICAV | V24: 0.0648045 | W24: 0.0235206 | X24: 0.0882 | Y24: 0.1252 | Z24: -0.1633
B25: BlackRock Global Long-Horizon Equity (A2) | C25: LU0011850046 | D25: BlackRock Inc | E25: Internacional Ações Não Hedgeado | F25: Equity | G25: Global | H25: Global Equity Large Cap | I25: US Dollar | J25: ★★★ | K25: MSCI ACWI NR USD | L25: 35123 | M25: 1000 | N25: 750 | O25: T + 4 | P25: 0.018067 | Q25: 0.015 | R25: 0 | S25: 0 | T25: Luxembourg | U25: SICAV | V25: 0.0766572 | W25: -0.0275482 | X25: 0.1145 | Y25: 0.133 | Z25: -0.1888
B26: BlackRock Global Multi-Asset Income (A2) | C26: LU0784385840 | D26: BlackRock Inc | E26: Internacional Multimercado Não Hedgeado | F26: Allocation | G26: Global | H26: Moderate Allocation | I26: US Dollar | J26: ★★★ | K26: Bloomberg Global Aggregate TR Hdg USD [50.00%]; MSCI World NR USD [50.00%] | L26: 41087 | M26: 1000 | N26: 1000 | O26: T + 4 | P26: 0.017818 | Q26: 0.015 | R26: 0 | S26: 0.003 | T26: Luxembourg | U26: SICAV | V26: 0.0321489 | W26: 0.018931 | X26: 0.0622 | Y26: 0.0977 | Z26: -0.1311
B27: BlackRock Global Sustainable Energy (A2) | C27: LU0124384867 | D27: BlackRock Inc | E27: Internacional Ações Não Hedgeado | F27: Equity | G27: Global | H27: Energy Sector Equity | I27: US Dollar | J27: ★★★★★ | K27: MSCI ACWI NR USD | L27: 36986 | M27: 1000 | N27: 750 | O27: T + 4 | P27: 0.01965 | Q27: 0.0165 | R27: 0 | S27: 0.0033 | T27: Luxembourg | U27: SICAV | V27: 0.1126634 | W27: 0.1881617 | X27: -0.0904 | Y27: 0.1276 | Z27: -0.1832
B28: BlackRock Global US Flexible Equity (A2) | C28: LU0154236417 | D28: BlackRock Inc | E28: Internacional Ações Não Hedgeado | F28: Equity | G28: United States of America | H28: US Equity Large Cap Blend | I28: US Dollar | J28: ★★ | K28: Russell 1000 TR USD | L28: 37559 | M28: 1000 | N28: 1000 | O28: T + 4 | P28: 0.018032 | Q28: 0.015 | R28: 0 | S28: 0.003 | T28: Luxembourg | U28: SICAV | V28: 0.161406 | W28: 0.0975031 | X28: 0.1521 | Y28: 0.2246 | Z28: -0.1528
B29: BlackRock Global World Healthscience (A2) | C29: LU0122379950 | D29: BlackRock Inc | E29: Internacional Ações Não Hedgeado | F29: Equity | G29: Global | H29: Healthcare Sector Equity | I29: US Dollar | J29: ★★★★ | K29: MSCI World/Health Care NR USD | L29: 36986 | M29: 1000 | N29: 1000 | O29: T + 4 | P29: 0.018056 | Q29: 0.015 | R29: 0 | S29: 0.003 | T29: Luxembourg | U29: SICAV | V29: -0.013219 | W29: -0.0645247 | X29: 0.0194 | Y29: 0.0218 | Z29: -0.0521
B30: BlackRock Global World Technology (A2) | C30: LU0056508442 | D30: BlackRock Inc | E30: Internacional Ações Não Hedgeado | F30: Equity | G30: Global | H30: Technology Sector Equity | I30: US Dollar | J30: ★★★★ | K30: MSCI ACWI Info Tech 10/40 (2013) NR USD | L30: 34760 | M30: 1000 | N30: 750 | O30: T + 4 | P30: 0.018025 | Q30: 0.015 | R30: 0 | S30: 0.003 | T30: Luxembourg | U30: SICAV | V30: 0.2685412 | W30: 0.1535994 | X30: 0.325 | Y30: 0.4978 | Z30: -0.4306
B31: BlackRock Short Duration Bonds (A2) | C31: LU0154237225 | D31: BlackRock Inc | E31: Internacional Renda Fixa Não Hedgeado | F31: Fixed Income | G31: United States of America | H31: US Fixed Income | I31: US Dollar | J31: ★★★ | K31: ICE BofA 1-3Y US Corp&Govt TR USD | L31: 37559 | M31: 1000 | N31: 750 | O31: T + 4 | P31: 0.008789 | Q31: 0.0075 | R31: 0 | S31: 0.0015 | T31: Luxembourg | U31: SICAV | V31: 0.0045161 | W31: 0.0038685 | X31: 0.0447 | Y31: 0.0492 | Z31: -0.0496
B32: BlackRock Strategic Funds Global Event Driven (A2) | C32: LU1251620883 | D32: BlackRock Inc | E32: Internacional Multimercado Não Hedgeado | F32: Alternative | G32: Global | H32: Market Neutral | I32: US Dollar | K32: ICE BofA US 3M Trsy Bill TR EUR | L32: 42220 | M32: 5000 | N32: 750 | O32: T + 4 | P32: 0.018559 | Q32: 0.015 | R32: 0 | S32: 0.00275 | T32: Luxembourg | U32: SICAV | V32: 0.0130181 | W32: 0.0170034 | X32: 0.0087 | Y32: 0.0682 | Z32: -0.0278
B33: BlackRock US Dollar Reserve (A2) | C33: LU0006061419 | D33: BlackRock Inc | E33: Internacional Renda Fixa Não Hedgeado | F33: Money Market | G33: United States of America | H33: US Money Market | I33: US Dollar | K33: Secured Overnight Financing Rate(SOFR) | L33: 34302 | M33: 1000 | N33: 1000 | O33: T + 4 | P33: 0.005417 | Q33: 0.0045 | R33: 0 | S33: 0.001125 | T33: Luxembourg | U33: SICAV | V33: 0.0027509 | W33: 0.0106704 | X33: 0.049 | Y33: 0.0481 | Z33: 0.0135
B34: Franklin Income (A) | C34: LU1162221912 | D34: Franklin Templeton Invts | E34: Internacional Multimercado Não Hedgeado | F34: Allocation | G34: Global | H34: Moderate Allocation | I34: US Dollar | J34: ★★★ | K34: MSCI USA High Dividend Yield NR USD [50.00%]; Bloomberg High Yield Very Liquid TR USD [25.00%]; Bloomberg US Agg Bond TR USD [25.00%] | L34: 42012 | M34: 1000 | N34: 1000 | O34: T + 4 | P34: 0.0166 | Q34: 0.0135 | R34: 0 | S34: 0.0025 | T34: Luxembourg | U34: SICAV | V34: 0 | W34: 0.0515595 | X34: 0.0606 | Y34: 0.0705 | Z34: -0.0735
B35: Franklin India (A) | C35: LU0231203729 | D35: Franklin Templeton Investments | E35: Internacional Ações Não Hedgeado | F35: Equity | G35: India | H35: India Equity | I35: US Dollar | J35: ★★★★ | K35: MSCI India NR USD | L35: 38649 | M35: 1000 | N35: 1000 | O35: T + 4 | P35: 0.0182 | Q35: 0.015 | R35: 0 | S35: 0.0025 | T35: Luxembourg | U35: SICAV | V35: -0.002079 | W35: -0.1476768 | X35: 0.1477 | Y35: 0.2687 | Z35: -0.1155
B36: Franklin Templeton Brandywine Global Income Optimiser (A) | C36: IE00BBT3JP45 | D36: Brandywine Global Investment Mgmt, LLC | E36: Internacional Renda Fixa Não Hedgeado | F36: Fixed Income | G36: Global | H36: Global Fixed Income | I36: US Dollar | J36: ★★★ | K36: Bloomberg Multiverse TR Hdg USD | L36: 41515 | M36: 1000 | N36: 0 | O36: T + 4 | P36: 0.0138 | Q36: 0.011 | R36: 0 | S36: 0.0025 | T36: Ireland | U36: Open Ended Investment Company | V36: 0.0009835 | W36: 0.0172586 | X36: 0.0147 | Y36: 0.0722 | Z36: -0.1459
B37: Franklin Templeton High Yield (A) | C37: LU0131126228 | D37: Franklin Templeton Invts | E37: Internacional Renda Fixa Não Hedgeado | F37: Fixed Income | G37: United States of America | H37: US Fixed Income | I37: US Dollar | J37: ★★★ | K37: ICE BofA US HY Constnd TR USD | L37: 37073 | M37: 1000 | N37: 1000 | O37: T + 4 | P37: 0.0145 | Q37: 0.011 | R37: 0 | S37: 0.002 | T37: Luxembourg | U37: SICAV | V37: 0.0015692 | W37: 0.0118906 | X37: 0.0755 | Y37: 0.1255 | Z37: -0.1053
B38: FTGF Brandywine Global High Yield Fund (A) | C38: IE00BBM55T37 | D38: Brandywine Global Investment Mgmt, LLC | E38: Internacional Ações Hedgeado | F38: Fixed Income | G38: Global | H38: Global Fixed Income | I38: US Dollar | J38: ★★★ | K38: ICE BofA Global High Yield TR USD | L38: 41243 | M38: 1000 | N38: 1000 | O38: T + 4 | P38: 0.014 | Q38: 0.011 | R38: 0 | S38: 0.00375 | T38: Ireland | U38: Open Ended Investment Company | V38: 0.0004744 | W38: 0.0026489 | X38: 0.0819 | Y38: 0.1399 | Z38: -0.1258
B39: FTGF ClearBridge Infrastructure Value (A) | C39: IE00BD4GTV84 | D39: ClearBridge Investments, LLC. | E39: Internacional Ações Não Hedgeado | F39: Equity | G39: Global | H39: Infrastructure Sector Equity | I39: US Dollar | K39: FTSE Global Core Infra 50/50 TR EUR | L39: 42809 | M39: 1000 | N39: 0 | O39: T + 4 | P39: 0.0197 | Q39: 0.015 | R39: 0 | S39: 0.00375 | T39: Ireland | U39: Open Ended Investment Company | V39: -0.0064995 | W39: 0.1174935 | X39: 0.12 | Y39: 0.0424 | Z39: 0.0293
B40: FTGF ClearBridge US Large Cap Growth (A) | C40: IE00B19Z9505 | D40: ClearBridge Investments, LLC. | E40: Internacional Ações Não Hedgeado | F40: Equity | G40: United States of America | H40: US Equity Large Cap Growth | I40: US Dollar | J40: ★★★ | K40: Russell 1000 Growth TR USD | L40: 39191 | M40: 1000 | N40: 0 | O40: T + 4 | P40: 0.0171 | Q40: 0.0125 | R40: 0 | S40: 0.00375 | T40: Ireland | U40: Open Ended Investment Company | V40: 0.0028439 | W40: -0.0018663 | X40: 0.2569 | Y40: 0.4252 | Z40: -0.3288
B41: FTGF Franklin Ultra Short Duration Acc | C41: IE0000KQO741 | D41: Franklin Advisers, Inc. | E41: Internacional Renda Fixa Não Hedgeado | F41: Fixed Income | G41: United States of America | H41: US Fixed Income | I41: US Dollar | K41: ICE BofA US Treasury Bill TR USD | L41: 04/042025 | M41: 1000 | N41: - | O41: T + 4 | P41: 0 | Q41: 0.008 | R41: 0 | S41: 0.0025 | T41: Ireland | U41: Open Ended Investment Company | V41: 0.000288 | W41: 0.0092978
B42: Janus Henderson Balanced (A2) | C42: IE0004445015 | D42: Janus Henderson Investors | E42: Internacional Multimercado Não Hedgeado | F42: Allocation | G42: United States of America | H42: Moderate Allocation | I42: US Dollar | J42: ★★★★★ | K42: Bloomberg US Agg Bond TR USD [40.00%]; S&P 500 TR USD [60.00%] | L42: 36152 | M42: 2500 | N42: 100 | O42: T + 4 | P42: 0.0188 | Q42: 0.01 | R42: 0 | S42: 0.00375 | T42: Ireland | U42: Open Ended Investment Company | V42: -0.0003872 | W42: 0.0058445 | X42: 0.1366 | Y42: 0.1361 | Z42: -0.1757
B43: Janus Henderson Global Real Estate Equity Income (A2) | C43: IE0033534557 | D43: Janus Henderson Investors | E43: Internacional Ações Não Hedgeado | F43: Equity | G43: Global | H43: Real Estate Sector Equity | I43: US Dollar | J43: ★★★★ | K43: FTSE EPRA Nareit Global REITs NR USD | L43: 37892 | M43: 2500 | N43: 100 | O43: T + 4 | P43: 0.0218 | Q43: 0.0125 | R43: 0 | S43: 0.00375 | T43: Ireland | U43: Open Ended Investment Company | V43: -0.0021684 | W43: 0.0840204 | X43: 0.034 | Y43: 0.077 | Z43: -0.2309
